Workbook

Sheet Leeme
A1: Tablero de validación: IPS Salud y Vida
A3: Para qué es | B3: Validar, entre los cuatro y en línea, el anexo técnico de la Resolución 866 de 2021 contra las 33 historias entregadas, antes de mover cambios a Trello. Trello sigue siendo el backlog que evalúa el docente; este archivo es el lugar de trabajo.
A4: Un solo archivo | B4: Se trabaja solo en línea, en este enlace. Nadie descarga, edita en su equipo y vuelve a subir: eso pisa el trabajo de los demás.
A5: Colores de columna | B5: Encabezado gris oscuro y celdas grises: referencia, no se edita. Encabezado azul y celdas amarillas: se llenan. Encabezado gris medio: fórmulas, no se tocan.
A6: Fuente que manda | B6: El PDF del anexo, hojas 13 a 25. Las columnas "referencia" de la hoja Validación son una transcripción hecha con IA: sirven para guiarse, y si no coinciden con la hoja del PDF, manda la hoja.
A7: Ajustes al prompt | B7: Antes de analizar cualquier fila, leer la hoja Ajustes al prompt, que es el mismo texto del archivo ajustes-prompt-v2.1.md. Aplican a todos los bloques desde el 2026-10-18 y mandan sobre el prompt v2.1 donde choquen.
A8: Protocolo | B8: 1. Para tomar una fila: primero tu nombre en Responsable, después Estado en "En análisis". La columna "¿Se puede tomar?" cambia sola.
B9: 2. Al terminar: Estado en "Analizado", con Fuente del análisis y Detalle de la fuente llenos. La fila queda como "Lista para revisar".
B10: 3. Otra persona revisa contra el PDF, se pone como Revisor y cambia el Estado a "Aprobado". Nadie aprueba lo suyo: la columna Alerta lo marca.
B11: 4. Solo lo aprobado pasa a Trello. El comentario de la tarjeta copia la fuente y la fecha de la fila, y aquí se anota el ID en Trello con Estado "En Trello".
B12: Si falta una decisión del equipo para seguir: Estado "Bloqueado" y en "Bloqueada por" el número de la hoja Decisiones, por ejemplo D-02.
A14: Ejemplo de fila tomada | B14: Responsable: Juliana · Estado: En análisis · Fuente del análisis: Hoja del PDF del anexo · Detalle de la fuente: hoja 15, fila del elemento 12 · Fecha de inicio: 2026-10-18
A15: Estado al 2026-10-20 | B15: Al 2026-10-20 las 28 filas de Validación y las 33 historias están analizadas por Juan Fernando con apoyo de un modelo. V-18 queda bloqueada por D-05. La revisión la hace otra persona: Revisor distinto de Responsable. Criterio de la columna L: “Sí” solo si las columnas F a K coinciden con la hoja letra por letra, salvo separadores; una paráfrasis o una tilde distinta cuenta como diferencia. Una revisión independiente cotejó las 28 filas contra las hojas 13 a 18. Resumen de entidades y conteo de historias en la hoja Entidades. Los elementos 24 a 49 no están en el tablero: dependen de D-16. Las celdas L2:L22 se habían llenado por arrastre y se rehicieron contra las hojas del PDF. Retroalimentación: los 63 comentarios del docente de HU-001 a HU-030, de la exportación de Trello del 19 oct 2026; HU-031 a HU-033 no están en esa exportación. Ajustes por historia en lenguaje simple: cada historia remite al numeral del anexo en vez de copiar formatos.
A16: Reparto sugerido | B16: Todas las filas están analizadas por Juan Fernando. Cada integrante toma un bloque como Revisor (columna Z), contra el PDF, y cambia el Estado a Aprobado o lo devuelve. Bloque A, elementos 1 a 6 · Bloque B, 7 a 12 · Bloque C, 13 a 18 · Bloque D, 19 a 23. Las historias se revisan con la hoja Ajustes por historia.
A17: El mapa | B17: mapa-anexo-vs-backlog.md se abre cuando cada uno termine su bloque, para comparar. Antes de eso condiciona la validación.
A19: Hojas | B19: Validación: una fila por componente del anexo. Historias: las 33 entregadas, texto sin cambios. Por redactar: IDs reservados para las historias que falten. Decisiones: lo que el equipo debe acordar. Retroalimentación: los textos del docente tal como llegaron. Escenarios: los criterios BDD de las 33. Reglas comunes: RC-1 a RC-11 (RC-6 a RC-11 son del backlog v3). Ajustes por historia: una fila por historia y fila de validación; los ajustes van ahí y no en la hoja Historias, para que dos bloques no escriban en la misma celda. Ajustes al prompt: correcciones al prompt v2.1. Entidades: cada entidad con su regla, sus historias existentes y nuevas, y el total del backlog según D-17. Historias, columnas R a T: resultado y resumen por historia; el detalle por escenario sigue en Ajustes por historia. Anexo 1 a 49: una fila por componente de los 49 elementos, con lo que cubre este backlog, lo que cubren los compañeros y lo que falta; del 24 al 49 la clasificación es preliminar (D-16). Backlog v3: las 30 historias del plan de reescritura, con su origen, su tanda, su estado y el archivo de su borrador (carpeta backlog-v3); las hojas Ajustes por historia y Retroalimentación dicen a qué historia del v3 va cada fila.
A21: Avance | B21: Cantidad
A22: Validación: libres | B22: =COUNTIF(Validación!T:T,"Libre") -> 0
A23: Validación: en análisis | B23: =COUNTIF(Validación!T:T,"En análisis") -> 0
A24: Validación: analizadas | B24: =COUNTIF(Validación!T:T,"Analizado") -> 27
A25: Validación: en revisión | B25: =COUNTIF(Validación!T:T,"En revisión") -> 0
A26: Validación: aprobadas | B26: =COUNTIF(Validación!T:T,"Aprobado") -> 0
A27: Validación: bloqueadas | B27: =COUNTIF(Validación!T:T,"Bloqueado") -> 1
A28: Validación: filas con alerta | B28: =COUNTIF(Validación!V2:V200,"?*") -> 0
A29: Historias: filas con alerta | B29: =COUNTIF(Historias!X2:X200,"?*") -> 0
A30: Historias: resultado Cumple | B30: =COUNTIF(Historias!R:R,"Cumple") -> 0
A31: Historias: resultado Ajustar | B31: =COUNTIF(Historias!R:R,"Ajustar") -> 33
A32: Historias: resultado Sobra | B32: =COUNTIF(Historias!R:R,"Sobra") -> 0
A33: Historias: libres | B33: =COUNTIF(Historias!V:V,"Libre") -> 0
A34: Historias: aprobadas o en Trello | B34: =COUNTIF(Historias!V:V,"Aprobado")+COUNTIF(Historias!V:V,"En Trello") -> 0
A35: Historias por redactar en uso | B35: =COUNTA('Por redactar'!C:C)-1 -> 0
A36: Decisiones pendientes | B36: =COUNTIF(Decisiones!E:E,"Pendiente") -> 27
A37: Ajustes por historia: filas | B37: =COUNTA('Ajustes por historia'!A:A)-1 -> 104
A38: Total de historias si D-17 = una por operación | B38: =Entidades!H23 -> 69
A39: Total de historias si D-17 = una por entidad | B39: =Entidades!I23 -> 24

Sheet Ajustes al prompt
A1: N.º | B1: Ajuste al prompt v2.1 (2026-10-18). Mismo texto que ajustes-prompt-v2.1.md
A2: 1 | B2: Umbral. El numeral 2.3 dice "más de 5 opciones seleccionables" y la revisión General del docente lo repite ("campos con más de cinco opciones"). Usa más de 5. Una lista de exactamente 5 valores es campo, y en Observaciones escribe "Depende de D-01".
A3: 2 | B3: Reutilizar va antes de las preguntas 2 y 3. Si otro componente usa el mismo catálogo, la entidad es de la fila con el número V más bajo; las demás filas se clasifican "Reutiliza otra entidad" y no proponen historias. Ejemplo: V-01 crea Países y V-12 la reutiliza.
A4: 3 | B4: El numeral 2.1 de la guía tiene 7 filas, no 2. Además de las dos estructuras separadas: un paciente puede tener más de un país de nacionalidad; la fecha de nacimiento se separa de la hora; la ocupación solo admite las ocupaciones hijas del CIUO-88 AC; un paciente puede registrar más de una discapacidad; la ciudad de residencia se registra con su código DANE. Cada una da al menos un escenario en las historias del paciente; HU-004 a HU-006 ya las tienen.
A5: 4 | B5: Escenarios que le faltan a la tabla del prompt: dato con varios valores (se aceptan dos o más); catálogo donde solo se eligen hijas (una categoría padre se rechaza); fecha con longitud mínima 10 y máxima 16 (la hora puede faltar); código con cero inicial ("1" en vez de "01" se rechaza por la longitud mínima).
A6: 5 | B6: Tipos (propuesta D-18). Cada componente se guarda con el tipo de la columna Tipo de la hoja: Alfanumérico es texto de la longitud indicada, aunque sus valores se vean como cifras; Numérico es entero; Fecha es fecha y hora. En los elementos 1 a 23 todos los códigos son Alfanumérico.
A7: 6 | B7: Los datos de los elementos 16 a 23 son de la atención (el contacto con el servicio de salud), no de la historia clínica. Si el componente es campo, en Entidad escribe "Atención". Si es catálogo, la atención guarda el código que apunta a él.
A8: 7 | B8: Catálogos y artículo 7 de la Resolución 866: los catálogos "no podrán ser modificados, reducidos o adicionados". El CRUD que pide el numeral 2.3 crea y actualiza solo para reflejar el catálogo oficial, con su fuente y versión. El llenado inicial de catálogos grandes (CIE-10, DIVIPOLA, CIUO-88, ISO 3166-1) es tarea técnica del equipo, no historia de usuario. No uses "cargar" en una historia.
A9: 8 | B9: El nombre que corresponde a un código va en la misma entidad que el código y no es texto libre. Solo los elementos 1, 7, 11, 12, 15 y 23 traen el nombre como componente propio (Alfanumérico, máximo 200, mínimo 3); en los demás, los nombres están solo dentro de los valores permitidos.
A10: 9 | B10: RC-3 dice "sincronizada". No copies esa palabra en una historia; escribe "PENDIENTE reescribir RC-3".
A11: 10 | B11: Historias nuevas: en la columna "Historias nuevas propuestas" escribe "4 historias; IDs en espera de D-17". No reserves IDs en Por redactar hasta que se decida D-17 (una historia por operación del CRUD o una por entidad).
A12: 11 | B12: Los ajustes a historias existentes van a la hoja "Ajustes por historia", una fila por historia y fila de validación. No escribas en la columna Resultado de la hoja Historias: se consolida al final.
A13: 12 | B13: El prestador (elementos 9 y 16) depende de D-05. Mientras esté Pendiente, clasifícalo "Pendiente de decisión".
... A16: 15 | B16: Las filas V-22 a V-26 (bloque D) ya están analizadas. Sirven de ejemplo del formato de las columnas, no de la clasificación de otros bloques.

Sheet Validación
A1: Fila | B1: Bloque | C1: Elemento | D1: Componente | E1: Hoja del PDF | F1: Valores (referencia) | G1: N.º de valores (referencia) | H1: Tipo (referencia) | I1: Formato (referencia) | J1: Long. máx. (referencia) | K1: Long. mín. (referencia) | L1: ¿Transcripción confirmada contra el PDF? | M1: N.º de valores contado en el PDF | N1: Clasificación | O1: Entidad | P1: Pregunta del prompt que decidió (1 a 5) | Q1: Historias existentes que lo cubren | R1: Historias nuevas propuestas | S1: Responsable | T1: Estado | U1: ¿Se puede tomar? | V1: Alerta | W1: Fuente del análisis | X1: Detalle de la fuente | Y1: Bloqueada por | Z1: Revisor | AA1: Fecha de inicio | AB1: Fecha de cierre | AC1: Observaciones y diferencias
A2: V-01 | B2: A | C2: 1 | D2: Código y nombre del país de nacionalidad | E2: 13 | F2: Código a tres caracteres según estándar ISO 3166-1. Nombre correspondiente al código | G2: El anexo no los enumera | H2: Alfanumérico | I2: 999 / sin formato | J2: 3 / 200 | K2: 3 / 3 | L2: No: hay diferencias | M2: No los enumera | N2: Entidad por 2.3 | O2: Países | P2: 2 | Q2: HU-018 a HU-021 cubren el CRUD (Ajustar). HU-004 a HU-006 usan el dato; los escenarios de varias nacionalidades cumplen. | R2: ninguna | S2: Juan Fernando | T2: Analizado | U2: =IF(OR(T2="",T2="Libre"),"Disponible",IF(T2="Bloqueado","Bloqueada: "&IF(Y2="","falta motivo",Y2),IF(OR(T2="Aprobado",T2="En Trello"),"Cerrada",IF(T2="En revisión","En revisión: "&IF(Z2="","falta revisor",Z2),IF(T2="Analizado","Lista para revisar: analizó "&IF(S2="","falta responsable",S2),IF(S2="","Falta responsable","Ocupada por "&S2)))))) -> Lista para revisar: analizó Juan Fernando | V2: =IF(AND(Z2<>"",Z2=S2),"El revisor no puede ser el responsable",IF(AND(OR(T2="Analizado",T2="En revisión",T2="Aprobado"),W2=""),"Falta la fuente del análisis",IF(AND(OR(T2="Aprobado",T2="En Trello"),Z2=""),"Aprobado sin revisor",""))) | W2: Prompt con IA | X2: Hoja 13, elemento 1: código ISO 3166-1 (alfanumérico, 999, 3 y 3) y nombre (alfanumérico, 200 y 3). Numeral 2.1: más de un país de nacionalidad. Numeral 2.3: catálogo externo. | AA2: 46315 | AC2: La hoja 13 deja vacíos los valores permitidos del nombre del país; la referencia escribe “Nombre correspondiente al código”. Coinciden tipos, formatos y longitudes. Código ISO 3166-1 de 3 caracteres, alfabético o numérico: PENDIENTE D-03. Varias nacionalidades por paciente (2.1): relación de muchos a muchos entre paciente y país. Fuente y versión del catálogo: PENDIENTE D-21. Carga desde el archivo oficial: funcionalidad de la historia del catálogo (el docente la da por funcional).
A3: V-02 | B3: A | C3: 2 | D3: Tipo de documento de identificación | E3: 13 | F3: CC Cédula ciudadanía · CE Cédula de extranjería · CD Carné diplomático · PA Pasaporte · SC Salvoconducto de permanencia · PT Permiso Temporal de Permanencia · PE Permiso Especial de Permanencia · RC Registro civil · TI Tarjeta de identidad · CN Certificado de nacido vivo · AS Adulto sin identificar · MS Menor sin identificar · DE Documento extranjero · SI Sin identificación | G3: 14 | H3: Alfanumérico | I3: 99 | J3: 2 | K3: 2 | L3: Sí | M3: 14 | N3: Entidad por 2.3 | O3: Tipos de documento de identificación | P3: 3 | Q3: Ninguna cubre el CRUD. HU-004 a HU-006 usan el dato (Ajustar). | R3: 4 historias; IDs en espera de D-17 | S3: Juan Fernando | T3: Analizado | U3: =IF(OR(T3="",T3="Libre"),"Disponible",IF(T3="Bloqueado","Bloqueada: "&IF(Y3="","falta motivo",Y3),IF(OR(T3="Aprobado",T3="En Trello"),"Cerrada",IF(T3="En revisión","En revisión: "&IF(Z3="","falta revisor",Z3),IF(T3="Analizado","Lista para revisar: analizó "&IF(S3="","falta responsable",S3),IF(S3="","Falta responsable","Ocupada por "&S3)))))) -> Lista para revisar: analizó Juan Fernando | V3: =IF(AND(Z3<>"",Z3=S3),"El revisor no puede ser el responsable",IF(AND(OR(T3="Analizado",T3="En revisión",T3="Aprobado"),W3=""),"Falta la fuente del análisis",IF(AND(OR(T3="Aprobado",T3="En Trello"),Z3=""),"Aprobado sin revisor",""))) | W3: Prompt con IA | X3: Hoja 13, elemento 2: 14 valores, alfanumérico, formato 99, longitud 2 y 2. Numeral 2.3: más de 5 opciones. Retroalimentación HU-004: clave del duplicado por tipo y número. | AA3: 46315 | AC3: Coinciden los 14 valores, tipo, formato y longitudes. Clave de paciente duplicado: tipo y número de documento, PENDIENTE D-07. Cargo que mantiene el catálogo: PENDIENTE D-02. Representación del código: PENDIENTE D-18.
A4: V-03 | B4: A | C4: 2 | D4: Número de documento de identificación | E4: 13 | F4: Conjunto de caracteres asignados a una persona de acuerdo con el tipo de documento | G4: No aplica: dato abierto | H4: Alfanumérico | I4: sin formato | J4: 20 | K4: 3 | L4: No: hay diferencias | M4: No aplica | N4: Campo del paciente | O4: Paciente | P4: 5 | Q4: HU-004, HU-005, HU-006 (Ajustar). | R4: ninguna | S4: Juan Fernando | T4: Analizado | U4: =IF(OR(T4="",T4="Libre"),"Disponible",IF(T4="Bloqueado","Bloqueada: "&IF(Y4="","falta motivo",Y4),IF(OR(T4="Aprobado",T4="En Trello"),"Cerrada",IF(T4="En revisión","En revisión: "&IF(Z4="","falta revisor",Z4),IF(T4="Analizado","Lista para revisar: analizó "&IF(S4="","falta responsable",S4),IF(S4="","Falta responsable","Ocupada por "&S4)))))) -> Lista para revisar: analizó Juan Fernando | V4: =IF(AND(Z4<>"",Z4=S4),"El revisor no puede ser el responsable",IF(AND(OR(T4="Analizado",T4="En revisión",T4="Aprobado"),W4=""),"Falta la fuente del análisis",IF(AND(OR(T4="Aprobado",T4="En Trello"),Z4=""),"Aprobado sin revisor",""))) | W4: Prompt con IA | X4: Hoja 13, elemento 2: número de documento, alfanumérico, longitud 20 y 3, dato abierto. | AA4: 46315 | AC4: La referencia abrevia el texto de la hoja (“…para efectos de identidad e individualización dentro del territorio nacional”). Dato abierto de 3 a 20 caracteres alfanuméricos. Con el tipo forma la clave del duplicado (D-07).
A5: V-04 | B5: A | C5: 3 | D5: Primer apellido, segundo apellido, primer nombre, segundo nombre | E5: 13 | F5: Según el documento de identificación | G5: No aplica: dato abierto | H5: Alfanumérico | I5: sin formato | J5: 60 cada uno | K5: 2 cada uno | L5: No: hay diferencias | M5: No aplica | N5: Campo del paciente | O5: Paciente | P5: 5 | Q5: HU-004, HU-005, HU-006 (Ajustar). | R5: ninguna | S5: Juan Fernando | T5: Analizado | U5: =IF(OR(T5="",T5="Libre"),"Disponible",IF(T5="Bloqueado","Bloqueada: "&IF(Y5="","falta motivo",Y5),IF(OR(T5="Aprobado",T5="En Trello"),"Cerrada",IF(T5="En revisión","En revisión: "&IF(Z5="","falta revisor",Z5),IF(T5="Analizado","Lista para revisar: analizó "&IF(S5="","falta responsable",S5),IF(S5="","Falta responsable","Ocupada por "&S5)))))) -> Lista para revisar: analizó Juan Fernando | V5: =IF(AND(Z5<>"",Z5=S5),"El revisor no puede ser el responsable",IF(AND(OR(T5="Analizado",T5="En revisión",T5="Aprobado"),W5=""),"Falta la fuente del análisis",IF(AND(OR(T5="Aprobado",T5="En Trello"),Z5=""),"Aprobado sin revisor",""))) | W5: Prompt con IA | X5: Hoja 13, elemento 3: primer y segundo apellido, primer y segundo nombre, alfanumérico, longitud 60 y 2 cada uno. | AA5: 46315 | AC5: Cuatro componentes con los mismos límites: 2 a 60 caracteres. Que se acepten tildes, ñ y espacios es un supuesto a confirmar con el equipo. Cuáles son obligatorios (el segundo nombre y el segundo apellido pueden no existir): PENDIENTE D-19. La hoja escribe “De acuerdo como se especifica en el documento de identificación”; la referencia, “Según el documento de identificación”.
A6: V-05 | B6: A | C6: 4 | D6: Fecha y hora de nacimiento | E6: 13 | F6: Según el documento de identificación o como la declare el individuo | G6: No aplica: dato abierto | H6: Fecha | I6: AAAA-MM-DD HH:MM | J6: 16 | K6: 10 | L6: No: hay diferencias | M6: No aplica | N6: Campo del paciente | O6: Paciente | P6: 5 | Q6: HU-004, HU-005, HU-006. Los escenarios de fecha separada de la hora y de hora faltante cumplen; faltan los de formato (Ajustar). | R6: ninguna | S6: Juan Fernando | T6: Analizado | U6: =IF(OR(T6="",T6="Libre"),"Disponible",IF(T6="Bloqueado","Bloqueada: "&IF(Y6="","falta motivo",Y6),IF(OR(T6="Aprobado",T6="En Trello"),"Cerrada",IF(T6="En revisión","En revisión: "&IF(Z6="","falta revisor",Z6),IF(T6="Analizado","Lista para revisar: analizó "&IF(S6="","falta responsable",S6),IF(S6="","Falta responsable","Ocupada por "&S6)))))) -> Lista para revisar: analizó Juan Fernando | V6: =IF(AND(Z6<>"",Z6=S6),"El revisor no puede ser el responsable",IF(AND(OR(T6="Analizado",T6="En revisión",T6="Aprobado"),W6=""),"Falta la fuente del análisis",IF(AND(OR(T6="Aprobado",T6="En Trello"),Z6=""),"Aprobado sin revisor",""))) | W6: Prompt con IA | X6: Hoja 13, elemento 4: Fecha, AAAA-MM-DD HH:MM, longitud 16 y 10. Numeral 2.1: separar fecha y hora. Retroalimentación HU-004 ampliada: fecha sin hora compatible con la mínima de 10. | AA6: 46315 | AC6: La mínima de 10 permite la fecha sin hora; el numeral 2.1 pide separar fecha y hora: dos campos del paciente. Se guarda como fecha y hora: PENDIENTE D-18. La hoja escribe “De acuerdo como se especifica” donde la referencia escribe “Según”.
A7: V-06 | B7: A | C7: 5 | D7: Sexo biológico | E7: 13 | F7: 01 Hombre · 02 Mujer · 03 Indeterminado/Intersexual | G7: 3 | H7: Alfanumérico | I7: 99 | J7: 2 | K7: 2 | L7: Sí | M7: 3 | N7: Campo del paciente | O7: Paciente | P7: 5 | Q7: HU-004, HU-005, HU-006 (Ajustar). | R7: ninguna | S7: Juan Fernando | T7: Analizado | U7: =IF(OR(T7="",T7="Libre"),"Disponible",IF(T7="Bloqueado","Bloqueada: "&IF(Y7="","falta motivo",Y7),IF(OR(T7="Aprobado",T7="En Trello"),"Cerrada",IF(T7="En revisión","En revisión: "&IF(Z7="","falta revisor",Z7),IF(T7="Analizado","Lista para revisar: analizó "&IF(S7="","falta responsable",S7),IF(S7="","Falta responsable","Ocupada por "&S7)))))) -> Lista para revisar: analizó Juan Fernando | V7: =IF(AND(Z7<>"",Z7=S7),"El revisor no puede ser el responsable",IF(AND(OR(T7="Analizado",T7="En revisión",T7="Aprobado"),W7=""),"Falta la fuente del análisis",IF(AND(OR(T7="Aprobado",T7="En Trello"),Z7=""),"Aprobado sin revisor",""))) | W7: Prompt con IA | X7: Hoja 13, elemento 5: 3 valores, alfanumérico, formato 99, longitud 2 y 2. Numeral 2.3: no llega a más de 5 opciones. | AA7: 46315 | AC7: Lista de 3 valores. Campo del paciente. Se guarda como texto de 2 caracteres: PENDIENTE D-18.
A8: V-07 | B8: A | C8: 6 | D8: Identidad de género | E8: 14 | F8: 01 Masculino · 02 Femenino · 03 Transgénero · 04 Neutro · 05 No lo declara | G8: 5 | H8: Alfanumérico | I8: 99 | J8: 2 | K8: 2 | L8: Sí | M8: 5 | N8: Campo del paciente | O8: Paciente | P8: 5 | Q8: HU-004, HU-005, HU-006 (Ajustar). | R8: ninguna | S8: Juan Fernando | T8: Analizado | U8: =IF(OR(T8="",T8="Libre"),"Disponible",IF(T8="Bloqueado","Bloqueada: "&IF(Y8="","falta motivo",Y8),IF(OR(T8="Aprobado",T8="En Trello"),"Cerrada",IF(T8="En revisión","En revisión: "&IF(Z8="","falta revisor",Z8),IF(T8="Analizado","Lista para revisar: analizó "&IF(S8="","falta responsable",S8),IF(S8="","Falta responsable","Ocupada por "&S8)))))) -> Lista para revisar: analizó Juan Fernando | V8: =IF(AND(Z8<>"",Z8=S8),"El revisor no puede ser el responsable",IF(AND(OR(T8="Analizado",T8="En revisión",T8="Aprobado"),W8=""),"Falta la fuente del análisis",IF(AND(OR(T8="Aprobado",T8="En Trello"),Z8=""),"Aprobado sin revisor",""))) | W8: Prompt con IA | X8: Hoja 14, elemento 6: 5 valores, alfanumérico, formato 99, longitud 2 y 2. Numeral 2.3: no llega a más de 5 opciones. D-01. | AA8: 46315 | AC8: Lista de exactamente 5 valores. Depende de D-01: si el umbral pasa a 5 o más, cambia a Entidad por 2.3 con 4 historias nuevas.
A9: V-08 | B9: B | C9: 7 | D9: Código y nombre de la ocupación | E9: 14 | F9: Catálogo CIUO-88 A.C., Clasificación Internacional Uniforme de Ocupaciones Adaptada para Colombia por el DANE. Nombre correspondiente al código | G9: El anexo no los enumera | H9: Alfanumérico | I9: 9999 / sin formato | J9: 4 / 200 | K9: 4 / 3 | L9: Sí | M9: No los enumera | N9: Entidad por 2.3 | O9: Ocupaciones | P9: 2 | Q9: HU-022 a HU-025 cubren el CRUD (Ajustar). HU-004 a HU-006 usan el dato; los escenarios de solo ocupaciones hijas cumplen. | R9: ninguna | S9: Juan Fernando | T9: Analizado | U9: =IF(OR(T9="",T9="Libre"),"Disponible",IF(T9="Bloqueado","Bloqueada: "&IF(Y9="","falta motivo",Y9),IF(OR(T9="Aprobado",T9="En Trello"),"Cerrada",IF(T9="En revisión","En revisión: "&IF(Z9="","falta revisor",Z9),IF(T9="Analizado","Lista para revisar: analizó "&IF(S9="","falta responsable",S9),IF(S9="","Falta responsable","Ocupada por "&S9)))))) -> Lista para revisar: analizó Juan Fernando | V9: =IF(AND(Z9<>"",Z9=S9),"El revisor no puede ser el responsable",IF(AND(OR(T9="Analizado",T9="En revisión",T9="Aprobado"),W9=""),"Falta la fuente del análisis",IF(AND(OR(T9="Aprobado",T9="En Trello"),Z9=""),"Aprobado sin revisor",""))) | W9: Prompt con IA | X9: Hoja 14, elemento 7: código CIUO-88 A.C. (alfanumérico, 9999, 4 y 4) y nombre (200 y 3). Numeral 2.1: solo ocupaciones hijas. Numeral 2.3: catálogo externo. | AA9: 46315 | AC9: Código de exactamente 4 caracteres: solo se asocian ocupaciones de ese nivel, coherente con “solo las ocupaciones hijas” del 2.1. Que la CIUO-88 A.C. tenga niveles de 1 a 3 caracteres por encima es inferencia del modelo, no está en la hoja. Fuente y versión del catálogo: PENDIENTE D-21. Carga desde el archivo oficial: funcionalidad de la historia del catálogo (el docente la da por funcional).
A10: V-09 | B10: B | C10: 8 | D10: Manifestación de oposición a la presunción legal de donación, y fecha del documento | E10: 14 | F10: 01 Sí · 02 No. Fecha en que se suscribe el documento válido ante el INS o la entidad administradora del plan de beneficios | G10: 2 | H10: Alfanumérico / Fecha | I10: 99 / AAAA-MM-DD | J10: 2 / 10 | K10: 2 / 10 | L10: No: hay diferencias | M10: 2 | N10: Entidad por 2.1 | O10: Oposición a la presunción legal de donación | P10: 1 | Q10: HU-010 a HU-013 (Ajustar). | R10: ninguna | S10: Juan Fernando | T10: Analizado | U10: =IF(OR(T10="",T10="Libre"),"Disponible",IF(T10="Bloqueado","Bloqueada: "&IF(Y10="","falta motivo",Y10),IF(OR(T10="Aprobado",T10="En Trello"),"Cerrada",IF(T10="En revisión","En revisión: "&IF(Z10="","falta revisor",Z10),IF(T10="Analizado","Lista para revisar: analizó "&IF(S10="","falta responsable",S10),IF(S10="","Falta responsable","Ocupada por "&S10)))))) -> Lista para revisar: analizó Juan Fernando | V10: =IF(AND(Z10<>"",Z10=S10),"El revisor no puede ser el responsable",IF(AND(OR(T10="Analizado",T10="En revisión",T10="Aprobado"),W10=""),"Falta la fuente del análisis",IF(AND(OR(T10="Aprobado",T10="En Trello"),Z10=""),"Aprobado sin revisor",""))) | W10: Prompt con IA | X10: Hoja 14, elemento 8: manifestación (01 Sí, 02 No; alfanumérico, 99, 2 y 2) y fecha de suscripción del documento (Fecha, AAAA-MM-DD, 10 y 10). Numeral 2.1: estructura separada (CRUD). | AA10: 46315 | AC10: Estructura separada por el 2.1. La fecha es la de suscripción del documento válido ante el Instituto Nacional de Salud o la Entidad Administradora del Plan de Beneficios; HU-010 escenario 4 usa otra fecha. Eliminar como inactivación: PENDIENTE D-20. Hoja 14: “01: Si”, sin tilde; la referencia escribe “Sí” y abrevia “Instituto Nacional de Salud” como “INS”.
A11: V-10 | B11: B | C11: 9 | D11: Documento de voluntad anticipada, fecha y código del prestador donde se encuentra | E11: 14 | F11: 01 Sí · 02 No. Fecha de suscripción, modificación, sustitución o revocación. Código del prestador donde se encuentra el documento | G11: 2 | H11: Alfanumérico / Fecha / Alfanumérico | I11: 99 / AAAA-MM-DD / 999999999999 | J11: 2 / 10 / 12 | K11: 2 / 10 / 12 | L11: No: hay diferencias | M11: 2 | N11: Entidad por 2.1 | O11: Documento de voluntad anticipada | P11: 1 | Q11: HU-014 a HU-017 (Ajustar). | R11: ninguna | S11: Juan Fernando | T11: Analizado | U11: =IF(OR(T11="",T11="Libre"),"Disponible",IF(T11="Bloqueado","Bloqueada: "&IF(Y11="","falta motivo",Y11),IF(OR(T11="Aprobado",T11="En Trello"),"Cerrada",IF(T11="En revisión","En revisión: "&IF(Z11="","falta revisor",Z11),IF(T11="Analizado","Lista para revisar: analizó "&IF(S11="","falta responsable",S11),IF(S11="","Falta responsable","Ocupada por "&S11)))))) -> Lista para revisar: analizó Juan Fernando | V11: =IF(AND(Z11<>"",Z11=S11),"El revisor no puede ser el responsable",IF(AND(OR(T11="Analizado",T11="En revisión",T11="Aprobado"),W11=""),"Falta la fuente del análisis",IF(AND(OR(T11="Aprobado",T11="En Trello"),Z11=""),"Aprobado sin revisor",""))) | W11: Prompt con IA | X11: Hoja 14, elemento 9: documento (01 Sí, 02 No; 99, 2 y 2), fecha de suscripción, modificación, sustitución o revocación (AAAA-MM-DD, 10 y 10) y código del prestador donde reposa (999999999999, 12 y 12). Numeral 2.1: estructura separada (CRUD). | AA11: 46315 | AC11: Estructura separada por el 2.1. La revocación es una actualización con su fecha, porque la hoja la pone en el mismo campo que la suscripción: resuelve el pendiente 2 de la tanda 3. El código del prestador depende de D-05. Si es catálogo, por el ajuste 2 lo propondría esta fila, la más baja; se deja en V-18, porque allí el código es el dato de la fila y aquí es un componente de la estructura. Eliminar como inactivación: PENDIENTE D-20. Hoja 14: “01: Si”, sin tilde; la referencia escribe “Sí”.
A12: V-11 | B12: B | C12: 10 | D12: Categoría de discapacidad | E12: 14 y 15 | F12: 01 Discapacidad física · 02 Discapacidad visual · 03 Discapacidad auditiva · 04 Discapacidad intelectual · 05 Discapacidad psicosocial (mental) · 06 Sordoceguera · 07 Discapacidad múltiple · 08 Sin discapacidad | G12: 8 | H12: Alfanumérico | I12: 99 | J12: 2 | K12: 2 | L12: No: hay diferencias | M12: 8 | N12: Entidad por 2.3 | O12: Categorías de discapacidad | P12: 3 | Q12: Ninguna cubre el CRUD. HU-004 a HU-006 usan el dato; los escenarios de varias discapacidades cumplen. | R12: 4 historias; IDs en espera de D-17 | S12: Juan Fernando | T12: Analizado | U12: =IF(OR(T12="",T12="Libre"),"Disponible",IF(T12="Bloqueado","Bloqueada: "&IF(Y12="","falta motivo",Y12),IF(OR(T12="Aprobado",T12="En Trello"),"Cerrada",IF(T12="En revisión","En revisión: "&IF(Z12="","falta revisor",Z12),IF(T12="Analizado","Lista para revisar: analizó "&IF(S12="","falta responsable",S12),IF(S12="","Falta responsable","Ocupada por "&S12)))))) -> Lista para revisar: analizó Juan Fernando | V12: =IF(AND(Z12<>"",Z12=S12),"El revisor no puede ser el responsable",IF(AND(OR(T12="Analizado",T12="En revisión",T12="Aprobado"),W12=""),"Falta la fuente del análisis",IF(AND(OR(T12="Aprobado",T12="En Trello"),Z12=""),"Aprobado sin revisor",""))) | W12: Prompt con IA | X12: Hojas 14 y 15, elemento 10: 8 valores, alfanumérico, formato 99, longitud 2 y 2. Numeral 2.1: más de una discapacidad. Numeral 2.3: más de 5 opciones. | AA12: 46315 | AC12: Hojas 14 y 15, valor 05: “Discapacidad sicosocial (mental)”, con el paréntesis en la hoja 15; la referencia escribe “psicosocial”. Coinciden conteo, tipo, formato y longitudes. Varias discapacidades por paciente (2.1): relación de muchos a muchos. La tanda 4a afirma que ningún campo del 2.1 pasa de 5 opciones: esta lista tiene 8. Cargo: PENDIENTE D-02.
A13: V-12 | B13: B | C13: 11 | D13: Código y nombre del país de residencia habitual | E13: 15 | F13: Código a tres caracteres según estándar ISO 3166-1. Nombre correspondiente al código | G13: El anexo no los enumera | H13: Alfanumérico | I13: 999 / sin formato | J13: 3 / 200 | K13: 3 / 3 | L13: Sí | M13: No los enumera | N13: Reutiliza otra entidad | O13: Países | P13: 4 | Q13: HU-018 a HU-021 (catálogo de países). HU-004 a HU-006 no nombran el país de residencia (Ajustar). | R13: ninguna | S13: Juan Fernando | T13: Analizado | U13: =IF(OR(T13="",T13="Libre"),"Disponible",IF(T13="Bloqueado","Bloqueada: "&IF(Y13="","falta motivo",Y13),IF(OR(T13="Aprobado",T13="En Trello"),"Cerrada",IF(T13="En revisión","En revisión: "&IF(Z13="","falta revisor",Z13),IF(T13="Analizado","Lista para revisar: analizó "&IF(S13="","falta responsable",S13),IF(S13="","Falta responsable","Ocupada por "&S13)))))) -> Lista para revisar: analizó Juan Fernando | V13: =IF(AND(Z13<>"",Z13=S13),"El revisor no puede ser el responsable",IF(AND(OR(T13="Analizado",T13="En revisión",T13="Aprobado"),W13=""),"Falta la fuente del análisis",IF(AND(OR(T13="Aprobado",T13="En Trello"),Z13=""),"Aprobado sin revisor",""))) | W13: Prompt con IA | X13: Hoja 15, elemento 11: código ISO 3166-1 (3 y 3) y nombre (200 y 3). Mismo catálogo que V-01. Ajuste 2 del prompt: la entidad es de la fila más baja. | AA13: 46315 | AC13: Mismo catálogo que V-01 (ISO 3166-1): no propone historias. Ninguna historia del paciente nombra hoy el país de residencia habitual.
A14: V-13 | B14: B | C14: 12 | D14: Código y nombre del municipio de residencia habitual | E14: 15 | F14: Código según DIVIPOLA del DANE: dos dígitos de departamento y tres de municipio. Nombre correspondiente al código | G14: El anexo no los enumera | H14: Alfanumérico | I14: 99999 / sin formato | J14: 5 / 200 | K14: 5 / 3 | L14: No: hay diferencias | M14: No los enumera | N14: Entidad por 2.3 | O14: Municipios | P14: 2 | Q14: HU-026 a HU-029 cubren el CRUD (Ajustar). HU-004 a HU-006 usan el dato; los escenarios de código DANE cumplen. | R14: ninguna | S14: Juan Fernando | T14: Analizado | U14: =IF(OR(T14="",T14="Libre"),"Disponible",IF(T14="Bloqueado","Bloqueada: "&IF(Y14="","falta motivo",Y14),IF(OR(T14="Aprobado",T14="En Trello"),"Cerrada",IF(T14="En revisión","En revisión: "&IF(Z14="","falta revisor",Z14),IF(T14="Analizado","Lista para revisar: analizó "&IF(S14="","falta responsable",S14),IF(S14="","Falta responsable","Ocupada por "&S14)))))) -> Lista para revisar: analizó Juan Fernando | V14: =IF(AND(Z14<>"",Z14=S14),"El revisor no puede ser el responsable",IF(AND(OR(T14="Analizado",T14="En revisión",T14="Aprobado"),W14=""),"Falta la fuente del análisis",IF(AND(OR(T14="Aprobado",T14="En Trello"),Z14=""),"Aprobado sin revisor",""))) | W14: Prompt con IA | X14: Hoja 15, elemento 12: código DIVIPOLA (alfanumérico, 99999, 5 y 5) y nombre (200 y 3). Numeral 2.1: ciudad con código DANE. Numeral 2.3: catálogo externo. | AA14: 46315 | AC14: Código DIVIPOLA de 5 caracteres: 2 del departamento y 3 del municipio (Medellín 05001; como entero pierde el 0). Supuesto: si la residencia habitual está fuera de Colombia, el municipio no aplica. Fuente y versión: PENDIENTE D-21. Carga desde el archivo oficial: funcionalidad de la historia del catálogo (el docente la da por funcional). La referencia parafrasea los valores permitidos; la hoja escribe “Código del municipio según División Política Administrativa”.
A15: V-14 | B15: C | C15: 13 | D15: Etnia | E15: 15 | F15: 01 Indígena · 02 ROM (Gitanos) · 03 Raizal (San Andrés y Providencia) · 04 Palenquero de San Basilio de Palenque · 05 Negro(a) · 06 Afrocolombiano(a) · 99 Ninguna de las anteriores | G15: 7 | H15: Alfanumérico | I15: 99 | J15: 2 | K15: 2 | L15: Sí | M15: 7 | N15: Entidad por 2.3 | O15: Etnias | P15: 3 | Q15: Ninguna cubre el CRUD. HU-004 a HU-006 no nombran el dato (Ajustar). | R15: 4 historias; IDs en espera de D-17 | S15: Juan Fernando | T15: Analizado | U15: =IF(OR(T15="",T15="Libre"),"Disponible",IF(T15="Bloqueado","Bloqueada: "&IF(Y15="","falta motivo",Y15),IF(OR(T15="Aprobado",T15="En Trello"),"Cerrada",IF(T15="En revisión","En revisión: "&IF(Z15="","falta revisor",Z15),IF(T15="Analizado","Lista para revisar: analizó "&IF(S15="","falta responsable",S15),IF(S15="","Falta responsable","Ocupada por "&S15)))))) -> Lista para revisar: analizó Juan Fernando | V15: =IF(AND(Z15<>"",Z15=S15),"El revisor no puede ser el responsable",IF(AND(OR(T15="Analizado",T15="En revisión",T15="Aprobado"),W15=""),"Falta la fuente del análisis",IF(AND(OR(T15="Aprobado",T15="En Trello"),Z15=""),"Aprobado sin revisor",""))) | W15: Prompt con IA | X15: Hoja 15, elemento 13: 7 valores (01 a 06 y 99), alfanumérico, formato 99, longitud 2 y 2. Numeral 2.3: más de 5 opciones. | AA15: 46315 | AC15: Lista de 7 valores. Cargo: PENDIENTE D-02. Representación del código: PENDIENTE D-18. Lectura dudosa: el escaneo de la hoja 15 muestra “Indigena”, posiblemente sin tilde; confirmar en el impreso. Si no la tiene, L pasa a “No: hay diferencias”.
A16: V-15 | B16: C | C16: 13 | D16: Comunidad étnica | E16: 15 | F16: Según catálogo de referencia de comunidades étnicas vigente | G16: El anexo no los enumera | H16: Alfanumérico | I16: 999 | J16: 3 | K16: 3 | L16: No: hay diferencias | M16: No los enumera | N16: Entidad por 2.3 | O16: Comunidades étnicas | P16: 2 | Q16: Ninguna cubre el CRUD. HU-004 a HU-006 no nombran el dato (Ajustar). | R16: 4 historias; IDs en espera de D-17 | S16: Juan Fernando | T16: Analizado | U16: =IF(OR(T16="",T16="Libre"),"Disponible",IF(T16="Bloqueado","Bloqueada: "&IF(Y16="","falta motivo",Y16),IF(OR(T16="Aprobado",T16="En Trello"),"Cerrada",IF(T16="En revisión","En revisión: "&IF(Z16="","falta revisor",Z16),IF(T16="Analizado","Lista para revisar: analizó "&IF(S16="","falta responsable",S16),IF(S16="","Falta responsable","Ocupada por "&S16)))))) -> Lista para revisar: analizó Juan Fernando | V16: =IF(AND(Z16<>"",Z16=S16),"El revisor no puede ser el responsable",IF(AND(OR(T16="Analizado",T16="En revisión",T16="Aprobado"),W16=""),"Falta la fuente del análisis",IF(AND(OR(T16="Aprobado",T16="En Trello"),Z16=""),"Aprobado sin revisor",""))) | W16: Prompt con IA | X16: Hoja 15, elemento 13: “según catálogo de comunidades étnicas vigente”, alfanumérico, 999, 3 y 3. Numeral 2.3: catálogo externo. | AA16: 46315 | AC16: Que cada comunidad pertenezca a una etnia es inferencia del modelo por la definición de la hoja; no se agrega como regla. Fuente y versión del catálogo: PENDIENTE D-21. La hoja escribe “Según catálogo de referencia de comunidades étnicas, según catálogo de comunidades étnicas vigente”; la referencia lo acorta.
A17: V-16 | B17: C | C17: 14 | D17: Zona territorial de residencia | E17: 15 | F17: 01 Urbana · 02 Rural | G17: 2 | H17: Alfanumérico | I17: 99 | J17: 2 | K17: 2 | L17: Sí | M17: 2 | N17: Campo del paciente | O17: Paciente | P17: 5 | Q17: HU-004, HU-005, HU-006 no nombran el dato (Ajustar). | R17: ninguna | S17: Juan Fernando | T17: Analizado | U17: =IF(OR(T17="",T17="Libre"),"Disponible",IF(T17="Bloqueado","Bloqueada: "&IF(Y17="","falta motivo",Y17),IF(OR(T17="Aprobado",T17="En Trello"),"Cerrada",IF(T17="En revisión","En revisión: "&IF(Z17="","falta revisor",Z17),IF(T17="Analizado","Lista para revisar: analizó "&IF(S17="","falta responsable",S17),IF(S17="","Falta responsable","Ocupada por "&S17)))))) -> Lista para revisar: analizó Juan Fernando | V17: =IF(AND(Z17<>"",Z17=S17),"El revisor no puede ser el responsable",IF(AND(OR(T17="Analizado",T17="En revisión",T17="Aprobado"),W17=""),"Falta la fuente del análisis",IF(AND(OR(T17="Aprobado",T17="En Trello"),Z17=""),"Aprobado sin revisor",""))) | W17: Prompt con IA | X17: Hoja 15, elemento 14: 2 valores, alfanumérico, formato 99, longitud 2 y 2. Numeral 2.3: no llega a más de 5 opciones. | AA17: 46315 | AC17: Lista de 2 valores. Campo del paciente.
A18: V-17 | B18: C | C18: 15 | D18: Código y nombre de la entidad que responde por el plan de beneficios | E18: 15 y 16 | F18: EPS, entidades adaptadas, regímenes especial y de excepción, fondo de población privada de la libertad, secretarías e institutos de salud, aseguradoras SOAT, planes voluntarios y ARL, según catálogo del Ministerio de Salud. Si la atención es particular, la secretaría de salud del lugar | G18: El anexo no los enumera | H18: Alfanumérico | I18: 999999 / sin formato | J18: 6 / 200 | K18: 6 / 3 | L18: No: hay diferencias | M18: No los enumera | N18: Entidad por 2.3 | O18: Entidades administradoras de planes de beneficios | P18: 2 | Q18: Ninguna cubre el CRUD. HU-004 a HU-006 no nombran el dato (Ajustar). | R18: 4 historias; IDs en espera de D-17 | S18: Juan Fernando | T18: Analizado | U18: =IF(OR(T18="",T18="Libre"),"Disponible",IF(T18="Bloqueado","Bloqueada: "&IF(Y18="","falta motivo",Y18),IF(OR(T18="Aprobado",T18="En Trello"),"Cerrada",IF(T18="En revisión","En revisión: "&IF(Z18="","falta revisor",Z18),IF(T18="Analizado","Lista para revisar: analizó "&IF(S18="","falta responsable",S18),IF(S18="","Falta responsable","Ocupada por "&S18)))))) -> Lista para revisar: analizó Juan Fernando | V18: =IF(AND(Z18<>"",Z18=S18),"El revisor no puede ser el responsable",IF(AND(OR(T18="Analizado",T18="En revisión",T18="Aprobado"),W18=""),"Falta la fuente del análisis",IF(AND(OR(T18="Aprobado",T18="En Trello"),Z18=""),"Aprobado sin revisor",""))) | W18: Prompt con IA | X18: Hojas 15 y 16, elemento 15: código (alfanumérico, 999999, 6 y 6) y nombre (200 y 3), “según catálogo que establezca el Ministerio de Salud y Protección Social”. Numeral 2.3: catálogo externo. | AA18: 46315 | AC18: La referencia resume el texto de los valores permitidos; coinciden código y nombre. Fuente y versión del catálogo: PENDIENTE D-21. Si la atención es particular, el código es el de la secretaría de salud del lugar donde se prestó (hoja 16).
A19: V-18 | B19: C | C19: 16 | D19: Código del prestador de servicios de salud que realiza la atención | E19: 16 | F19: Código asignado en el SGSSS a los prestadores inscritos en el REPS, o asignado por el Ministerio en casos de excepción, publicados en SISPRO | G19: El anexo no los enumera | H19: Alfanumérico | I19: 999999999999 | J19: 12 | K19: 12 | L19: No: hay diferencias | M19: No los enumera | N19: Pendiente de decisión | O19: Prestadores si D-05 lo hace catálogo; si no, Atención | Q19: HU-007, HU-008, HU-009 usan el código (Ajustar). | R19: 4 historias si D-05 lo hace catálogo; IDs en espera de D-17 | S19: Juan Fernando | T19: Bloqueado | U19: =IF(OR(T19="",T19="Libre"),"Disponible",IF(T19="Bloqueado","Bloqueada: "&IF(Y19="","falta motivo",Y19),IF(OR(T19="Aprobado",T19="En Trello"),"Cerrada",IF(T19="En revisión","En revisión: "&IF(Z19="","falta revisor",Z19),IF(T19="Analizado","Lista para revisar: analizó "&IF(S19="","falta responsable",S19),IF(S19="","Falta responsable","Ocupada por "&S19)))))) -> Bloqueada: D-05 | V19: =IF(AND(Z19<>"",Z19=S19),"El revisor no puede ser el responsable",IF(AND(OR(T19="Analizado",T19="En revisión",T19="Aprobado"),W19=""),"Falta la fuente del análisis",IF(AND(OR(T19="Aprobado",T19="En Trello"),Z19=""),"Aprobado sin revisor",""))) | W19: Prompt con IA | X19: Hoja 16, elemento 16: código del REPS publicado en SISPRO, alfanumérico, 999999999999, 12 y 12. D-05. | Y19: D-05 | AA19: 46315 | AC19: Si es catálogo propio depende de D-05. Para una sola IPS, el prestador que realiza la atención puede ser fijo (sus sedes); el del elemento 9 puede ser cualquier prestador del país. Fila bloqueada hasta D-05. La referencia parafrasea el texto de los valores permitidos de la hoja 16.
A20: V-19 | B20: C | C20: 17 | D20: Fecha y hora de inicio de la atención | E20: 16 | F20: Sin lista | G20: No aplica: dato abierto | H20: Fecha | I20: AAAA-MM-DD HH:MM | J20: 16 | K20: 16 | L20: No: hay diferencias | M20: No aplica | N20: Campo de la atención | O20: Atención | P20: 5 | Q20: HU-007, HU-008, HU-009 (Ajustar). | R20: ninguna | S20: Juan Fernando | T20: Analizado | U20: =IF(OR(T20="",T20="Libre"),"Disponible",IF(T20="Bloqueado","Bloqueada: "&IF(Y20="","falta motivo",Y20),IF(OR(T20="Aprobado",T20="En Trello"),"Cerrada",IF(T20="En revisión","En revisión: "&IF(Z20="","falta revisor",Z20),IF(T20="Analizado","Lista para revisar: analizó "&IF(S20="","falta responsable",S20),IF(S20="","Falta responsable","Ocupada por "&S20)))))) -> Lista para revisar: analizó Juan Fernando | V20: =IF(AND(Z20<>"",Z20=S20),"El revisor no puede ser el responsable",IF(AND(OR(T20="Analizado",T20="En revisión",T20="Aprobado"),W20=""),"Falta la fuente del análisis",IF(AND(OR(T20="Aprobado",T20="En Trello"),Z20=""),"Aprobado sin revisor",""))) | W20: Prompt con IA | X20: Hoja 16, elemento 17: Fecha, longitud 16 y 16. Retroalimentación HU-007 ampliada: concretar fecha/hora. | AA20: 46315 | AC20: La hoja 16 imprime el formato “AAAA-MM-DD HH MM”, sin dos puntos; los elementos 4 y 22 traen “HH:MM” y la longitud es 16 en los dos casos. Se asume “HH:MM”: supuesto a confirmar. La hora es obligatoria (mínima 16).
A21: V-20 | B21: C | C21: 18 | D21: Modalidad de realización | E21: 16 | F21: 01 Intramural · 02 Extramural unidad móvil · 03 Extramural domiciliaria · 04 Extramural jornada de salud · 05 Extramural (atención prehospitalaria o transporte asistencial) · 06 Telemedicina interactiva · 07 Telemedicina no interactiva · 08 Telemedicina, telexperticia · 09 Telemedicina, telemonitoreo | G21: 9 | H21: Alfanumérico | I21: 99 | J21: 2 | K21: 2 | L21: No: hay diferencias | M21: 9 | N21: Entidad por 2.3 | O21: Modalidades de realización | P21: 3 | Q21: Ninguna cubre el CRUD. HU-007, HU-008 y HU-009 usan el dato (Ajustar). | R21: 4 historias; IDs en espera de D-17 | S21: Juan Fernando | T21: Analizado | U21: =IF(OR(T21="",T21="Libre"),"Disponible",IF(T21="Bloqueado","Bloqueada: "&IF(Y21="","falta motivo",Y21),IF(OR(T21="Aprobado",T21="En Trello"),"Cerrada",IF(T21="En revisión","En revisión: "&IF(Z21="","falta revisor",Z21),IF(T21="Analizado","Lista para revisar: analizó "&IF(S21="","falta responsable",S21),IF(S21="","Falta responsable","Ocupada por "&S21)))))) -> Lista para revisar: analizó Juan Fernando | V21: =IF(AND(Z21<>"",Z21=S21),"El revisor no puede ser el responsable",IF(AND(OR(T21="Analizado",T21="En revisión",T21="Aprobado"),W21=""),"Falta la fuente del análisis",IF(AND(OR(T21="Aprobado",T21="En Trello"),Z21=""),"Aprobado sin revisor",""))) | W21: Prompt con IA | X21: Hoja 16, elemento 18: 9 valores, alfanumérico, formato 99, longitud 2 y 2. Numeral 2.3: más de 5 opciones. Retroalimentación HU-007 ampliada: concretar modalidad/grupo. | AA21: 46315 | AC21: Hoja 16: valor 05 “Extramural (atención pre hospitalaria o transporte asistencial)”; 08 “Telemedicina – Telexperticia”; 09 “Telemedicina – Telemonitoreo”. La referencia escribe “prehospitalaria” y separa con coma. Coinciden conteo, tipo, formato y longitudes. Cargo: PENDIENTE D-02. La referencia además escribe “telexperticia” y “telemonitoreo” en minúscula.
A22: V-21 | B22: C | C22: 18 | D22: Grupo de servicios | E22: 16 | F22: 01 Consulta externa · 02 Apoyo diagnóstico y complementación terapéutica · 03 Internación · 04 Quirúrgico · 05 Atención inmediata | G22: 5 | H22: Alfanumérico | I22: 99 | J22: 2 | K22: 2 | L22: No: hay diferencias | M22: 5 | N22: Campo de la atención | O22: Atención | P22: 5 | Q22: HU-007, HU-008, HU-009 (Ajustar). | R22: ninguna | S22: Juan Fernando | T22: Analizado | U22: =IF(OR(T22="",T22="Libre"),"Disponible",IF(T22="Bloqueado","Bloqueada: "&IF(Y22="","falta motivo",Y22),IF(OR(T22="Aprobado",T22="En Trello"),"Cerrada",IF(T22="En revisión","En revisión: "&IF(Z22="","falta revisor",Z22),IF(T22="Analizado","Lista para revisar: analizó "&IF(S22="","falta responsable",S22),IF(S22="","Falta responsable","Ocupada por "&S22)))))) -> Lista para revisar: analizó Juan Fernando | V22: =IF(AND(Z22<>"",Z22=S22),"El revisor no puede ser el responsable",IF(AND(OR(T22="Analizado",T22="En revisión",T22="Aprobado"),W22=""),"Falta la fuente del análisis",IF(AND(OR(T22="Aprobado",T22="En Trello"),Z22=""),"Aprobado sin revisor",""))) | W22: Prompt con IA | X22: Hoja 16, elemento 18: 5 valores, alfanumérico, formato 99, longitud 2 y 2. Numeral 2.3: no llega a más de 5 opciones. D-01. | AA22: 46315 | AC22: Lista de exactamente 5 valores. Depende de D-01: si el umbral pasa a 5 o más, cambia a Entidad por 2.3 con 4 historias nuevas. La hoja escribe el valor 05 con mayúscula: “Atención Inmediata”.
A23: V-22 | B23: D | C23: 19 | D23: Entorno donde se realiza la atención | E23: 16 | F23: 01 Hogar · 02 Comunitario · 03 Escolar · 04 Laboral · 05 Institucional | G23: 5 | H23: Alfanumérico | I23: 99 | J23: 2 | K23: 2 | L23: Sí | M23: 5 | N23: Campo de la atención | O23: Atención | P23: 5 | Q23: HU-007, HU-008, HU-009 | R23: ninguna | S23: Juan Fernando | T23: Analizado | U23: =IF(OR(T23="",T23="Libre"),"Disponible",IF(T23="Bloqueado","Bloqueada: "&IF(Y23="","falta motivo",Y23),IF(OR(T23="Aprobado",T23="En Trello"),"Cerrada",IF(T23="En revisión","En revisión: "&IF(Z23="","falta revisor",Z23),IF(T23="Analizado","Lista para revisar: analizó "&IF(S23="","falta responsable",S23),IF(S23="","Falta responsable","Ocupada por "&S23)))))) -> Lista para revisar: analizó Juan Fernando | V23: =IF(AND(Z23<>"",Z23=S23),"El revisor no puede ser el responsable",IF(AND(OR(T23="Analizado",T23="En revisión",T23="Aprobado"),W23=""),"Falta la fuente del análisis",IF(AND(OR(T23="Aprobado",T23="En Trello"),Z23=""),"Aprobado sin revisor",""))) | W23: Prompt con IA | X23: Hoja 16, elemento 19: 5 valores, alfanumérico, formato 99, longitud 2 y 2. Numeral 2.3: no llega a más de 5 opciones. D-01. Retroalimentación HU-007, revisión ampliada: concretar entorno. | AA23: 46313 | AC23: Lista de exactamente 5 valores. Depende de D-01: si el umbral pasa a 5 o más, cambia a Entidad por 2.3 con 4 historias nuevas. Obligatoriedad del dato: PENDIENTE D-15. Se guarda como texto de 2 caracteres: PENDIENTE D-18.
A24: V-23 | B24: D | C24: 20 | D24: Vía de ingreso del usuario al servicio de salud | E24: 16 y 17 | F24: 01 Demanda espontánea · 02 Derivado de consulta externa · 03 Derivado de urgencias · 04 Derivado de hospitalización · 05 Derivado de sala de cirugía · 06 Derivado de sala de partos · 07 Recién nacido en la institución · 08 Recién nacido en otra institución · 09 Derivado o referido de hospitalización domiciliaria · 10 Derivado de atención domiciliaria · 11 Derivado de telemedicina · 12 Derivado de jornada de salud · 13 Referido de otra institución · 14 Contrarreferido de otra institución | G24: 14 | H24: Alfanumérico | I24: 99 | J24: 2 | K24: 2 | L24: No: hay diferencias | M24: 14 | N24: Entidad por 2.3 | O24: Vía de ingreso | P24: 3 | Q24: Ninguna cubre el CRUD. HU-007, HU-008 y HU-009 usan el dato (Ajustar). | R24: 4 historias; IDs en espera de D-17 | S24: Juan Fernando | T24: Analizado | U24: =IF(OR(T24="",T24="Libre"),"Disponible",IF(T24="Bloqueado","Bloqueada: "&IF(Y24="","falta motivo",Y24),IF(OR(T24="Aprobado",T24="En Trello"),"Cerrada",IF(T24="En revisión","En revisión: "&IF(Z24="","falta revisor",Z24),IF(T24="Analizado","Lista para revisar: analizó "&IF(S24="","falta responsable",S24),IF(S24="","Falta responsable","Ocupada por "&S24)))))) -> Lista para revisar: analizó Juan Fernando | V24: =IF(AND(Z24<>"",Z24=S24),"El revisor no puede ser el responsable",IF(AND(OR(T24="Analizado",T24="En revisión",T24="Aprobado"),W24=""),"Falta la fuente del análisis",IF(AND(OR(T24="Aprobado",T24="En Trello"),Z24=""),"Aprobado sin revisor",""))) | W24: Prompt con IA | X24: Hojas 16 y 17, elemento 20: 14 valores, alfanumérico, formato 99, longitud 2 y 2. Numeral 2.3: más de 5 opciones. Retroalimentación General ampliada: cobertura de todos los catálogos con más de cinco opciones. HU-007 ampliada: concretar vía. | AA24: 46313 | AC24: Hoja 17, valor 14: “Contra referido de otra institución”; la referencia escribe “Contrarreferido”. Coinciden conteo, tipo, formato y longitudes. Entidad con código de 2 caracteres, guardado como texto para conservar el cero inicial, y nombre. La atención guarda el código de la vía. Por el artículo 7 de la Resolución 866, el catálogo solo refleja los valores de la hoja. Cargo que mantiene el catálogo: PENDIENTE D-02. Obligatoriedad en la atención: PENDIENTE D-15. Representación del código: PENDIENTE D-18.
A25: V-24 | B25: D | C25: 21 | D25: Causa que motiva la atención | E25: 17 | F25: 21 Accidente de trabajo · 22 Accidente en el hogar · 23 Accidente de tránsito de origen común · 24 Accidente de tránsito de origen laboral · 25 Accidente en el entorno educativo · 26 Otro tipo de accidente · 27 Evento catastrófico de origen natural · 28 Lesión por agresión · 29 Lesión autoinfligida · 30 Sospecha de violencia física · 31 Sospecha de violencia psicológica · 32 Sospecha de violencia sexual · 33 Sospecha de negligencia y abandono · 34 IVE relacionado con peligro a la salud o vida de la mujer · 35 IVE por malformación congénita incompatible con la vida · 36 IVE por violencia sexual, incesto o por inseminación artificial o transferencia de óvulo fecundado no consentida · 37 Evento adverso en salud · 38 Enfermedad general · 39 Enfermedad laboral · 40 Promoción y mantenimiento de la salud, intervenciones individuales · 41 Intervención colectiva · 42 Atención de población materno perinatal · 43 Seguridad y salud en el trabajo · 44 Otros eventos catastróficos · 45 Accidente de mina antipersonal (MAP) · 46 Accidente de artefacto explosivo improvisado (AEI) · 47 Accidente de munición sin explotar (MUSE) · 48 Otra víctima de conflicto armado colombiano · 49 Riesgo ambiental | G25: 29 | H25: Alfanumérico | I25: 99 | J25: 2 | K25: 2 | L25: No: hay diferencias | M25: 29 | N25: Entidad por 2.3 | O25: Causa que motiva la atención | P25: 3 | Q25: Ninguna cubre el CRUD. HU-007, HU-008 y HU-009 usan el dato (Ajustar). | R25: 4 historias; IDs en espera de D-17 | S25: Juan Fernando | T25: Analizado | U25: =IF(OR(T25="",T25="Libre"),"Disponible",IF(T25="Bloqueado","Bloqueada: "&IF(Y25="","falta motivo",Y25),IF(OR(T25="Aprobado",T25="En Trello"),"Cerrada",IF(T25="En revisión","En revisión: "&IF(Z25="","falta revisor",Z25),IF(T25="Analizado","Lista para revisar: analizó "&IF(S25="","falta responsable",S25),IF(S25="","Falta responsable","Ocupada por "&S25)))))) -> Lista para revisar: analizó Juan Fernando | V25: =IF(AND(Z25<>"",Z25=S25),"El revisor no puede ser el responsable",IF(AND(OR(T25="Analizado",T25="En revisión",T25="Aprobado"),W25=""),"Falta la fuente del análisis",IF(AND(OR(T25="Aprobado",T25="En Trello"),Z25=""),"Aprobado sin revisor",""))) | W25: Prompt con IA | X25: Hoja 17, elemento 21: 29 valores (códigos 21 a 49), alfanumérico, formato 99, longitud 2 y 2. Numeral 2.3: más de 5 opciones. Retroalimentación General ampliada: cobertura de catálogos con más de cinco opciones. HU-007 ampliada: concretar causa. | AA25: 46313 | AC25: Hoja 17: el valor 29 dice “Lesión auto infligida”; el 40, “Promoción y mantenimiento de la salud-Intervenciones individuales.”; del 45 al 47 la sigla va después de un guion y no entre paréntesis; en el 43, 44, 46 y 47 la referencia quitó mayúsculas. Coinciden conteo, tipo, formato y longitudes. Los nombres del catálogo se toman de la hoja. El 36 dice “ovulo”, sin tilde. Entidad con código de 2 caracteres y nombre. La hoja no cita catálogo externo: sus 29 valores son la fuente oficial y, por el artículo 7 de la Resolución 866, la IPS no agrega otros. Cargo: PENDIENTE D-02. Obligatoriedad en la atención: PENDIENTE D-15. Representación del código: PENDIENTE D-18. Valor 27: la hoja escribe “orígen natural”, con tilde; la referencia, “origen”.
A26: V-25 | B26: D | C26: 22 | D26: Fecha, hora y clasificación del triage | E26: 17 y 18 | F26: Fecha y hora del triage. Clasificación: 01 Triage I · 02 Triage II · 03 Triage III · 04 Triage IV · 05 Triage V | G26: 5 | H26: Fecha / Alfanumérico | I26: AAAA-MM-DD HH:MM / 99 | J26: 16 / 2 | K26: 16 / 2 | L26: Sí | M26: 5 | N26: Campo de la atención | O26: Atención | P26: 5 | Q26: HU-007, HU-008, HU-009 | R26: ninguna | S26: Juan Fernando | T26: Analizado | U26: =IF(OR(T26="",T26="Libre"),"Disponible",IF(T26="Bloqueado","Bloqueada: "&IF(Y26="","falta motivo",Y26),IF(OR(T26="Aprobado",T26="En Trello"),"Cerrada",IF(T26="En revisión","En revisión: "&IF(Z26="","falta revisor",Z26),IF(T26="Analizado","Lista para revisar: analizó "&IF(S26="","falta responsable",S26),IF(S26="","Falta responsable","Ocupada por "&S26)))))) -> Lista para revisar: analizó Juan Fernando | V26: =IF(AND(Z26<>"",Z26=S26),"El revisor no puede ser el responsable",IF(AND(OR(T26="Analizado",T26="En revisión",T26="Aprobado"),W26=""),"Falta la fuente del análisis",IF(AND(OR(T26="Aprobado",T26="En Trello"),Z26=""),"Aprobado sin revisor",""))) | W26: Prompt con IA | X26: Hojas 17 y 18, elemento 22: fecha y hora (Fecha, AAAA-MM-DD HH:MM, 16 y 16) y clasificación (5 valores, alfanumérico, 99, 2 y 2). Numeral 2.3: no llega a más de 5 opciones. D-01, D-13. Retroalimentación HU-007, revisión ampliada: “triage cuando corresponda”. | AA26: 46313 | AC26: Dos componentes. Fecha y hora del triage: Fecha, AAAA-MM-DD HH:MM, 16 y 16. Clasificación: 5 valores, formato 99, 2 y 2; depende de D-01. La hoja 18 completa la definición: prioridad de la atención en un servicio de urgencias. Los dos componentes son campos de la atención. Si el umbral pasa a 5 o más, la clasificación cambia a Entidad por 2.3 con 4 historias nuevas. La fecha exige hora (mínima 16), a diferencia de la fecha de nacimiento (mínima 10). Cuándo se exige: PENDIENTE D-13. La fecha se guarda como fecha y hora; la clasificación como texto de 2: PENDIENTE D-18.
A27: V-26 | B27: D | C27: 23 | D27: Código y nombre del diagnóstico principal de ingreso | E27: 18 | F27: Código del diagnóstico confirmado o presuntivo según catálogo CIE-10 vigente. Nombre correspondiente al código | G27: El anexo no los enumera | H27: Alfanumérico | I27: 9999 / sin formato | J27: 4 / 200 | K27: 4 / 3 | L27: No: hay diferencias | M27: No los enumera | N27: Entidad por 2.3 | O27: Diagnósticos CIE-10 | P27: 2 | Q27: HU-030, HU-031, HU-032, HU-033 cubren el CRUD (Ajustar). HU-007, HU-008 y HU-009 usan el código (Ajustar). | R27: ninguna | S27: Juan Fernando | T27: Analizado | U27: =IF(OR(T27="",T27="Libre"),"Disponible",IF(T27="Bloqueado","Bloqueada: "&IF(Y27="","falta motivo",Y27),IF(OR(T27="Aprobado",T27="En Trello"),"Cerrada",IF(T27="En revisión","En revisión: "&IF(Z27="","falta revisor",Z27),IF(T27="Analizado","Lista para revisar: analizó "&IF(S27="","falta responsable",S27),IF(S27="","Falta responsable","Ocupada por "&S27)))))) -> Lista para revisar: analizó Juan Fernando | V27: =IF(AND(Z27<>"",Z27=S27),"El revisor no puede ser el responsable",IF(AND(OR(T27="Analizado",T27="En revisión",T27="Aprobado"),W27=""),"Falta la fuente del análisis",IF(AND(OR(T27="Aprobado",T27="En Trello"),Z27=""),"Aprobado sin revisor",""))) | W27: Prompt con IA | X27: Hoja 18, elemento 23: código CIE-10 (alfanumérico, formato 9999, longitud 4 y 4) y nombre correspondiente al código (alfanumérico, 200 y 3). Numeral 2.2: última versión del CIE-10 y jerarquía padre-hijo. Numeral 2.3. HU-007 ampliada: diagnóstico principal/tipo. | AA27: 46313 | AC27: Hoja 18: “catálogo de CIE10 vigente”. Versión: PENDIENTE D-09. Código y nombre en la misma entidad: el nombre es el que corresponde al código, no texto libre. Si un código padre se puede asociar a una atención: D-22 (propuesta: no, por la longitud 4 y 4). Carga desde el archivo oficial: funcionalidad de la historia del catálogo (el docente la da por funcional). La referencia parafrasea los valores permitidos; la hoja escribe “de acuerdo catálogo CIE10 y las normas que la modifiquen”.
A28: V-27 | B28: D | C28: 23 | D28: Código de enfermedad huérfana | E28: 18 | F28: En caso de presentar una enfermedad huérfana, código del catálogo de enfermedades huérfanas vigente | G28: El anexo no los enumera | H28: Alfanumérico | I28: 9999 | J28: 4 | K28: 1 | L28: No: hay diferencias | M28: No los enumera | N28: Entidad por 2.3 | O28: Enfermedades huérfanas | P28: 2 | Q28: Ninguna cubre el CRUD. HU-007, HU-008 y HU-009 usan el dato (Ajustar). | R28: 4 historias; IDs en espera de D-17 | S28: Juan Fernando | T28: Analizado | U28: =IF(OR(T28="",T28="Libre"),"Disponible",IF(T28="Bloqueado","Bloqueada: "&IF(Y28="","falta motivo",Y28),IF(OR(T28="Aprobado",T28="En Trello"),"Cerrada",IF(T28="En revisión","En revisión: "&IF(Z28="","falta revisor",Z28),IF(T28="Analizado","Lista para revisar: analizó "&IF(S28="","falta responsable",S28),IF(S28="","Falta responsable","Ocupada por "&S28)))))) -> Lista para revisar: analizó Juan Fernando | V28: =IF(AND(Z28<>"",Z28=S28),"El revisor no puede ser el responsable",IF(AND(OR(T28="Analizado",T28="En revisión",T28="Aprobado"),W28=""),"Falta la fuente del análisis",IF(AND(OR(T28="Aprobado",T28="En Trello"),Z28=""),"Aprobado sin revisor",""))) | W28: Prompt con IA | X28: Hoja 18, elemento 23: código de enfermedad huérfana, alfanumérico, 9999, longitud 4 y 1, “según catálogo de enfermedades huérfanas vigente”. Numeral 2.3: catálogo externo. D-14. | AA28: 46313 | AC28: En la hoja este componente no tiene nombre propio: es la segunda línea de “Código del diagnóstico principal”, y aplica solo “en caso de presentar” una enfermedad huérfana. Longitud mínima 1, máxima 4. Catálogo distinto del CIE-10: la hoja lo nombra aparte y sus longitudes (1 a 4) no son las del CIE-10 (4 y 4). Fuente y versión: PENDIENTE D-14. Dato opcional de la atención: solo si el paciente la presenta. La referencia parafrasea el texto de la hoja sobre enfermedades huérfanas.
A29: V-28 | B29: D | C29: 23 | D29: Tipo de diagnóstico principal de ingreso | E29: 18 | F29: 01 Impresión diagnóstica · 02 Confirmado nuevo · 03 Confirmado repetido | G29: 3 | H29: Alfanumérico | I29: 99 | J29: 2 | K29: 2 | L29: Sí | M29: 3 | N29: Campo de la atención | O29: Atención | P29: 5 | Q29: HU-007, HU-008, HU-009 (Ajustar). | R29: ninguna | S29: Juan Fernando | T29: Analizado | U29: =IF(OR(T29="",T29="Libre"),"Disponible",IF(T29="Bloqueado","Bloqueada: "&IF(Y29="","falta motivo",Y29),IF(OR(T29="Aprobado",T29="En Trello"),"Cerrada",IF(T29="En revisión","En revisión: "&IF(Z29="","falta revisor",Z29),IF(T29="Analizado","Lista para revisar: analizó "&IF(S29="","falta responsable",S29),IF(S29="","Falta responsable","Ocupada por "&S29)))))) -> Lista para revisar: analizó Juan Fernando | V29: =IF(AND(Z29<>"",Z29=S29),"El revisor no puede ser el responsable",IF(AND(OR(T29="Analizado",T29="En revisión",T29="Aprobado"),W29=""),"Falta la fuente del análisis",IF(AND(OR(T29="Aprobado",T29="En Trello"),Z29=""),"Aprobado sin revisor",""))) | W29: Prompt con IA | X29: Hoja 18, elemento 23: tipo de diagnóstico, 3 valores, alfanumérico, formato 99, longitud 2 y 2. Numeral 2.3: no llega a más de 5 opciones. | AA29: 46313 | AC29: Lista de 3 valores. Campo de la atención.

Sheet Entidades
A1: Entidad o grupo | B1: Regla | C1: Filas de validación | D1: Elementos | E1: Valores en la hoja | F1: Historias existentes | G1: Historias nuevas (una por operación) | H1: Total si D-17 = una por operación | I1: Total si D-17 = una por entidad | J1: Decisiones que la afectan | K1: Nota
A2: Inicio de sesión | B2: Numeral 2.4 | C2: Sin fila | D2: No aplica | E2: No aplica | F2: HU-001 a HU-003 | G2: 0 | H2: 3 | I2: 3 | J2: D-04, D-06 | K2: Si D-04 = una historia, el grupo da 1.
A3: Paciente | B3: Numeral 2: registrar, consultar, actualizar | C3: V-01 a V-17 (campos) | D3: 1 a 15 | E3: No aplica | F3: HU-004 a HU-006 | G3: 0 | H3: 3 | I3: 3 | J3: D-07, D-19 | K3: Sin eliminar: el numeral 2 no lo pide.
A4: Atención | B4: Numeral 2: crear, consultar, modificar | C4: V-18 a V-28 (campos) | D4: 16 a 23 | E4: No aplica | F4: HU-007 a HU-009 | G4: 0 | H4: 3 | I4: 3 | J4: D-08, D-13, D-15, D-27 | K4: Sin eliminar: el numeral 2 no lo pide. El backlog v3 agrega la anulación (HU-043, D-27).
A5: Países | B5: 2.3, catálogo externo ISO 3166-1 | C5: V-01, V-12 | D5: 1, 11 | E5: Catálogo | F5: HU-018 a HU-021 | G5: 0 | H5: 4 | I5: 1 | J5: D-02, D-03, D-17, D-20, D-21 | K5: V-12 reutiliza.
A6: Tipos de documento de identificación | B6: 2.3, lista de 14 | C6: V-02 | D6: 2 | E6: 14 | F6: Ninguna | G6: 4 | H6: 4 | I6: 1 | J6: D-02, D-17, D-20
A7: Ocupaciones | B7: 2.3, catálogo externo CIUO-88 A.C. | C7: V-08 | D7: 7 | E7: Catálogo | F7: HU-022 a HU-025 | G7: 0 | H7: 4 | I7: 1 | J7: D-02, D-17, D-20, D-21 | K7: Solo códigos de 4 caracteres se asocian.
A8: Oposición a la presunción legal de donación | B8: 2.1, estructura separada | C8: V-09 | D8: 8 | E8: 2 | F8: HU-010 a HU-013 | G8: 0 | H8: 4 | I8: 1 | J8: D-17, D-20
A9: Documento de voluntad anticipada | B9: 2.1, estructura separada | C9: V-10 | D9: 9 | E9: 2 | F9: HU-014 a HU-017 | G9: 0 | H9: 4 | I9: 1 | J9: D-05, D-17, D-20 | K9: La revocación es actualización.
A10: Categorías de discapacidad | B10: 2.3, lista de 8 | C10: V-11 | D10: 10 | E10: 8 | F10: Ninguna | G10: 4 | H10: 4 | I10: 1 | J10: D-02, D-17, D-20 | K10: Varias por paciente.
A11: Municipios | B11: 2.3, catálogo externo DIVIPOLA | C11: V-13 | D11: 12 | E11: Catálogo | F11: HU-026 a HU-029 | G11: 0 | H11: 4 | I11: 1 | J11: D-02, D-17, D-20, D-21
A12: Etnias | B12: 2.3, lista de 7 | C12: V-14 | D12: 13 | E12: 7 | F12: Ninguna | G12: 4 | H12: 4 | I12: 1 | J12: D-02, D-17, D-20
A13: Comunidades étnicas | B13: 2.3, catálogo externo | C13: V-15 | D13: 13 | E13: Catálogo | F13: Ninguna | G13: 4 | H13: 4 | I13: 1 | J13: D-02, D-17, D-20, D-21
A14: Entidades administradoras de planes de beneficios | B14: 2.3, catálogo externo | C14: V-17 | D14: 15 | E14: Catálogo | F14: Ninguna | G14: 4 | H14: 4 | I14: 1 | J14: D-02, D-17, D-20, D-21
A15: Modalidades de realización | B15: 2.3, lista de 9 | C15: V-20 | D15: 18 | E15: 9 | F15: Ninguna | G15: 4 | H15: 4 | I15: 1 | J15: D-02, D-17, D-20
A16: Vía de ingreso | B16: 2.3, lista de 14 | C16: V-23 | D16: 20 | E16: 14 | F16: Ninguna | G16: 4 | H16: 4 | I16: 1 | J16: D-02, D-17, D-20
A17: Causa que motiva la atención | B17: 2.3, lista de 29 | C17: V-24 | D17: 21 | E17: 29 | F17: Ninguna | G17: 4 | H17: 4 | I17: 1 | J17: D-02, D-17, D-20
A18: Diagnósticos CIE-10 | B18: 2.3 y 2.2, catálogo externo con jerarquía | C18: V-26 | D18: 23 | E18: Catálogo | F18: HU-030 a HU-033 | G18: 0 | H18: 4 | I18: 1 | J18: D-02, D-09, D-17, D-20, D-26 | K18: Backlog v3: HU-030 (catálogo) y HU-031 (búsqueda del médico, otro actor).
A19: Enfermedades huérfanas | B19: 2.3, catálogo externo | C19: V-27 | D19: 23 | E19: Catálogo | F19: Ninguna | G19: 4 | H19: 4 | I19: 1 | J19: D-02, D-14, D-17, D-20 | K19: Opcional en la atención.
A20: Prestadores (solo si D-05 lo hace catálogo) | B20: 2.3, catálogo externo REPS | C20: V-18 (y componente 3 de V-10) | D20: 16, 9 | E20: Catálogo | F20: Ninguna | G20: 4 | H20: 4 | I20: 1 | J20: D-05, D-17, D-20, D-21 | K20: No entra en los totales de abajo.
A22: Historias nuevas | G22: =SUM(G2:G19) -> 36
A23: Total del backlog | H23: =SUM(H2:H19) -> 69 | I23: =SUM(I2:I19) -> 24
A24: Total del backlog con prestador | H24: =H23+H20 -> 73 | I24: =I23+I20 -> 25
A25: Mínimo del numeral 2.5 | H25: 30 | I25: 30
A27: Cómo leerla: “una por operación” son 4 historias por entidad (crear, consultar, actualizar, eliminar o inactivar); “una por entidad” junta el CRUD en una. Paciente, atención e inicio de sesión quedan en 3 en las dos columnas. Con todo comprimido el backlog queda por debajo de 30 (numeral 2.5): D-17 solo puede comprimir una parte. Cada entidad que vuelve a 4 historias suma 3: desde 24 hacen falta al menos 2 entidades con sus 4 historias para llegar a 30.

Sheet Anexo 1 a 49
A1: Elemento | B1: Nombre del elemento | C1: Grupo del anexo | D1: Componente | E1: Hoja del PDF | F1: Valores en la hoja | G1: Tipo | H1: Fila de Validación | I1: Clasificación | J1: Estado de la clasificación | K1: Entidad o dónde vive el dato | L1: Historias de este backlog | M1: Historias de los compañeros (Trabajo equipo) | N1: Qué falta en este backlog | O1: Observación
A2: 1 | B2: País de la nacionalidad | C2: Identificación del usuario (1 a 15) | D2: Código y nombre del país de nacionalidad | E2: 13 | F2: No los enumera | G2: Alfanumérico | H2: V-01 | I2: Entidad por 2.3 | J2: Analizada en Validación | K2: Países | L2: HU-018 a HU-021 cubren el CRUD (Ajustar). HU-004 a HU-006 usan el dato; los escenarios de varias nacionalidades cumplen. | M2: HU08 (CRUD de países); HU04 | N2: Ajustar las historias existentes (Ajustes por historia).
A3: 2 | B3: Documento de identificación | C3: Identificación del usuario (1 a 15) | D3: Tipo de documento de identificación | E3: 13 | F3: 14 | G3: Alfanumérico | H3: V-02 | I3: Entidad por 2.3 | J3: Analizada en Validación | K3: Tipos de documento de identificación | L3: Ninguna cubre el CRUD. HU-004 a HU-006 usan el dato (Ajustar). | M3: HU07 (CRUD de tipos de documento) | N3: CRUD de Tipos de documento de identificación: 4 historias nuevas (D-17). | O3: HU07 escenario 7 dice 13 tipos; la hoja 13 trae 14.
A4: 2 | B4: Documento de identificación | C4: Identificación del usuario (1 a 15) | D4: Número de documento de identificación | E4: 13 | F4: No aplica | G4: Alfanumérico | H4: V-03 | I4: Campo del paciente | J4: Analizada en Validación | K4: Paciente | L4: HU-004, HU-005, HU-006 (Ajustar). | M4: HU04, HU05, HU23 | N4: Escenarios en las historias de su entidad (Ajustes por historia).
A5: 3 | B5: Nombres y apellidos | C5: Identificación del usuario (1 a 15) | D5: Primer apellido, segundo apellido, primer nombre, segundo nombre | E5: 13 | F5: No aplica | G5: Alfanumérico | H5: V-04 | I5: Campo del paciente | J5: Analizada en Validación | K5: Paciente | L5: HU-004, HU-005, HU-006 (Ajustar). | M5: HU04, HU05, HU23 | N5: Escenarios en las historias de su entidad (Ajustes por historia).
A6: 4 | B6: Fecha y hora de nacimiento | C6: Identificación del usuario (1 a 15) | D6: Fecha y hora de nacimiento | E6: 13 | F6: No aplica | G6: Fecha | H6: V-05 | I6: Campo del paciente | J6: Analizada en Validación | K6: Paciente | L6: HU-004, HU-005, HU-006. Los escenarios de fecha separada de la hora y de hora faltante cumplen; faltan los de formato (Ajustar). | M6: HU04, HU05, HU23 | N6: Escenarios en las historias de su entidad (Ajustes por historia).
A7: 5 | B7: Sexo biológico | C7: Identificación del usuario (1 a 15) | D7: Sexo biológico | E7: 13 | F7: 3 | G7: Alfanumérico | H7: V-06 | I7: Campo del paciente | J7: Analizada en Validación | K7: Paciente | L7: HU-004, HU-005, HU-006 (Ajustar). | M7: HU04, HU05, HU23 | N7: Escenarios en las historias de su entidad (Ajustes por historia).
A8: 6 | B8: Identidad de género | C8: Identificación del usuario (1 a 15) | D8: Identidad de género | E8: 14 | F8: 5 | G8: Alfanumérico | H8: V-07 | I8: Campo del paciente | J8: Analizada en Validación | K8: Paciente | L8: HU-004, HU-005, HU-006 (Ajustar). | M8: HU04, HU05, HU23 | N8: Escenarios en las historias de su entidad (Ajustes por historia).
A9: 7 | B9: Ocupación al momento de la atención | C9: Identificación del usuario (1 a 15) | D9: Código y nombre de la ocupación | E9: 14 | F9: No los enumera | G9: Alfanumérico | H9: V-08 | I9: Entidad por 2.3 | J9: Analizada en Validación | K9: Ocupaciones | L9: HU-022 a HU-025 cubren el CRUD (Ajustar). HU-004 a HU-006 usan el dato; los escenarios de solo ocupaciones hijas cumplen. | M9: HU09 (CRUD de ocupaciones) | N9: Ajustar las historias existentes (Ajustes por historia).
A10: 8 | B10: Oposición a la presunción legal de donación | C10: Identificación del usuario (1 a 15) | D10: Manifestación de oposición a la presunción legal de donación, y fecha del documento | E10: 14 | F10: 2 | G10: Alfanumérico / Fecha | H10: V-09 | I10: Entidad por 2.1 | J10: Analizada en Validación | K10: Oposición a la presunción legal de donación | L10: HU-010 a HU-013 (Ajustar). | M10: Ninguna | N10: Ajustar las historias existentes (Ajustes por historia). | O10: Sin historias de oposición, que el numeral 2.1 pide como estructura separada.
A11: 9 | B11: Documento de voluntad anticipada | C11: Identificación del usuario (1 a 15) | D11: Documento de voluntad anticipada, fecha y código del prestador donde se encuentra | E11: 14 | F11: 2 | G11: Alfanumérico / Fecha / Alfanumérico | H11: V-10 | I11: Entidad por 2.1 | J11: Analizada en Validación | K11: Documento de voluntad anticipada | L11: HU-014 a HU-017 (Ajustar). | M11: Ninguna | N11: Ajustar las historias existentes (Ajustes por historia). | O11: Sin historias de voluntad anticipada, que el numeral 2.1 pide como estructura separada.
A12: 10 | B12: Categoría de discapacidad | C12: Identificación del usuario (1 a 15) | D12: Categoría de discapacidad | E12: 14 y 15 | F12: 8 | G12: Alfanumérico | H12: V-11 | I12: Entidad por 2.3 | J12: Analizada en Validación | K12: Categorías de discapacidad | L12: Ninguna cubre el CRUD. HU-004 a HU-006 usan el dato; los escenarios de varias discapacidades cumplen. | M12: HU04 (como dato) | N12: CRUD de Categorías de discapacidad: 4 historias nuevas (D-17). | O12: Sin CRUD de discapacidad (8 valores).
A13: 11 | B13: País de residencia habitual | C13: Identificación del usuario (1 a 15) | D13: Código y nombre del país de residencia habitual | E13: 15 | F13: No los enumera | G13: Alfanumérico | H13: V-12 | I13: Reutiliza otra entidad | J13: Analizada en Validación | K13: Países | L13: HU-018 a HU-021 (catálogo de países). HU-004 a HU-006 no nombran el país de residencia (Ajustar). | M13: HU08; HU04 | N13: Nada nuevo: usa Países.
A14: 12 | B14: Municipio de residencia habitual | C14: Identificación del usuario (1 a 15) | D14: Código y nombre del municipio de residencia habitual | E14: 15 | F14: No los enumera | G14: Alfanumérico | H14: V-13 | I14: Entidad por 2.3 | J14: Analizada en Validación | K14: Municipios | L14: HU-026 a HU-029 cubren el CRUD (Ajustar). HU-004 a HU-006 usan el dato; los escenarios de código DANE cumplen. | M14: HU04 (como dato) | N14: Ajustar las historias existentes (Ajustes por historia). | O14: Sin CRUD de municipios; el docente dice que gestionar ese catálogo sí es funcionalidad.
A15: 13 | B15: Pertenencia étnica | C15: Identificación del usuario (1 a 15) | D15: Etnia | E15: 15 | F15: 7 | G15: Alfanumérico | H15: V-14 | I15: Entidad por 2.3 | J15: Analizada en Validación | K15: Etnias | L15: Ninguna cubre el CRUD. HU-004 a HU-006 no nombran el dato (Ajustar). | M15: HU04 (como dato) | N15: CRUD de Etnias: 4 historias nuevas (D-17). | O15: Sin CRUD de etnias (7 valores).
A16: 13 | B16: Pertenencia étnica | C16: Identificación del usuario (1 a 15) | D16: Comunidad étnica | E16: 15 | F16: No los enumera | G16: Alfanumérico | H16: V-15 | I16: Entidad por 2.3 | J16: Analizada en Validación | K16: Comunidades étnicas | L16: Ninguna cubre el CRUD. HU-004 a HU-006 no nombran el dato (Ajustar). | M16: HU04 (como dato) | N16: CRUD de Comunidades étnicas: 4 historias nuevas (D-17). | O16: Sin CRUD de comunidades étnicas.
A17: 14 | B17: Zona territorial de residencia | C17: Identificación del usuario (1 a 15) | D17: Zona territorial de residencia | E17: 15 | F17: 2 | G17: Alfanumérico | H17: V-16 | I17: Campo del paciente | J17: Analizada en Validación | K17: Paciente | L17: HU-004, HU-005, HU-006 no nombran el dato (Ajustar). | M17: HU04 | N17: Escenarios en las historias de su entidad (Ajustes por historia).
A18: 15 | B18: Entidad que responde por el plan de beneficios en salud | C18: Identificación del usuario (1 a 15) | D18: Código y nombre de la entidad que responde por el plan de beneficios | E18: 15 y 16 | F18: No los enumera | G18: Alfanumérico | H18: V-17 | I18: Entidad por 2.3 | J18: Analizada en Validación | K18: Entidades administradoras de planes de beneficios | L18: Ninguna cubre el CRUD. HU-004 a HU-006 no nombran el dato (Ajustar). | M18: HU10 (asignación) y HU11 (CRUD) | N18: CRUD de Entidades administradoras de planes de beneficios: 4 historias nuevas (D-17).
A19: 16 | B19: Código del prestador de servicios de salud que realiza la atención | C19: Contacto con el servicio de salud (16 a 23) | D19: Código del prestador de servicios de salud que realiza la atención | E19: 16 | F19: No los enumera | G19: Alfanumérico | H19: V-18 | I19: Pendiente de decisión | J19: Analizada en Validación | K19: Prestadores si D-05 lo hace catálogo; si no, Atención | L19: HU-007, HU-008, HU-009 usan el código (Ajustar). | M19: HU14, HU16 | N19: Depende de D-05.
A20: 17 | B20: Fecha y hora de inicio de la atención | C20: Contacto con el servicio de salud (16 a 23) | D20: Fecha y hora de inicio de la atención | E20: 16 | F20: No aplica | G20: Fecha | H20: V-19 | I20: Campo de la atención | J20: Analizada en Validación | K20: Atención | L20: HU-007, HU-008, HU-009 (Ajustar). | M20: HU14, HU16 | N20: Escenarios en las historias de su entidad (Ajustes por historia).
A21: 18 | B21: Modalidad y grupo de servicios | C21: Contacto con el servicio de salud (16 a 23) | D21: Modalidad de realización | E21: 16 | F21: 9 | G21: Alfanumérico | H21: V-20 | I21: Entidad por 2.3 | J21: Analizada en Validación | K21: Modalidades de realización | L21: Ninguna cubre el CRUD. HU-007, HU-008 y HU-009 usan el dato (Ajustar). | M21: HU19; catálogo en HU13 | N21: CRUD de Modalidades de realización: 4 historias nuevas (D-17). | O21: HU19 escenario 8 habla de tres tipos de telemedicina; la hoja 16 trae cuatro.
A22: 18 | B22: Modalidad y grupo de servicios | C22: Contacto con el servicio de salud (16 a 23) | D22: Grupo de servicios | E22: 16 | F22: 5 | G22: Alfanumérico | H22: V-21 | I22: Campo de la atención | J22: Analizada en Validación | K22: Atención | L22: HU-007, HU-008, HU-009 (Ajustar). | M22: HU19; catálogo en HU13 | N22: Escenarios en las historias de su entidad (Ajustes por historia).
A23: 19 | B23: Entorno donde se realiza la atención | C23: Contacto con el servicio de salud (16 a 23) | D23: Entorno donde se realiza la atención | E23: 16 | F23: 5 | G23: Alfanumérico | H23: V-22 | I23: Campo de la atención | J23: Analizada en Validación | K23: Atención | L23: HU-007, HU-008, HU-009 | M23: Catálogo en HU13 | N23: Escenarios en las historias de su entidad (Ajustes por historia).
A24: 20 | B24: Vía de ingreso del usuario al servicio de salud | C24: Contacto con el servicio de salud (16 a 23) | D24: Vía de ingreso del usuario al servicio de salud | E24: 16 y 17 | F24: 14 | G24: Alfanumérico | H24: V-23 | I24: Entidad por 2.3 | J24: Analizada en Validación | K24: Vía de ingreso | L24: Ninguna cubre el CRUD. HU-007, HU-008 y HU-009 usan el dato (Ajustar). | M24: Catálogo en HU13 | N24: CRUD de Vía de ingreso: 4 historias nuevas (D-17).
A25: 21 | B25: Causa que motiva la atención | C25: Contacto con el servicio de salud (16 a 23) | D25: Causa que motiva la atención | E25: 17 | F25: 29 | G25: Alfanumérico | H25: V-24 | I25: Entidad por 2.3 | J25: Analizada en Validación | K25: Causa que motiva la atención | L25: Ninguna cubre el CRUD. HU-007, HU-008 y HU-009 usan el dato (Ajustar). | M25: HU18 | N25: CRUD de Causa que motiva la atención: 4 historias nuevas (D-17). | O25: HU18 dice 49 causas; la hoja 17 trae 29 (códigos 21 a 49).
A26: 22 | B26: Triage | C26: Contacto con el servicio de salud (16 a 23) | D26: Fecha, hora y clasificación del triage | E26: 17 y 18 | F26: 5 | G26: Fecha / Alfanumérico | H26: V-25 | I26: Campo de la atención | J26: Analizada en Validación | K26: Atención | L26: HU-007, HU-008, HU-009 | M26: HU15 | N26: Escenarios en las historias de su entidad (Ajustes por historia). | O26: HU15 escenario 7 dice que fecha y hora son obligatorias “según la normativa vigente”; el anexo no tiene columna de obligatoriedad.
A27: 23 | B27: Diagnóstico principal de ingreso | C27: Contacto con el servicio de salud (16 a 23) | D27: Código y nombre del diagnóstico principal de ingreso | E27: 18 | F27: No los enumera | G27: Alfanumérico | H27: V-26 | I27: Entidad por 2.3 | J27: Analizada en Validación | K27: Diagnósticos CIE-10 | L27: HU-030, HU-031, HU-032, HU-033 cubren el CRUD (Ajustar). HU-007, HU-008 y HU-009 usan el código (Ajustar). | M27: HU12 (CRUD de diagnósticos); HU14, HU16 | N27: Ajustar las historias existentes (Ajustes por historia).
A28: 23 | B28: Diagnóstico principal de ingreso | C28: Contacto con el servicio de salud (16 a 23) | D28: Código de enfermedad huérfana | E28: 18 | F28: No los enumera | G28: Alfanumérico | H28: V-27 | I28: Entidad por 2.3 | J28: Analizada en Validación | K28: Enfermedades huérfanas | L28: Ninguna cubre el CRUD. HU-007, HU-008 y HU-009 usan el dato (Ajustar). | M28: HU17 escenario 9 y HU28 escenario 5 (como dato opcional) | N28: CRUD de Enfermedades huérfanas: 4 historias nuevas (D-17). | O28: Sin CRUD de enfermedades huérfanas.
A29: 23 | B29: Diagnóstico principal de ingreso | C29: Contacto con el servicio de salud (16 a 23) | D29: Tipo de diagnóstico principal de ingreso | E29: 18 | F29: 3 | G29: Alfanumérico | H29: V-28 | I29: Campo de la atención | J29: Analizada en Validación | K29: Atención | L29: HU-007, HU-008, HU-009 (Ajustar). | M29: HU28 escenario 2 (en el egreso) | N29: Escenarios en las historias de su entidad (Ajustes por historia).
A30: 24 | B30: Tecnología en salud | C30: Tecnologías en salud (24 a 36) | D30: Tipo de tecnología en salud | E30: 18 | F30: 13 valores | G30: Alfanumérico | H30: No está en Validación | I30: Entidad por 2.3 | J30: Preliminar (sujeta a D-16) | K30: Tipos de tecnología en salud | L30: Ninguna | M30: HU21 (cita 13) | N30: Si D-16 incluye el numeral: CRUD de Tipos de tecnología en salud.
A31: 24 | B31: Tecnología en salud | C31: Tecnologías en salud (24 a 36) | D31: Código de la tecnología en salud | E31: 18 y 19 | F31: Remite a catálogo: 13 filas, una por tipo (CUPS, IUM y catálogos del Ministerio) | G31: Alfanumérico | H31: No está en Validación | I31: Entidad por 2.3 (un catálogo por tipo) | J31: Preliminar (sujeta a D-16) | K31: CUPS, IUM y 9 catálogos del Ministerio | L31: Ninguna | M31: HU21, escenarios 2 y 3 (solo CUPS e IUM) | N31: Si D-16 incluye el numeral: CRUD de CUPS, IUM y 9 catálogos del Ministerio. | O31: Longitud según el tipo: 6 (CUPS), 15 (IUM), 13 a 25 (dispositivo), 19 (sangre, fluidos, órganos, tejidos, células).
A32: 24 | B32: Tecnología en salud | C32: Tecnologías en salud (24 a 36) | D32: Nombre de la tecnología en salud | E32: 19 | F32: Dato abierto | G32: Alfanumérico | H32: No está en Validación | I32: Campo de la tecnología | J32: Preliminar (sujeta a D-16) | K32: Tecnología en salud de la atención (varias por atención) | L32: Ninguna | M32: HU21, escenario 2 | N32: Si D-16 incluye el numeral: dato de Tecnología en salud de la atención (varias por atención). | O32: Nombre según la codificación o el nombre comercial; 200 y 5.
A33: 25 | B33: Finalidad de la tecnología de salud | C33: Tecnologías en salud (24 a 36) | D33: (sin componente) | E33: 19 y 20 | F33: 34 valores (códigos 11 a 44) | G33: Alfanumérico | H33: No está en Validación | I33: Entidad por 2.3 | J33: Preliminar (sujeta a D-16) | K33: Finalidades de la tecnología | L33: Ninguna | M33: HU21, escenario 5 (cita 44) | N33: Si D-16 incluye el numeral: CRUD de Finalidades de la tecnología. | O33: Los compañeros cuentan 44: es el último código, no la cantidad.
A34: 26 | B34: Descripción común del medicamento | C34: Tecnologías en salud (24 a 36) | D34: (sin componente) | E34: 20 | F34: Remite a catálogo DCI | G34: Numérico | H34: No está en Validación | I34: Entidad por 2.3 | J34: Preliminar (sujeta a D-16) | K34: Denominación Común Internacional (DCI) | L34: Ninguna | M34: Ninguna | N34: Si D-16 incluye el numeral: CRUD de Denominación Común Internacional (DCI).
A35: 27 | B35: Fecha de prescripción de la tecnología en salud | C35: Tecnologías en salud (24 a 36) | D35: (sin componente) | E35: 20 | F35: Dato abierto | G35: Fecha | H35: No está en Validación | I35: Campo de la tecnología | J35: Preliminar (sujeta a D-16) | K35: Tecnología en salud de la atención (varias por atención) | L35: Ninguna | M35: Ninguna | N35: Si D-16 incluye el numeral: dato de Tecnología en salud de la atención (varias por atención). | O35: AAAA-MM-DD HH:MM, 16 y 16.
A36: 28 | B36: Dosis prescrita del medicamento | C36: Tecnologías en salud (24 a 36) | D36: Cantidad prescrita de una dosis | E36: 20 | F36: Dato abierto | G36: Numérico | H36: No está en Validación | I36: Campo de la tecnología | J36: Preliminar (sujeta a D-16) | K36: Tecnología en salud de la atención (varias por atención) | L36: Ninguna | M36: Ninguna | N36: Si D-16 incluye el numeral: dato de Tecnología en salud de la atención (varias por atención).
A37: 28 | B37: Dosis prescrita del medicamento | C37: Tecnologías en salud (24 a 36) | D37: Código de la unidad de medida de la dosis | E37: 20 | F37: Remite a catálogo UMM | G37: Alfanumérico | H37: No está en Validación | I37: Entidad por 2.3 | J37: Preliminar (sujeta a D-16) | K37: Unidades de medida (UMM) | L37: Ninguna | M37: Ninguna | N37: Si D-16 incluye el numeral: CRUD de Unidades de medida (UMM).
A38: 29 | B38: Vía de administración de la tecnologia | C38: Tecnologías en salud (24 a 36) | D38: (sin componente) | E38: 20 | F38: Remite a catálogo VAD | G38: Alfanumérico | H38: No está en Validación | I38: Entidad por 2.3 | J38: Preliminar (sujeta a D-16) | K38: Vías de administración (VAD) | L38: Ninguna | M38: Ninguna | N38: Si D-16 incluye el numeral: CRUD de Vías de administración (VAD).
A39: 30 | B39: Duración prescrita del tratamiento | C39: Tecnologías en salud (24 a 36) | D39: Cantidad | E39: 20 y 21 | F39: Dato abierto | G39: Numérico | H39: No está en Validación | I39: Campo de la tecnología | J39: Preliminar (sujeta a D-16) | K39: Tecnología en salud de la atención (varias por atención) | L39: Ninguna | M39: Ninguna | N39: Si D-16 incluye el numeral: dato de Tecnología en salud de la atención (varias por atención).
A40: 30 | B40: Duración prescrita del tratamiento | C40: Tecnologías en salud (24 a 36) | D40: Código de unidad de tiempo | E40: 21 | F40: 7 valores | G40: Numérico | H40: No está en Validación | I40: Entidad por 2.3 | J40: Preliminar (sujeta a D-16) | K40: Unidades de tiempo | L40: Ninguna | M40: Ninguna | N40: Si D-16 incluye el numeral: CRUD de Unidades de tiempo.
A41: 31 | B41: Frecuencia de administración de la tecnologia prescrita | C41: Tecnologías en salud (24 a 36) | D41: Cantidad | E41: 21 | F41: Dato abierto | G41: Numérico | H41: No está en Validación | I41: Campo de la tecnología | J41: Preliminar (sujeta a D-16) | K41: Tecnología en salud de la atención (varias por atención) | L41: Ninguna | M41: Ninguna | N41: Si D-16 incluye el numeral: dato de Tecnología en salud de la atención (varias por atención).
A42: 31 | B42: Frecuencia de administración de la tecnologia prescrita | C42: Tecnologías en salud (24 a 36) | D42: Código de unidad de tiempo | E42: 21 | F42: 7 valores | G42: Numérico | H42: No está en Validación | I42: Reutiliza otra entidad | J42: Preliminar (sujeta a D-16) | K42: Unidades de tiempo | L42: Ninguna | M42: Ninguna | N42: Si D-16 incluye el numeral: usa Unidades de tiempo. | O42: Mismo catálogo que el 30.
A43: 32 | B43: Dosis administrada del medicamento institucionalmente | C43: Tecnologías en salud (24 a 36) | D43: Cantidad administrada de una dosis | E43: 21 | F43: Dato abierto | G43: Numérico | H43: No está en Validación | I43: Campo de la tecnología | J43: Preliminar (sujeta a D-16) | K43: Tecnología en salud de la atención (varias por atención) | L43: Ninguna | M43: Ninguna | N43: Si D-16 incluye el numeral: dato de Tecnología en salud de la atención (varias por atención).
A44: 32 | B44: Dosis administrada del medicamento institucionalmente | C44: Tecnologías en salud (24 a 36) | D44: Código de la unidad de medida de la dosis | E44: 21 | F44: Remite a catálogo UMM | G44: Alfanumérico | H44: No está en Validación | I44: Reutiliza otra entidad | J44: Preliminar (sujeta a D-16) | K44: Unidades de medida (UMM) | L44: Ninguna | M44: Ninguna | N44: Si D-16 incluye el numeral: usa Unidades de medida (UMM).
A45: 33 | B45: Fecha de entrega de la tecnología en salud | C45: Tecnologías en salud (24 a 36) | D45: (sin componente) | E45: 21 | F45: Dato abierto | G45: Fecha | H45: No está en Validación | I45: Campo de la tecnología | J45: Preliminar (sujeta a D-16) | K45: Tecnología en salud de la atención (varias por atención) | L45: Ninguna | M45: Ninguna | N45: Si D-16 incluye el numeral: dato de Tecnología en salud de la atención (varias por atención).
A46: 34 | B46: Dosis entregadas del medicamento | C46: Tecnologías en salud (24 a 36) | D46: Cantidad entregada de una dosis | E46: 21 | F46: Dato abierto | G46: Numérico | H46: No está en Validación | I46: Campo de la tecnología | J46: Preliminar (sujeta a D-16) | K46: Tecnología en salud de la atención (varias por atención) | L46: Ninguna | M46: Ninguna | N46: Si D-16 incluye el numeral: dato de Tecnología en salud de la atención (varias por atención).
A47: 34 | B47: Dosis entregadas del medicamento | C47: Tecnologías en salud (24 a 36) | D47: Código de la unidad de medida de la dosis | E47: 21 | F47: Remite a catálogo UMM | G47: Alfanumérico | H47: No está en Validación | I47: Reutiliza otra entidad | J47: Preliminar (sujeta a D-16) | K47: Unidades de medida (UMM) | L47: Ninguna | M47: Ninguna | N47: Si D-16 incluye el numeral: usa Unidades de medida (UMM).
A48: 35 | B48: Número de unidades entregadas o aplicadas de la tecnología | C48: Tecnologías en salud (24 a 36) | D48: Cantidad | E48: 21 | F48: Dato abierto | G48: Numérico | H48: No está en Validación | I48: Campo de la tecnología | J48: Preliminar (sujeta a D-16) | K48: Tecnología en salud de la atención (varias por atención) | L48: Ninguna | M48: Ninguna | N48: Si D-16 incluye el numeral: dato de Tecnología en salud de la atención (varias por atención). | O48: Cuatro enteros y dos decimales con coma.
A49: 35 | B49: Número de unidades entregadas o aplicadas de la tecnología | C49: Tecnologías en salud (24 a 36) | D49: Código de unidad de medida | E49: 21 | F49: Remite a catálogo FMM (formas farmacéuticas) | G49: Alfanumérico | H49: No está en Validación | I49: Entidad por 2.3 | J49: Preliminar (sujeta a D-16) | K49: Formas farmacéuticas (FMM) | L49: Ninguna | M49: Ninguna | N49: Si D-16 incluye el numeral: CRUD de Formas farmacéuticas (FMM). | O49: Remite a FMM, no a UMM.
A50: 36 | B50: Identificación del talento humano en salud que realiza, entrega o aplica la tecnología de salud | C50: Tecnologías en salud (24 a 36) | D50: Tipo de identificación de la persona | E50: 21 | F50: 5 valores (CC, CE, PA, PE, TI) | G50: Alfanumérico | H50: No está en Validación | I50: Reutiliza otra entidad | J50: Preliminar (sujeta a D-16) | K50: Tipos de documento de identificación (5 de los 14) | L50: Ninguna | M50: Ninguna | N50: Si D-16 incluye el numeral: usa Tipos de documento de identificación (5 de los 14). | O50: Son 5 de los 14 tipos del numeral 2.
A51: 36 | B51: Identificación del talento humano en salud que realiza, entrega o aplica la tecnología de salud | C51: Tecnologías en salud (24 a 36) | D51: Número de identificación de la persona | E51: 22 | F51: Dato abierto | G51: Alfanumérico | H51: No está en Validación | I51: Campo de la tecnología | J51: Preliminar (sujeta a D-16) | K51: Tecnología en salud de la atención (varias por atención) | L51: Ninguna | M51: Ninguna | N51: Si D-16 incluye el numeral: dato de Tecnología en salud de la atención (varias por atención). | O51: Inscrito en ReTHUS, según la definición.
A52: 37 | B52: Diagnóstico principal de egreso | C52: Resultados del uso de las tecnologías en salud (37 a 49) | D52: Código del diagnóstico principal (CIE-10 o enfermedad huérfana) | E52: 22 | F52: Remite a catálogo CIE-10 y de enfermedades huérfanas | G52: Alfanumérico | H52: No está en Validación | I52: Reutiliza otra entidad | J52: Preliminar (sujeta a D-16) | K52: Diagnósticos CIE-10 y Enfermedades huérfanas | L52: Ninguna registra el dato; el catálogo es el de HU-030 a HU-033 | M52: HU28 | N52: Si D-16 incluye el numeral: usa Diagnósticos CIE-10 y Enfermedades huérfanas.
A53: 37 | B53: Diagnóstico principal de egreso | C53: Resultados del uso de las tecnologías en salud (37 a 49) | D53: Nombre del diagnóstico principal | E53: 22 | F53: Nombre correspondiente al código | G53: Alfanumérico | H53: No está en Validación | I53: Reutiliza otra entidad | J53: Preliminar (sujeta a D-16) | K53: Diagnósticos CIE-10 | L53: Ninguna registra el dato; el catálogo es el de HU-030 a HU-033 | M53: HU28 | N53: Si D-16 incluye el numeral: usa Diagnósticos CIE-10.
A54: 37 | B54: Diagnóstico principal de egreso | C54: Resultados del uso de las tecnologías en salud (37 a 49) | D54: Tipo de diagnóstico principal de ingreso | E54: 22 | F54: 3 valores | G54: Alfanumérico | H54: No está en Validación | I54: Campo de la atención | J54: Preliminar (sujeta a D-16) | K54: Atención (egreso) | L54: Ninguna | M54: HU28, escenario 2 | N54: Si D-16 incluye el numeral: dato de Atención (egreso). | O54: La hoja lo llama de ingreso dentro del elemento de egreso.
A55: 38 | B55: Diagnóstico relacionado | C55: Resultados del uso de las tecnologías en salud (37 a 49) | D55: Código del diagnóstico relacionado (CIE-10 o enfermedad huérfana) | E55: 22 | F55: Remite a catálogo CIE-10 y de enfermedades huérfanas | G55: Alfanumérico | H55: No está en Validación | I55: Reutiliza otra entidad | J55: Preliminar (sujeta a D-16) | K55: Diagnósticos CIE-10 y Enfermedades huérfanas | L55: Ninguna registra el dato; el catálogo es el de HU-030 a HU-033 | M55: HU17 | N55: Si D-16 incluye el numeral: usa Diagnósticos CIE-10 y Enfermedades huérfanas. | O55: La hoja no fija cuántos.
A56: 38 | B56: Diagnóstico relacionado | C56: Resultados del uso de las tecnologías en salud (37 a 49) | D56: Nombre del diagnóstico relacionado | E56: 22 | F56: Nombre correspondiente al código | G56: Alfanumérico | H56: No está en Validación | I56: Reutiliza otra entidad | J56: Preliminar (sujeta a D-16) | K56: Diagnósticos CIE-10 | L56: Ninguna registra el dato; el catálogo es el de HU-030 a HU-033 | M56: HU17 | N56: Si D-16 incluye el numeral: usa Diagnósticos CIE-10.
A57: 39 | B57: Resultado de evaluación de valoración clínica o del resultado en salud | C57: Resultados del uso de las tecnologías en salud (37 a 49) | D57: Fecha del resultado | E57: 22 | F57: Dato abierto | G57: Fecha | H57: No está en Validación | I57: Campo de la atención | J57: Preliminar (sujeta a D-16) | K57: Atención (egreso) | L57: Ninguna | M57: Ninguna | N57: Si D-16 incluye el numeral: dato de Atención (egreso).
A58: 39 | B58: Resultado de evaluación de valoración clínica o del resultado en salud | C58: Resultados del uso de las tecnologías en salud (37 a 49) | D58: Identificación del instrumento para medir el resultado observado | E58: 22 y 23 | F58: Remite a catálogo | G58: Alfanumérico | H58: No está en Validación | I58: Entidad por 2.3 | J58: Preliminar (sujeta a D-16) | K58: Instrumentos de evaluación del resultado | L58: Ninguna | M58: Ninguna | N58: Si D-16 incluye el numeral: CRUD de Instrumentos de evaluación del resultado.
A59: 39 | B59: Resultado de evaluación de valoración clínica o del resultado en salud | C59: Resultados del uso de las tecnologías en salud (37 a 49) | D59: Código del parámetro del resultado observado | E59: 23 | F59: Remite a catálogo | G59: Alfanumérico | H59: No está en Validación | I59: Entidad por 2.3 | J59: Preliminar (sujeta a D-16) | K59: Parámetros del resultado | L59: Ninguna | M59: Ninguna | N59: Si D-16 incluye el numeral: CRUD de Parámetros del resultado.
A60: 39 | B60: Resultado de evaluación de valoración clínica o del resultado en salud | C60: Resultados del uso de las tecnologías en salud (37 a 49) | D60: Valor del resultado observado | E60: 23 | F60: Dato abierto | G60: Decimal | H60: No está en Validación | I60: Campo de la atención | J60: Preliminar (sujeta a D-16) | K60: Atención (egreso) | L60: Ninguna | M60: Ninguna | N60: Si D-16 incluye el numeral: dato de Atención (egreso). | O60: La hoja dice “tres (2) decimales”.
A61: 40 | B61: Diagnósticos de la complicación | C61: Resultados del uso de las tecnologías en salud (37 a 49) | D61: Código de la complicación (CIE-10 o enfermedad huérfana) | E61: 23 | F61: Remite a catálogo CIE-10 y de enfermedades huérfanas | G61: Alfanumérico | H61: No está en Validación | I61: Reutiliza otra entidad | J61: Preliminar (sujeta a D-16) | K61: Diagnósticos CIE-10 y Enfermedades huérfanas | L61: Ninguna registra el dato; el catálogo es el de HU-030 a HU-033 | M61: Ninguna | N61: Si D-16 incluye el numeral: usa Diagnósticos CIE-10 y Enfermedades huérfanas.
A62: 40 | B62: Diagnósticos de la complicación | C62: Resultados del uso de las tecnologías en salud (37 a 49) | D62: Nombre del diagnóstico de la complicación | E62: 23 | F62: Nombre correspondiente al código | G62: Alfanumérico | H62: No está en Validación | I62: Reutiliza otra entidad | J62: Preliminar (sujeta a D-16) | K62: Diagnósticos CIE-10 | L62: Ninguna registra el dato; el catálogo es el de HU-030 a HU-033 | M62: Ninguna | N62: Si D-16 incluye el numeral: usa Diagnósticos CIE-10.
A63: 41 | B63: Condición y destino del usuario al egreso | C63: Resultados del uso de las tecnologías en salud (37 a 49) | D63: (sin componente) | E63: 23 | F63: 7 valores | G63: Alfanumérico | H63: No está en Validación | I63: Entidad por 2.3 | J63: Preliminar (sujeta a D-16) | K63: Condiciones y destinos al egreso | L63: Ninguna | M63: HU22; catálogo en HU13 | N63: Si D-16 incluye el numeral: CRUD de Condiciones y destinos al egreso. | O63: Aplica a la salida de urgencias u hospitalización.
A64: 42 | B64: Diagnóstico de la causa básica de muerte | C64: Resultados del uso de las tecnologías en salud (37 a 49) | D64: Código de la causa básica de muerte (CIE-10 o enfermedad huérfana) | E64: 23 | F64: Remite a catálogo CIE-10 y de enfermedades huérfanas | G64: Alfanumérico | H64: No está en Validación | I64: Reutiliza otra entidad | J64: Preliminar (sujeta a D-16) | K64: Diagnósticos CIE-10 y Enfermedades huérfanas | L64: Ninguna registra el dato; el catálogo es el de HU-030 a HU-033 | M64: HU22, escenario 2 | N64: Si D-16 incluye el numeral: usa Diagnósticos CIE-10 y Enfermedades huérfanas.
A65: 42 | B65: Diagnóstico de la causa básica de muerte | C65: Resultados del uso de las tecnologías en salud (37 a 49) | D65: Nombre del diagnóstico de la causa básica de la muerte | E65: 23 | F65: Nombre correspondiente al código | G65: Alfanumérico | H65: No está en Validación | I65: Reutiliza otra entidad | J65: Preliminar (sujeta a D-16) | K65: Diagnósticos CIE-10 | L65: Ninguna registra el dato; el catálogo es el de HU-030 a HU-033 | M65: HU22, escenario 10 | N65: Si D-16 incluye el numeral: usa Diagnósticos CIE-10.
A66: 43 | B66: Fecha y hora de la finalización de la atención | C66: Resultados del uso de las tecnologías en salud (37 a 49) | D66: (sin componente) | E66: 24 | F66: Dato abierto | G66: Fecha | H66: No está en Validación | I66: Campo de la atención | J66: Preliminar (sujeta a D-16) | K66: Atención (egreso) | L66: Ninguna | M66: HU22, escenario 4 | N66: Si D-16 incluye el numeral: dato de Atención (egreso). | O66: En caso de muerte, fecha y hora del deceso.
A67: 44 | B67: Código del prestador de servicios de salud a donde se refiere | C67: Resultados del uso de las tecnologías en salud (37 a 49) | D67: (sin componente) | E67: 24 | F67: Remite al REPS o al código del Ministerio | G67: Alfanumérico | H67: No está en Validación | I67: Pendiente de decisión | J67: Preliminar (sujeta a D-16) | K67: Prestadores si D-05 lo hace catálogo | L67: Ninguna | M67: HU22, escenario 3 | N67: Si D-16 incluye el numeral: depende de D-05. | O67: Si no se refiere, no se registra.
A68: 45 | B68: Incapacidad | C68: Resultados del uso de las tecnologías en salud (37 a 49) | D68: Alcance de la incapacidad | E68: 24 | F68: 2 valores | G68: Alfanumérico | H68: No está en Validación | I68: Campo de la atención | J68: Preliminar (sujeta a D-16) | K68: Atención (egreso) | L68: Ninguna | M68: Ninguna | N68: Si D-16 incluye el numeral: dato de Atención (egreso).
A69: 45 | B69: Incapacidad | C69: Resultados del uso de las tecnologías en salud (37 a 49) | D69: Días de incapacidad | E69: 24 | F69: Dato abierto (entre 1 y 999) | G69: Numérico | H69: No está en Validación | I69: Campo de la atención | J69: Preliminar (sujeta a D-16) | K69: Atención (egreso) | L69: Ninguna | M69: Ninguna | N69: Si D-16 incluye el numeral: dato de Atención (egreso).
A70: 46 | B70: Días de licencia de maternidad | C70: Resultados del uso de las tecnologías en salud (37 a 49) | D70: (sin componente) | E70: 24 | F70: Dato abierto (entre 1 y 999) | G70: Numérico | H70: No está en Validación | I70: Campo de la atención | J70: Preliminar (sujeta a D-16) | K70: Atención (egreso) | L70: Ninguna | M70: Ninguna | N70: Si D-16 incluye el numeral: dato de Atención (egreso).
A71: 47 | B71: Antecedentes de salud | C71: Resultados del uso de las tecnologías en salud (37 a 49) | D71: Código que indica si la persona tiene alergias | E71: 24 | F71: 6 valores | G71: Alfanumérico | H71: No está en Validación | I71: Entidad por 2.3 | J71: Preliminar (sujeta a D-16) | K71: Tipos de alérgeno | L71: Ninguna | M71: HU20 (cita 6) | N71: Si D-16 incluye el numeral: CRUD de Tipos de alérgeno. | O71: Varias por persona (“en múltiples opciones”).
A72: 47 | B72: Antecedentes de salud | C72: Resultados del uso de las tecnologías en salud (37 a 49) | D72: Nombre del alérgeno | E72: 24 | F72: Dato abierto | G72: Alfanumérico | H72: No está en Validación | I72: Campo del antecedente | J72: Preliminar (sujeta a D-16) | K72: Antecedentes de alergia (varios) | L72: Ninguna | M72: HU20, escenario 2 | N72: Si D-16 incluye el numeral: dato de Antecedentes de alergia (varios).
A73: 47 | B73: Antecedentes de salud | C73: Resultados del uso de las tecnologías en salud (37 a 49) | D73: Condición de salud familiar | E73: 24 | F73: Remite a catálogo CIE-10 y de enfermedades huérfanas | G73: Alfanumérico | H73: No está en Validación | I73: Reutiliza otra entidad | J73: Preliminar (sujeta a D-16) | K73: Diagnósticos CIE-10 y Enfermedades huérfanas | L73: Ninguna registra el dato; el catálogo es el de HU-030 a HU-033 | M73: HU20, escenario 9 | N73: Si D-16 incluye el numeral: usa Diagnósticos CIE-10 y Enfermedades huérfanas. | O73: Varios por persona.
A74: 47 | B74: Antecedentes de salud | C74: Resultados del uso de las tecnologías en salud (37 a 49) | D74: Parentesco | E74: 24 | F74: 4 valores | G74: Alfanumérico | H74: No está en Validación | I74: Campo del antecedente | J74: Preliminar (sujeta a D-16) | K74: Antecedentes familiares (varios) | L74: Ninguna | M74: HU20, escenario 4 | N74: Si D-16 incluye el numeral: dato de Antecedentes familiares (varios).
A75: 48 | B75: Exposición a factores de riesgo | C75: Resultados del uso de las tecnologías en salud (37 a 49) | D75: Tipo de factor de riesgo | E75: 24 | F75: 6 valores | G75: Numérico | H75: No está en Validación | I75: Entidad por 2.3 | J75: Preliminar (sujeta a D-16) | K75: Tipos de factor de riesgo | L75: Ninguna | M75: HU29 (cita 6) | N75: Si D-16 incluye el numeral: CRUD de Tipos de factor de riesgo. | O75: Tipo Numérico con códigos 01 a 06.
A76: 48 | B76: Exposición a factores de riesgo | C76: Resultados del uso de las tecnologías en salud (37 a 49) | D76: Nombre del factor de riesgo | E76: 24 | F76: Dato abierto | G76: Alfanumérico | H76: No está en Validación | I76: Campo del antecedente | J76: Preliminar (sujeta a D-16) | K76: Factores de riesgo (varios) | L76: Ninguna | M76: HU29, escenario 2 | N76: Si D-16 incluye el numeral: dato de Factores de riesgo (varios).
A77: 49 | B77: Identificación del talento humano en salud que realizó el egreso | C77: Resultados del uso de las tecnologías en salud (37 a 49) | D77: Tipo de documento de identificación | E77: 25 | F77: 5 valores (CC, CE, PA, PE, TI) | G77: Alfanumérico | H77: No está en Validación | I77: Reutiliza otra entidad | J77: Preliminar (sujeta a D-16) | K77: Tipos de documento de identificación (5 de los 14) | L77: Ninguna | M77: Ninguna | N77: Si D-16 incluye el numeral: usa Tipos de documento de identificación (5 de los 14).
A78: 49 | B78: Identificación del talento humano en salud que realizó el egreso | C78: Resultados del uso de las tecnologías en salud (37 a 49) | D78: Número de documento de identificación | E78: 25 | F78: Dato abierto | G78: Alfanumérico | H78: No está en Validación | I78: Campo de la atención | J78: Preliminar (sujeta a D-16) | K78: Atención (egreso) | L78: Ninguna | M78: Ninguna | N78: Si D-16 incluye el numeral: dato de Atención (egreso). | O78: Inscrito en ReTHUS.
A80: Elementos del anexo | F80: =SUMPRODUCT((A2:A78<>"")/COUNTIF(A2:A78,A2:A78&"")) -> 49
A81: Componentes (filas) | F81: =COUNTA(D2:D78) -> 77
A82: Componentes analizados en Validación (elementos 1 a 23) | F82: =COUNTIF(J2:J78,"Analizada en Validación") -> 28
A83: Componentes con clasificación preliminar (elementos 24 a 49) | F83: =COUNTIF(J2:J78,"Preliminar (sujeta a D-16)") -> 49
A84: Filas de entidad nueva entre los elementos 24 a 49 | F84: =COUNTIFS(J2:J78,"Preliminar (sujeta a D-16)",I2:I78,"Entidad por 2.3*") -> 13
A85: Componentes del 24 al 49 sin ninguna historia de los compañeros | F85: =COUNTIFS(J2:J78,"Preliminar (sujeta a D-16)",M2:M78,"Ninguna") -> 29
A87: Cómo leerla: los elementos 1 a 23 repiten la clasificación de la hoja Validación. Los 24 a 49 tienen clasificación preliminar con las mismas reglas: quedan fuera de la primera fase hasta que el docente responda D-16. Del 24 al 49 salen 6 listas de más de 5 valores (tipo de tecnología 13, finalidad 34, unidad de tiempo 7, condición de egreso 7, tipo de alérgeno 6, tipo de factor de riesgo 6) y entre 9 y 17 catálogos externos (CUPS, IUM, DCI, UMM, VAD, FMM, instrumentos y parámetros del resultado, y 9 catálogos “que establezca el Ministerio” para el código de la tecnología, contados como uno o por separado). Con una historia por operación serían entre 60 y 92 historias más; con una por entidad, entre 15 y 23, más las de registrar, consultar y modificar la tecnología en salud de la atención.

Sheet Backlog v3
A1: ID | B1: Título | C1: Bloque | D1: Numerales del anexo o de la guía | E1: Viene de | F1: Acción | G1: Tanda | H1: Estado | I1: Archivo | J1: Ajustes del tablero que recibe | K1: Comentarios del docente que recibe
A2: HU-001 | B2: Inicio de sesión con permisos por cargo | C2: Inicio de sesión | D2: Guía 2.4 | E2: HU-001, HU-002, HU-003 | F2: Fusionar | G2: T1 | H2: Borrador | I2: backlog-v3/backlog-v3-tanda-1-acceso-y-paciente.md | J2: =COUNTIF('Ajustes por historia'!I:I,A2) -> 8 | K2: =COUNTIF(Retroalimentación!F:F,A2) -> 7
A3: HU-004 | B3: Registro de un paciente | C3: Gestión de pacientes | D3: 1 a 15 | E3: HU-004 | F3: Editar | G3: T1 | H3: Borrador | I3: backlog-v3/backlog-v3-tanda-1-acceso-y-paciente.md | J3: =COUNTIF('Ajustes por historia'!I:I,A3) -> 6 | K3: =COUNTIF(Retroalimentación!F:F,A3) -> 2
A4: HU-005 | B4: Consulta de un paciente | C4: Gestión de pacientes | D4: 1 a 15 | E4: HU-005 | F4: Editar | G4: T1 | H4: Borrador | I4: backlog-v3/backlog-v3-tanda-1-acceso-y-paciente.md | J4: =COUNTIF('Ajustes por historia'!I:I,A4) -> 5 | K4: =COUNTIF(Retroalimentación!F:F,A4) -> 2
A5: HU-006 | B5: Actualización y corrección de los datos de un paciente | C5: Gestión de pacientes | D5: 1 a 15 | E5: HU-006 | F5: Editar | G5: T1 | H5: Borrador | I5: backlog-v3/backlog-v3-tanda-1-acceso-y-paciente.md | J5: =COUNTIF('Ajustes por historia'!I:I,A5) -> 4 | K5: =COUNTIF(Retroalimentación!F:F,A5) -> 2
A6: HU-007 | B6: Registro de información clínica | C6: Contacto con el servicio de salud | D6: 16 a 23 | E6: HU-007 | F6: Editar | G6: T2 | H6: Borrador | I6: backlog-v3/backlog-v3-tanda-2-atencion.md | J6: =COUNTIF('Ajustes por historia'!I:I,A6) -> 6 | K6: =COUNTIF(Retroalimentación!F:F,A6) -> 2
A7: HU-008 | B7: Consulta de la información clínica de un paciente | C7: Contacto con el servicio de salud | D7: 16 a 23 | E7: HU-008 | F7: Editar | G7: T2 | H7: Borrador | I7: backlog-v3/backlog-v3-tanda-2-atencion.md | J7: =COUNTIF('Ajustes por historia'!I:I,A7) -> 6 | K7: =COUNTIF(Retroalimentación!F:F,A7) -> 2
A8: HU-009 | B8: Modificación de la información clínica registrada | C8: Contacto con el servicio de salud | D8: 16 a 23 | E8: HU-009 | F8: Editar | G8: T2 | H8: Borrador | I8: backlog-v3/backlog-v3-tanda-2-atencion.md | J8: =COUNTIF('Ajustes por historia'!I:I,A8) -> 3 | K8: =COUNTIF(Retroalimentación!F:F,A8) -> 2
A9: HU-043 | B9: Anulación de una atención registrada por error | C9: Contacto con el servicio de salud | D9: 16 a 23 | E9: Nueva | F9: Escribir | G9: T2 | H9: Borrador | I9: backlog-v3/backlog-v3-tanda-2-atencion.md | J9: =COUNTIF('Ajustes por historia'!I:I,A9) -> 0 | K9: =COUNTIF(Retroalimentación!F:F,A9) -> 0
A10: HU-010 | B10: Registro de la oposición a la presunción legal de donación | C10: Oposición a la donación | D10: 8 | E10: HU-010 | F10: Editar | G10: T3 | H10: Borrador | I10: backlog-v3/backlog-v3-tanda-3-oposicion-y-voluntad.md | J10: =COUNTIF('Ajustes por historia'!I:I,A10) -> 4 | K10: =COUNTIF(Retroalimentación!F:F,A10) -> 2
A11: HU-011 | B11: Consulta de la oposición a la presunción legal de donación | C11: Oposición a la donación | D11: 8 | E11: HU-011 | F11: Editar | G11: T3 | H11: Borrador | I11: backlog-v3/backlog-v3-tanda-3-oposicion-y-voluntad.md | J11: =COUNTIF('Ajustes por historia'!I:I,A11) -> 3 | K11: =COUNTIF(Retroalimentación!F:F,A11) -> 2
A12: HU-012 | B12: Actualización de la oposición a la presunción legal de donación | C12: Oposición a la donación | D12: 8 | E12: HU-012 | F12: Editar | G12: T3 | H12: Borrador | I12: backlog-v3/backlog-v3-tanda-3-oposicion-y-voluntad.md | J12: =COUNTIF('Ajustes por historia'!I:I,A12) -> 3 | K12: =COUNTIF(Retroalimentación!F:F,A12) -> 2
A13: HU-013 | B13: Anulación de un registro de oposición hecho por error | C13: Oposición a la donación | D13: 8 | E13: HU-013 | F13: Editar | G13: T3 | H13: Borrador | I13: backlog-v3/backlog-v3-tanda-3-oposicion-y-voluntad.md | J13: =COUNTIF('Ajustes por historia'!I:I,A13) -> 3 | K13: =COUNTIF(Retroalimentación!F:F,A13) -> 2
... A31: HU-042 | B31: Catálogo de enfermedades huérfanas: carga y mantenimiento | C31: Catálogos | D31: 23 | E31: Nueva | F31: Escribir | G31: T5 | H31: Borrador | I31: backlog-v3/backlog-v3-tanda-5-diagnosticos-y-catalogos-atencion.md | J31: =COUNTIF('Ajustes por historia'!I:I,A31) -> 0 | K31: =COUNTIF(Retroalimentación!F:F,A31) -> 0
A33: Historias del backlog v3 | D33: =COUNTA(A2:A31) -> 30
A34: Editar | D34: =COUNTIF(F2:F31,"Editar") -> 15
A35: Fusionar | D35: =COUNTIF(F2:F31,"Fusionar") -> 5
A36: Reescribir | D36: =COUNTIF(F2:F31,"Reescribir") -> 0
A37: Escribir (nuevas) | D37: =COUNTIF(F2:F31,"Escribir") -> 10
A38: En borrador o más avanzadas | D38: =COUNTA(H2:H31)-COUNTIF(H2:H31,"Por escribir") -> 30
A39: Tarjetas que se archivan (absorbidas) | D39: 13
A40: Ajustes del tablero sin historia destino | D40: =COUNTIF('Ajustes por historia'!I:I,"Sin destino") -> 0
A41: Comentarios del docente sin historia destino | D41: =COUNTIF(Retroalimentación!F:F,"Sin destino") -> 0

Sheet Historias
A1: ID | B1: Título | C1: Funcionalidad relacionada | D1: Como | E1: Quiero | F1: Para | G1: Valor de negocio | H1: Prioridad | I1: Estimación relativa | J1: HU asociada | K1: Reglas de negocio | L1: Precondiciones | M1: N.º escenarios | N1: Dependencias | O1: Supuestos o asuntos pendientes | P1: Tanda | Q1: Retroalimentación específica del docente | R1: Resultado de la validación | S1: Qué ajustar, con número de escenario | T1: Filas de validación que lo deciden | U1: Responsable | V1: Estado | W1: ¿Se puede tomar? | X1: Alerta | Y1: Fuente del análisis | Z1: Detalle de la fuente | AA1: Bloqueada por | AB1: Revisor | AC1: Fecha de inicio | AD1: Fecha de cierre | AE1: Cambios realizados | AF1: ID en Trello
A2: HU-001 | B2: Acceso del auxiliar de admisión | C2: Control de acceso | D2: auxiliar de admisión | E2: identificarme antes de trabajar sobre la información de un paciente | F2: que quede constancia de quién registró cada dato | G2: Sin identificación previa no se puede saber quién hizo cada registro ni limitar quién accede a la información del paciente. | H2: Alta (Must) | I2: 0 | J2: N/A | K2: • El sistema implementa una funcionalidad básica de inicio de sesión [2.4]. • El registro de usuarios y la recuperación de cuenta no forman parte de esta fase [2.4]. | L2: • Las credenciales del auxiliar existen en el sistema. | M2: =COUNTIF(Escenarios!$A:$A,A2) -> 10 | N2: Prerrequisito de HU-004, HU-005 y HU-006. | O2: Quién crea las credenciales, sin definir. El documento descarta el módulo que lo haría [2.4]. | P2: tanda-1-acceso-y-pacientes | Q2: =IF(COUNTIF(Retroalimentación!$A:$A,A2)>0,"Sí: "&COUNTIF(Retroalimentación!$A:$A,A2)&" textos","No") -> Sí: 3 textos | R2: Ajustar | S2: Poner el tiempo de inactividad y decir qué puede hacer el auxiliar. Más el ajuste general (mockup y estimación). Detalle en Ajustes por historia: 3 filas. | T2: Sin fila del anexo (numeral 2.4) | U2: Juan Fernando | V2: Analizado | W2: =IF(OR(V2="",V2="Libre"),"Disponible",IF(V2="Bloqueado","Bloqueada: "&IF(AA2="","falta motivo",AA2),IF(OR(V2="Aprobado",V2="En Trello"),"Cerrada",IF(V2="En revisión","En revisión: "&IF(AB2="","falta revisor",AB2),IF(V2="Analizado","Lista para revisar: analizó "&IF(U2="","falta responsable",U2),IF(U2="","Falta responsable","Ocupada por "&U2)))))) -> Lista para revisar: analizó Juan Fernando | X2: =IF(AND(AB2<>"",AB2=U2),"El revisor no puede ser el responsable",IF(AND(OR(V2="Analizado",V2="En revisión",V2="Aprobado"),Y2=""),"Falta la fuente del análisis",IF(AND(OR(V2="Aprobado",V2="En Trello"),AB2=""),"Aprobado sin revisor",""))) | Y2: Prompt con IA | Z2: Comentarios del docente en Trello (exportación del 19 oct 2026), anexo por numeral y guía. Detalle en Ajustes por historia. | AC2: 46315
A3: HU-002 | B3: Acceso del médico tratante | C3: Control de acceso | D3: médico tratante | E3: identificarme antes de consultar o registrar información clínica | F3: que la historia clínica de un paciente no quede disponible para cualquiera | G3: La información clínica es reservada. El control de acceso es lo que sostiene esa reserva dentro del sistema. | H3: Alta (Must) | I3: 0 | J3: N/A | K3: • El sistema implementa una funcionalidad básica de inicio de sesión [2.4]. • El registro de usuarios y la recuperación de cuenta no forman parte de esta fase [2.4]. | L3: • Las credenciales del médico tratante existen en el sistema. | M3: =COUNTIF(Escenarios!$A:$A,A3) -> 10 | N3: Prerrequisito de las historias del módulo de contacto con el servicio de salud. | O3: La separación de permisos entre roles es decisión del equipo, no del documento. Si no se adopta, los escenarios 5 y 6 se retiran. | P3: tanda-1-acceso-y-pacientes | Q3: =IF(COUNTIF(Retroalimentación!$A:$A,A3)>0,"Sí: "&COUNTIF(Retroalimentación!$A:$A,A3)&" textos","No") -> Sí: 2 textos | R3: Ajustar | S3: Tiempo de inactividad, qué datos ve el médico y por qué su acceso va aparte. Más el ajuste general (mockup y estimación). Detalle en Ajustes por historia: 3 filas. | T3: Sin fila del anexo (numeral 2.4) | U3: Juan Fernando | V3: Analizado | W3: =IF(OR(V3="",V3="Libre"),"Disponible",IF(V3="Bloqueado","Bloqueada: "&IF(AA3="","falta motivo",AA3),IF(OR(V3="Aprobado",V3="En Trello"),"Cerrada",IF(V3="En revisión","En revisión: "&IF(AB3="","falta revisor",AB3),IF(V3="Analizado","Lista para revisar: analizó "&IF(U3="","falta responsable",U3),IF(U3="","Falta responsable","Ocupada por "&U3)))))) -> Lista para revisar: analizó Juan Fernando | X3: =IF(AND(AB3<>"",AB3=U3),"El revisor no puede ser el responsable",IF(AND(OR(V3="Analizado",V3="En revisión",V3="Aprobado"),Y3=""),"Falta la fuente del análisis",IF(AND(OR(V3="Aprobado",V3="En Trello"),AB3=""),"Aprobado sin revisor",""))) | Y3: Prompt con IA | Z3: Comentarios del docente en Trello (exportación del 19 oct 2026), anexo por numeral y guía. Detalle en Ajustes por historia. | AC3: 46315
A4: HU-003 | B4: Acceso del responsable de catálogos | C4: Control de acceso | D4: responsable de catálogos | E4: identificarme antes de modificar un catálogo | F4: que un cambio que afecta a todos los registros no pueda hacerlo cualquiera | G4: Un valor de catálogo mal cargado se propaga a todos los pacientes que lo usen. El control de acceso limita quién puede provocar ese efecto. | H4: Alta (Must) | I4: 0 | J4: N/A | K4: • El sistema implementa una funcionalidad básica de inicio de sesión [2.4]. • Cada entidad con más de cinco opciones seleccionables tiene su interfaz CRUD [2.3]. | L4: • Las credenciales del responsable de catálogos existen en el sistema. | M4: =COUNTIF(Escenarios!$A:$A,A4) -> 10 | N4: Prerrequisito de las historias de catálogos, HU-018 a HU-033. | O4: Los mismos permisos por rol que HU-002. | P4: tanda-1-acceso-y-pacientes | Q4: =IF(COUNTIF(Retroalimentación!$A:$A,A4)>0,"Sí: "&COUNTIF(Retroalimentación!$A:$A,A4)&" textos","No") -> Sí: 2 textos | R4: Ajustar | S4: Cargo que exista en la IPS, qué hace con los catálogos y tiempo de inactividad. Más el ajuste general (mockup y estimación). Detalle en Ajustes por historia: 2 filas. | T4: Sin fila del anexo (numeral 2.4) | U4: Juan Fernando | V4: Analizado | W4: =IF(OR(V4="",V4="Libre"),"Disponible",IF(V4="Bloqueado","Bloqueada: "&IF(AA4="","falta motivo",AA4),IF(OR(V4="Aprobado",V4="En Trello"),"Cerrada",IF(V4="En revisión","En revisión: "&IF(AB4="","falta revisor",AB4),IF(V4="Analizado","Lista para revisar: analizó "&IF(U4="","falta responsable",U4),IF(U4="","Falta responsable","Ocupada por "&U4)))))) -> Lista para revisar: analizó Juan Fernando | X4: =IF(AND(AB4<>"",AB4=U4),"El revisor no puede ser el responsable",IF(AND(OR(V4="Analizado",V4="En revisión",V4="Aprobado"),Y4=""),"Falta la fuente del análisis",IF(AND(OR(V4="Aprobado",V4="En Trello"),AB4=""),"Aprobado sin revisor",""))) | Y4: Prompt con IA | Z4: Comentarios del docente en Trello (exportación del 19 oct 2026), anexo por numeral y guía. Detalle en Ajustes por historia. | AC4: 46315
A5: HU-004 | B5: Registro de un paciente | C5: Gestión de pacientes | D5: auxiliar de admisión | E5: registrar a un paciente nuevo | F5: que quien lo atienda después no tenga que volver a preguntarle sus datos | G5: Sin el registro del paciente no hay sobre qué consultar, actualizar ni asociar información clínica. Es la condición de partida de los dos módulos. | H5: Alta (Must) | I5: 0 | J5: HU-001 | K5: • Los datos del paciente son los que exige la Resolución 866 de 2021 en su anexo técnico, grupo de identificación del usuario de los servicios de salud. • Un paciente puede tener más de un país registrado como nacionalidad [2.1]. • La fecha de nacimiento se registra separada de la hora de nacimiento [2.1]. La hora puede faltar: el anexo técnico admite un valor de solo fecha para ese elemento. • La ocupación admite solo las categorías hijas del catálogo CIUO-88 AC del DANE [2.1]. • Un paciente puede registrar más de una categoría de discapacidad [2.1]. • La ciudad de residencia se registra junto con su código oficial DANE [2.1]. • La oposición a la presunción legal de donación y el documento de voluntad anticipada se manejan como estructuras separadas [2.1], con sus propias historias. | L5: • El auxiliar de admisión tiene sesión iniciada (HU-001). • Los catálogos están cargados. | M5: =COUNTIF(Escenarios!$A:$A,A5) -> 12 | N5: Depende de HU-001 y de los catálogos cargados. Prerrequisito de HU-005, HU-006 y de todo el módulo clínico. | O5: Cuáles datos son obligatorios, sin definir por el documento. | P5: tanda-1-acceso-y-pacientes | Q5: =IF(COUNTIF(Retroalimentación!$A:$A,A5)>0,"Sí: "&COUNTIF(Retroalimentación!$A:$A,A5)&" textos","No") -> Sí: 2 textos | R5: Ajustar | S5: Listar los datos por numeral (1 a 15; faltan cinco), validar cada uno con su numeral, obligatorios y duplicado. Más el ajuste general (mockup y estimación). Detalle en Ajustes por historia: 6 filas. | T5: V-01 a V-17 | U5: Juan Fernando | V5: Analizado | W5: =IF(OR(V5="",V5="Libre"),"Disponible",IF(V5="Bloqueado","Bloqueada: "&IF(AA5="","falta motivo",AA5),IF(OR(V5="Aprobado",V5="En Trello"),"Cerrada",IF(V5="En revisión","En revisión: "&IF(AB5="","falta revisor",AB5),IF(V5="Analizado","Lista para revisar: analizó "&IF(U5="","falta responsable",U5),IF(U5="","Falta responsable","Ocupada por "&U5)))))) -> Lista para revisar: analizó Juan Fernando | X5: =IF(AND(AB5<>"",AB5=U5),"El revisor no puede ser el responsable",IF(AND(OR(V5="Analizado",V5="En revisión",V5="Aprobado"),Y5=""),"Falta la fuente del análisis",IF(AND(OR(V5="Aprobado",V5="En Trello"),AB5=""),"Aprobado sin revisor",""))) | Y5: Prompt con IA | Z5: Comentarios del docente en Trello (exportación del 19 oct 2026), anexo por numeral y guía. Detalle en Ajustes por historia. | AC5: 46315
A6: HU-005 | B6: Consulta de un paciente | C6: Gestión de pacientes | D6: auxiliar de admisión | E6: consultar los datos de un paciente registrado | F6: saber qué información falta antes de remitirlo a atención | G6: Evita que el paciente vuelva a entregar lo que ya dio y permite detectar datos incompletos antes de que se necesiten. | H6: Alta (Must) | I6: 0 | J6: HU-004 | K6: • El módulo de gestión de pacientes permite la consulta de los datos del paciente [2]. • Los datos con varios valores, como nacionalidad y discapacidad, se entregan completos [2.1]. | L6: • El auxiliar de admisión tiene sesión iniciada (HU-001). • El paciente tiene registro previo (HU-004). | M6: =COUNTIF(Escenarios!$A:$A,A6) -> 10 | N6: Depende de HU-001 y HU-004. | O6: Por qué dato se busca a un paciente, sin definir. | P6: tanda-1-acceso-y-pacientes | Q6: =IF(COUNTIF(Retroalimentación!$A:$A,A6)>0,"Sí: "&COUNTIF(Retroalimentación!$A:$A,A6)&" textos","No") -> Sí: 2 textos | R6: Ajustar | S6: Buscar por documento, entregar los datos de los numerales 1 a 15 y arreglar el escenario 7. Más el ajuste general (mockup y estimación). Detalle en Ajustes por historia: 5 filas. | T6: V-01 a V-17 | U6: Juan Fernando | V6: Analizado | W6: =IF(OR(V6="",V6="Libre"),"Disponible",IF(V6="Bloqueado","Bloqueada: "&IF(AA6="","falta motivo",AA6),IF(OR(V6="Aprobado",V6="En Trello"),"Cerrada",IF(V6="En revisión","En revisión: "&IF(AB6="","falta revisor",AB6),IF(V6="Analizado","Lista para revisar: analizó "&IF(U6="","falta responsable",U6),IF(U6="","Falta responsable","Ocupada por "&U6)))))) -> Lista para revisar: analizó Juan Fernando | X6: =IF(AND(AB6<>"",AB6=U6),"El revisor no puede ser el responsable",IF(AND(OR(V6="Analizado",V6="En revisión",V6="Aprobado"),Y6=""),"Falta la fuente del análisis",IF(AND(OR(V6="Aprobado",V6="En Trello"),AB6=""),"Aprobado sin revisor",""))) | Y6: Prompt con IA | Z6: Comentarios del docente en Trello (exportación del 19 oct 2026), anexo por numeral y guía. Detalle en Ajustes por historia. | AC6: 46315
A7: HU-006 | B7: Actualización de un paciente | C7: Gestión de pacientes | D7: auxiliar de admisión | E7: actualizar los datos de un paciente registrado | F7: que un dato viejo o mal tomado no se arrastre a las atenciones siguientes | G7: Un dato errado sin corregir se propaga a toda atención posterior. | H7: Alta (Must) | I7: 0 | J7: HU-004 | K7: • El módulo de gestión de pacientes permite actualizar los datos del paciente [2]. • Las restricciones del numeral [2.1] se aplican igual al actualizar que al registrar. • Una corrección agrega el dato nuevo con la fecha, la hora y quién la hizo, y conserva el anterior. Lo exige la Resolución 866 en su artículo 10 y condiciona el modelo de datos. | L7: • El auxiliar de admisión tiene sesión iniciada (HU-001). • El paciente tiene registro previo (HU-004). | M7: =COUNTIF(Escenarios!$A:$A,A7) -> 10 | N7: Depende de HU-001 y HU-004. | O7: Ninguno. | P7: tanda-1-acceso-y-pacientes | Q7: =IF(COUNTIF(Retroalimentación!$A:$A,A7)>0,"Sí: "&COUNTIF(Retroalimentación!$A:$A,A7)&" textos","No") -> Sí: 2 textos | R7: Ajustar | S7: Separar actualizar de corregir; la corrección guarda fecha, hora y quién. Más el ajuste general (mockup y estimación). Detalle en Ajustes por historia: 4 filas. | T7: V-01 a V-17 | U7: Juan Fernando | V7: Analizado | W7: =IF(OR(V7="",V7="Libre"),"Disponible",IF(V7="Bloqueado","Bloqueada: "&IF(AA7="","falta motivo",AA7),IF(OR(V7="Aprobado",V7="En Trello"),"Cerrada",IF(V7="En revisión","En revisión: "&IF(AB7="","falta revisor",AB7),IF(V7="Analizado","Lista para revisar: analizó "&IF(U7="","falta responsable",U7),IF(U7="","Falta responsable","Ocupada por "&U7)))))) -> Lista para revisar: analizó Juan Fernando | X7: =IF(AND(AB7<>"",AB7=U7),"El revisor no puede ser el responsable",IF(AND(OR(V7="Analizado",V7="En revisión",V7="Aprobado"),Y7=""),"Falta la fuente del análisis",IF(AND(OR(V7="Aprobado",V7="En Trello"),AB7=""),"Aprobado sin revisor",""))) | Y7: Prompt con IA | Z7: Comentarios del docente en Trello (exportación del 19 oct 2026), anexo por numeral y guía. Detalle en Ajustes por historia. | AC7: 46315
A8: HU-007 | B8: Registro de información clínica | C8: Contacto con el servicio de salud | D8: médico tratante | E8: registrar la atención de un paciente con su diagnóstico | F8: dejar constancia de lo que encontré antes de que se pierda con el turno | G8: Es el registro que asocia una atención a un paciente. Sin él, los datos del paciente quedan sin uso clínico y no hay historia que consultar en la siguiente atención. | H8: Alta (Must) | I8: 0 | J8: HU-004 | K8: • Los datos de la atención son los que exige la Resolución 866 de 2021 en su anexo técnico, grupo de contacto con el servicio de salud. • El diagnóstico se registra con la última versión del CIE-10 [2.2]. • Se respeta la jerarquía padre-hijo de los códigos diagnósticos [2.2]. Si un código padre puede asociarse directamente a una atención queda pendiente de definición. • El diagnóstico tiene entidad propia con su interfaz CRUD, por tener más de cinco opciones seleccionables [2.3]. | L8: • El médico tratante tiene sesión iniciada (HU-002). • El paciente tiene registro previo (HU-004). • El catálogo CIE-10 está cargado. | M8: =COUNTIF(Escenarios!$A:$A,A8) -> 11 | N8: Depende de HU-002, HU-004 y de la carga del catálogo CIE-10. Prerrequisito de HU-008 y HU-009. | O8: Cuál es la última versión del CIE-10 que se va a usar, sin definir. El documento dice "última versión" sin fijar cuál [2.2]. | P8: tanda-2-contacto-clinico | Q8: =IF(COUNTIF(Retroalimentación!$A:$A,A8)>0,"Sí: "&COUNTIF(Retroalimentación!$A:$A,A8)&" textos","No") -> Sí: 2 textos | R8: Ajustar | S8: Listar los datos por numeral (16 a 23), validar cada uno con su numeral y cerrar los escenarios 10 y 11. Más el ajuste general (mockup y estimación). Detalle en Ajustes por historia: 6 filas. | T8: V-18 a V-28 | U8: Juan Fernando | V8: Analizado | W8: =IF(OR(V8="",V8="Libre"),"Disponible",IF(V8="Bloqueado","Bloqueada: "&IF(AA8="","falta motivo",AA8),IF(OR(V8="Aprobado",V8="En Trello"),"Cerrada",IF(V8="En revisión","En revisión: "&IF(AB8="","falta revisor",AB8),IF(V8="Analizado","Lista para revisar: analizó "&IF(U8="","falta responsable",U8),IF(U8="","Falta responsable","Ocupada por "&U8)))))) -> Lista para revisar: analizó Juan Fernando | X8: =IF(AND(AB8<>"",AB8=U8),"El revisor no puede ser el responsable",IF(AND(OR(V8="Analizado",V8="En revisión",V8="Aprobado"),Y8=""),"Falta la fuente del análisis",IF(AND(OR(V8="Aprobado",V8="En Trello"),AB8=""),"Aprobado sin revisor",""))) | Y8: Prompt con IA | Z8: Comentarios del docente en Trello (exportación del 19 oct 2026), anexo por numeral y guía. Detalle en Ajustes por historia. | AC8: 46315
A9: HU-008 | B9: Consulta de la información clínica de un paciente | C9: Contacto con el servicio de salud | D9: médico tratante | E9: consultar las atenciones anteriores de un paciente | F9: no repetir lo que ya se hizo ni contradecir un diagnóstico previo sin saberlo | G9: Un diagnóstico hecho sin conocer los anteriores rompe la continuidad de la atención dentro de la propia IPS. | H9: Alta (Must) | I9: 0 | J9: HU-007 | K9: • El módulo de contacto con el servicio de salud incluye submódulo de consulta [2]. • La jerarquía padre-hijo del diagnóstico se conserva al consultar [2.2]. | L9: • El médico tratante tiene sesión iniciada (HU-002). • El paciente tiene al menos una atención registrada (HU-007). | M9: =COUNTIF(Escenarios!$A:$A,A9) -> 10 | N9: Depende de HU-002 y HU-007. | O9: Ninguno. | P9: tanda-2-contacto-clinico | Q9: =IF(COUNTIF(Retroalimentación!$A:$A,A9)>0,"Sí: "&COUNTIF(Retroalimentación!$A:$A,A9)&" textos","No") -> Sí: 2 textos | R9: Ajustar | S9: Entregar todos los datos de la atención, decir el orden y quitar la precondición. Más el ajuste general (mockup y estimación). Detalle en Ajustes por historia: 6 filas. | T9: V-18 a V-28 | U9: Juan Fernando | V9: Analizado | W9: =IF(OR(V9="",V9="Libre"),"Disponible",IF(V9="Bloqueado","Bloqueada: "&IF(AA9="","falta motivo",AA9),IF(OR(V9="Aprobado",V9="En Trello"),"Cerrada",IF(V9="En revisión","En revisión: "&IF(AB9="","falta revisor",AB9),IF(V9="Analizado","Lista para revisar: analizó "&IF(U9="","falta responsable",U9),IF(U9="","Falta responsable","Ocupada por "&U9)))))) -> Lista para revisar: analizó Juan Fernando | X9: =IF(AND(AB9<>"",AB9=U9),"El revisor no puede ser el responsable",IF(AND(OR(V9="Analizado",V9="En revisión",V9="Aprobado"),Y9=""),"Falta la fuente del análisis",IF(AND(OR(V9="Aprobado",V9="En Trello"),AB9=""),"Aprobado sin revisor",""))) | Y9: Prompt con IA | Z9: Comentarios del docente en Trello (exportación del 19 oct 2026), anexo por numeral y guía. Detalle en Ajustes por historia. | AC9: 46315
A10: HU-009 | B10: Modificación de la información clínica registrada | C10: Contacto con el servicio de salud | D10: médico tratante | E10: modificar un dato de una atención que quedó mal registrado | F10: que el error no sirva de base a la siguiente atención, sin borrar lo que se escribió | G10: Un diagnóstico errado sin corregir orienta mal la atención siguiente. Y conservar lo anterior permite saber qué se sabía en cada momento. | H10: Alta (Must) | I10: 0 | J10: HU-007 | K10: • El módulo de contacto con el servicio de salud incluye submódulo de modificación [2]. • Las restricciones del diagnóstico se aplican igual al modificar que al registrar [2.2]. • Una modificación agrega el dato nuevo con la fecha, la hora y quién la hizo, y conserva el anterior. Lo exige la Resolución 866 en su artículo 10 y condiciona el modelo de datos. | L10: • El médico tratante tiene sesión iniciada (HU-002). • Existe una atención registrada (HU-007). | M10: =COUNTIF(Escenarios!$A:$A,A10) -> 10 | N10: Depende de HU-002 y HU-007. | O10: Ninguno. | P10: tanda-2-contacto-clinico | Q10: =IF(COUNTIF(Retroalimentación!$A:$A,A10)>0,"Sí: "&COUNTIF(Retroalimentación!$A:$A,A10)&" textos","No") -> Sí: 2 textos | R10: Ajustar | S10: Guardar fecha, hora y quién corrige; las mismas reglas de HU-007. Más el ajuste general (mockup y estimación). Detalle en Ajustes por historia: 3 filas. | T10: V-18 a V-28 | U10: Juan Fernando | V10: Analizado | W10: =IF(OR(V10="",V10="Libre"),"Disponible",IF(V10="Bloqueado","Bloqueada: "&IF(AA10="","falta motivo",AA10),IF(OR(V10="Aprobado",V10="En Trello"),"Cerrada",IF(V10="En revisión","En revisión: "&IF(AB10="","falta revisor",AB10),IF(V10="Analizado","Lista para revisar: analizó "&IF(U10="","falta responsable",U10),IF(U10="","Falta responsable","Ocupada por "&U10)))))) -> Lista para revisar: analizó Juan Fernando | X10: =IF(AND(AB10<>"",AB10=U10),"El revisor no puede ser el responsable",IF(AND(OR(V10="Analizado",V10="En revisión",V10="Aprobado"),Y10=""),"Falta la fuente del análisis",IF(AND(OR(V10="Aprobado",V10="En Trello"),AB10=""),"Aprobado sin revisor",""))) | Y10: Prompt con IA | Z10: Comentarios del docente en Trello (exportación del 19 oct 2026), anexo por numeral y guía. Detalle en Ajustes por historia. | AC10: 46315
A11: HU-010 | B11: Registro de la oposición a la presunción legal de donación | C11: Oposición a la donación | D11: auxiliar de admisión | E11: registrar que un paciente manifestó oposición a ser donante | F11: que esa voluntad quede en el sistema antes de que alguien tenga que decidir sin ella | G11: Es una manifestación de voluntad con efectos legales. Si no está registrada al momento en que se necesita, no existe. | H11: Alta (Must) | I11: 0 | J11: HU-004 | K11: • La oposición a la presunción legal de donación se representa como estructura separada [2.1]. • La estructura tiene sus cuatro operaciones de CRUD [2.1]. | L11: • El auxiliar de admisión tiene sesión iniciada (HU-001). • El paciente tiene registro previo (HU-004). | M11: =COUNTIF(Escenarios!$A:$A,A11) -> 10 | N11: Depende de HU-001 y HU-004. Prerrequisito de HU-011, HU-012 y HU-013. | O11: Si la manifestación requiere soporte documental, sin definir por el documento. | P11: tanda-3-estructuras-separadas | Q11: =IF(COUNTIF(Retroalimentación!$A:$A,A11)>0,"Sí: "&COUNTIF(Retroalimentación!$A:$A,A11)&" textos","No") -> Sí: 2 textos | R11: Ajustar | S11: Sí o No y fecha del documento; sin registro no es No. Más el ajuste general (mockup y estimación). Detalle en Ajustes por historia: 4 filas. | T11: V-09 | U11: Juan Fernando | V11: Analizado | W11: =IF(OR(V11="",V11="Libre"),"Disponible",IF(V11="Bloqueado","Bloqueada: "&IF(AA11="","falta motivo",AA11),IF(OR(V11="Aprobado",V11="En Trello"),"Cerrada",IF(V11="En revisión","En revisión: "&IF(AB11="","falta revisor",AB11),IF(V11="Analizado","Lista para revisar: analizó "&IF(U11="","falta responsable",U11),IF(U11="","Falta responsable","Ocupada por "&U11)))))) -> Lista para revisar: analizó Juan Fernando | X11: =IF(AND(AB11<>"",AB11=U11),"El revisor no puede ser el responsable",IF(AND(OR(V11="Analizado",V11="En revisión",V11="Aprobado"),Y11=""),"Falta la fuente del análisis",IF(AND(OR(V11="Aprobado",V11="En Trello"),AB11=""),"Aprobado sin revisor",""))) | Y11: Prompt con IA | Z11: Comentarios del docente en Trello (exportación del 19 oct 2026), anexo por numeral y guía. Detalle en Ajustes por historia. | AC11: 46315
A12: HU-011 | B12: Consulta de la oposición a la presunción legal de donación | C12: Oposición a la donación | D12: auxiliar de admisión | E12: consultar si un paciente manifestó oposición a ser donante | F12: saber si esa voluntad ya está en el sistema o hay que preguntársela | G12: Permite distinguir entre una voluntad registrada y una que nadie preguntó. | H12: Alta (Must) | I12: 0 | J12: HU-010 | K12: • La oposición se consulta como estructura separada del registro general [2.1]. | L12: • El auxiliar de admisión tiene sesión iniciada (HU-001). • El paciente tiene registro previo (HU-004). | M12: =COUNTIF(Escenarios!$A:$A,A12) -> 10 | N12: Depende de HU-001, HU-004 y HU-010. | O12: Ninguno. | P12: tanda-3-estructuras-separadas | Q12: =IF(COUNTIF(Retroalimentación!$A:$A,A12)>0,"Sí: "&COUNTIF(Retroalimentación!$A:$A,A12)&" textos","No") -> Sí: 2 textos | R12: Ajustar | S12: Historial claro y fecha del documento; sin registro no es No. Más el ajuste general (mockup y estimación). Detalle en Ajustes por historia: 3 filas. | T12: V-09 | U12: Juan Fernando | V12: Analizado | W12: =IF(OR(V12="",V12="Libre"),"Disponible",IF(V12="Bloqueado","Bloqueada: "&IF(AA12="","falta motivo",AA12),IF(OR(V12="Aprobado",V12="En Trello"),"Cerrada",IF(V12="En revisión","En revisión: "&IF(AB12="","falta revisor",AB12),IF(V12="Analizado","Lista para revisar: analizó "&IF(U12="","falta responsable",U12),IF(U12="","Falta responsable","Ocupada por "&U12)))))) -> Lista para revisar: analizó Juan Fernando | X12: =IF(AND(AB12<>"",AB12=U12),"El revisor no puede ser el responsable",IF(AND(OR(V12="Analizado",V12="En revisión",V12="Aprobado"),Y12=""),"Falta la fuente del análisis",IF(AND(OR(V12="Aprobado",V12="En Trello"),AB12=""),"Aprobado sin revisor",""))) | Y12: Prompt con IA | Z12: Comentarios del docente en Trello (exportación del 19 oct 2026), anexo por numeral y guía. Detalle en Ajustes por historia. | AC12: 46315
A13: HU-012 | B13: Actualización de la oposición a la presunción legal de donación | C13: Oposición a la donación | D13: auxiliar de admisión | E13: actualizar la manifestación de un paciente sobre la donación | F13: que el sistema refleje su voluntad actual y no una que ya cambió | G13: Una manifestación de voluntad puede cambiar. Si el sistema conserva la antigua como vigente, obra contra la voluntad del paciente. | H13: Alta (Must) | I13: 0 | J13: HU-010 | K13: • La estructura de oposición admite actualización [2.1]. • La actualización conserva la manifestación anterior con su fecha y quién la registró. | L13: • El auxiliar de admisión tiene sesión iniciada (HU-001). • El paciente tiene una manifestación registrada (HU-010). | M13: =COUNTIF(Escenarios!$A:$A,A13) -> 10 | N13: Depende de HU-001, HU-004 y HU-010. | O13: Ninguno. | P13: tanda-3-estructuras-separadas | Q13: =IF(COUNTIF(Retroalimentación!$A:$A,A13)>0,"Sí: "&COUNTIF(Retroalimentación!$A:$A,A13)&" textos","No") -> Sí: 2 textos | R13: Ajustar | S13: Escenario de No a Sí; separar cambio de voluntad de corrección. Más el ajuste general (mockup y estimación). Detalle en Ajustes por historia: 3 filas. | T13: V-09 | U13: Juan Fernando | V13: Analizado | W13: =IF(OR(V13="",V13="Libre"),"Disponible",IF(V13="Bloqueado","Bloqueada: "&IF(AA13="","falta motivo",AA13),IF(OR(V13="Aprobado",V13="En Trello"),"Cerrada",IF(V13="En revisión","En revisión: "&IF(AB13="","falta revisor",AB13),IF(V13="Analizado","Lista para revisar: analizó "&IF(U13="","falta responsable",U13),IF(U13="","Falta responsable","Ocupada por "&U13)))))) -> Lista para revisar: analizó Juan Fernando | X13: =IF(AND(AB13<>"",AB13=U13),"El revisor no puede ser el responsable",IF(AND(OR(V13="Analizado",V13="En revisión",V13="Aprobado"),Y13=""),"Falta la fuente del análisis",IF(AND(OR(V13="Aprobado",V13="En Trello"),AB13=""),"Aprobado sin revisor",""))) | Y13: Prompt con IA | Z13: Comentarios del docente en Trello (exportación del 19 oct 2026), anexo por numeral y guía. Detalle en Ajustes por historia. | AC13: 46315
... A34: HU-033 | B34: Eliminación de un valor del catálogo de diagnósticos | C34: Catálogo de diagnósticos | D34: responsable de catálogos | E34: eliminar un código que se cargó por error | F34: que nadie diagnostique con un código que no existe en la clasificación oficial | G34: Un diagnóstico con código inventado no interopera con ningún otro prestador, que es justo lo que el proyecto debe garantizar. | H34: Media (Should) | I34: 0 | J34: HU-030 | K34: RC-1, RC-4, RC-5. • La jerarquía padre-hijo se conserva íntegra [2.2]. | L34: • El responsable de catálogos tiene sesión iniciada (HU-003). • El código existe en el catálogo (HU-030). | M34: =COUNTIF(Escenarios!$A:$A,A34) -> 10 | N34: Depende de HU-003 y HU-030. | O34: Qué hacer con los códigos hijos cuando su padre debe retirarse, sin definir. El escenario 3 lo bloquea. | P34: tanda-4b-municipios-diagnosticos | Q34: =IF(COUNTIF(Retroalimentación!$A:$A,A34)>0,"Sí: "&COUNTIF(Retroalimentación!$A:$A,A34)&" textos","No") -> Sí: 2 textos | R34: Ajustar | S34: Inactivar con motivo; escenario sin permiso. Más el ajuste general (mockup y estimación). Detalle en Ajustes por historia: 1 fila. | T34: V-26 | U34: Juan Fernando | V34: Analizado | W34: =IF(OR(V34="",V34="Libre"),"Disponible",IF(V34="Bloqueado","Bloqueada: "&IF(AA34="","falta motivo",AA34),IF(OR(V34="Aprobado",V34="En Trello"),"Cerrada",IF(V34="En revisión","En revisión: "&IF(AB34="","falta revisor",AB34),IF(V34="Analizado","Lista para revisar: analizó "&IF(U34="","falta responsable",U34),IF(U34="","Falta responsable","Ocupada por "&U34)))))) -> Lista para revisar: analizó Juan Fernando | X34: =IF(AND(AB34<>"",AB34=U34),"El revisor no puede ser el responsable",IF(AND(OR(V34="Analizado",V34="En revisión",V34="Aprobado"),Y34=""),"Falta la fuente del análisis",IF(AND(OR(V34="Aprobado",V34="En Trello"),AB34=""),"Aprobado sin revisor",""))) | Y34: Prompt con IA | Z34: Anexo por numeral y guía. Esta tarjeta no está en la exportación de Trello del 19 oct: su retroalimentación sigue sin verificar. | AC34: 46315

Sheet Ajustes por historia
A1: Historia | B1: Fila de validación | C1: Bloque | D1: Resultado | E1: Qué ajustar, con número de escenario | F1: Fuente | G1: Responsable | H1: Fecha | I1: Historia destino (v3) | J1: Estado en v3
A2: HU-001 a HU-033 | B2: General | D2: Ajustar | E2: En las 33: agregar el mockup (imagen o enlace) de la pantalla y sus estados, ligado a los escenarios (D-11). La estimación 0 pasa a “Pendiente de estimación” (D-12). Cuando una historia necesita muchas reglas, no las copia: dice el numeral del anexo que las fija. | F2: Docente: c1 y c2 de todas las historias; pedido del autor del 2026-10-20 | G2: Juan Fernando | H2: 46315 | I2: Todas (tanda 0) | J2: Aplicado: 30 mockups, uno por historia (fase 3); la estimación se hace en clase
A3: HU-018 a HU-033 | B3: General | D3: Ajustar | E3: En las de catálogos: cambiar “responsable de catálogos” por un cargo que exista en la IPS, con su función y sus permisos (D-02), en título, descripción, precondiciones y escenarios. | F3: Docente HU-022: c2; retro General | G3: Juan Fernando | H3: 46315 | I3: Catálogos (tanda 0 y T4, T5) | J3: Aplicado en tanda 0 (actores, D-02), T4 y T5
A4: HU-001 | B4: Sin fila (2.4) | D4: Ajustar | E4: Escenario 10: poner el tiempo de inactividad que cierra la sesión (D-06). | F4: Docente: c1 y c2 | G4: Juan Fernando | H4: 46315 | I4: HU-001 | J4: Aplicado en borrador T1
A5: HU-001 | B5: Sin fila (2.4) | D5: Ajustar | E5: Decir qué puede hacer el auxiliar de admisión y por qué su acceso es distinto del de HU-002 y HU-003 (D-04). | F5: Docente: c2 | G5: Juan Fernando | H5: 46315 | I5: HU-001 | J5: Aplicado en borrador T1
A6: HU-001 | B6: Sin fila (2.4) | D6: Cumple | E6: Escenario 9 (sin recuperación de clave) se queda. El docente retiró esa observación. | F6: Docente: c3 | G6: Juan Fernando | H6: 46315 | I6: HU-001 | J6: Aplicado en borrador T1
A7: HU-002 | B7: Sin fila (2.4) | D7: Ajustar | E7: Escenario 10: tiempo de inactividad (D-06). | F7: Docente: c1 y c2 | G7: Juan Fernando | H7: 46315 | I7: HU-001 | J7: Aplicado en borrador T1
A8: HU-002 | B8: Sin fila (2.4) | D8: Ajustar | E8: Escenario 5: decir qué datos del paciente ve el médico. Propuesta: los mismos que entrega HU-005. | F8: Docente: c1 | G8: Juan Fernando | H8: 46315 | I8: HU-001 | J8: Aplicado en borrador T1
A9: HU-002 | B9: Sin fila (2.4) | D9: Ajustar | E9: Decir qué puede hacer el médico y qué resultado de negocio separa su acceso de los otros dos (D-04). Si D-04 junta los accesos, esta historia se fusiona con HU-001. | F9: Docente: c2; numeral 2.4 | G9: Juan Fernando | H9: 46315 | I9: HU-001 | J9: Aplicado en borrador T1
A10: HU-003 | B10: Sin fila (2.4) | D10: Ajustar | E10: Cambiar “responsable de catálogos” por el cargo de D-02 en título, descripción, precondiciones y escenarios. | F10: Docente: c1 y c2 | G10: Juan Fernando | H10: 46315 | I10: HU-001 | J10: Aplicado en borrador T1
A11: HU-003 | B11: Sin fila (2.4) | D11: Ajustar | E11: Escenario 1: decir qué puede hacer con los catálogos (crear, consultar, actualizar, inactivar). Escenario 10: tiempo de inactividad (D-06). Decir por qué su acceso es aparte (D-04). | F11: Docente: c1 y c2 | G11: Juan Fernando | H11: 46315 | I11: HU-001 | J11: Aplicado en borrador T1
A12: HU-004 | B12: V-01 a V-17 | D12: Ajustar | E12: Reglas: listar los datos del paciente con su nombre y su numeral del anexo (1 a 15), y decir que cada dato se valida con el formato y la longitud de su numeral. Hoy faltan en la lista el país de residencia (11), la etnia y la comunidad étnica (13), la zona (14) y la entidad del plan de beneficios (15). | F12: Docente: c2; anexo, numerales 1 a 15 | G12: Juan Fernando | H12: 46315 | I12: HU-004 | J12: Aplicado en borrador T1
A13: HU-004 | B13: V-01 a V-17 | D13: Ajustar | E13: Escenario nuevo: un dato que no cumple el formato o la longitud de su numeral se rechaza, y el sistema dice cuál es. | F13: Anexo, numerales 1 a 15 | G13: Juan Fernando | H13: 46315 | I13: HU-004 | J13: Aplicado en borrador T1
... A15: HU-004 | B15: V-01 a V-17 | D15: Ajustar | E15: Escenario 9: decir cuáles datos son obligatorios (D-19). | F15: Docente: c1 y c2 | G15: Juan Fernando | H15: 46315 | I15: HU-004 | J15: Aplicado en borrador T1
A16: HU-004 | B16: V-02, V-03 | C16: A | D16: Ajustar | E16: Escenario 11: un paciente ya existe si tiene el mismo tipo y número de documento (D-07). | F16: Docente: c1 y c2; anexo, numeral 2 | G16: Juan Fernando | H16: 46315 | I16: HU-004 | J16: Aplicado en borrador T1
A17: HU-004 | B17: V-01, V-05, V-08, V-11, V-13 | D17: Cumple | E17: Escenarios 2 a 7 y 12 se quedan: varias nacionalidades, fecha y hora separadas, fecha sin hora, solo ocupaciones hijas, varias discapacidades, ciudad con código DANE. | F17: Docente: c2; numeral 2.1 | G17: Juan Fernando | H17: 46315 | I17: HU-004 | J17: Aplicado en borrador T1
A18: HU-005 | B18: V-02, V-03 | C18: A | D18: Ajustar | E18: Decir por qué datos se busca al paciente: tipo y número de documento (D-07). | F18: Docente: c1 y c2 | G18: Juan Fernando | H18: 46315 | I18: HU-005 | J18: Aplicado en borrador T1
A19: HU-005 | B19: V-01 a V-17 | D19: Ajustar | E19: Escenario 1: cambiar “su información completa” por “los datos de los numerales 1 a 15 que tenga registrados”. | F19: Docente: c1 y c2; anexo, numerales 1 a 15 | G19: Juan Fernando | H19: 46315 | I19: HU-005 | J19: Aplicado en borrador T1
A20: HU-005 | B20: Sin fila | D20: Ajustar | E20: Escenario 7 choca con HU-004, que no guarda un paciente sin sus datos obligatorios. Cambiarlo por: paciente con datos opcionales vacíos; el sistema entrega lo registrado y muestra vacíos los opcionales. | F20: Docente: c1 y c2 | G20: Juan Fernando | H20: 46315 | I20: HU-005 | J20: Aplicado en borrador T1
A21: HU-005 | B21: Sin fila | D21: Ajustar | E21: Decir quién puede consultar: el auxiliar de admisión y el médico tratante (D-04). | F21: Docente: c2 | G21: Juan Fernando | H21: 46315 | I21: HU-005 | J21: Aplicado en borrador T1
A22: HU-005 | B22: V-01, V-05, V-11, V-13 | D22: Cumple | E22: Escenarios 3 a 6 se quedan. | F22: Numeral 2.1 | G22: Juan Fernando | H22: 46315 | I22: HU-005 | J22: Aplicado en borrador T1
A23: HU-006 | B23: Sin fila | D23: Ajustar | E23: Separar dos cosas: actualizar un dato que cambió y corregir un error. La corrección guarda el dato anterior y el nuevo, la fecha, la hora, el nombre y la identificación de quien corrige (artículo 10, parágrafo 2). Escenario 2: agregar la hora y la identificación. | F23: Docente: c1 y c2 | G23: Juan Fernando | H23: 46315 | I23: HU-006 | J23: Aplicado en borrador T1
A24: HU-006 | B24: V-01 a V-17 | D24: Ajustar | E24: Decir qué datos se pueden editar: los de HU-004, con las mismas reglas de su numeral. | F24: Docente: c2; anexo, numerales 1 a 15 | G24: Juan Fernando | H24: 46315 | I24: HU-006 | J24: Aplicado en borrador T1
A25: HU-006 | B25: V-01 a V-17 | D25: Ajustar | E25: Escenario 7: decir cuáles datos son obligatorios (D-19). | F25: Docente: c1 | G25: Juan Fernando | H25: 46315 | I25: HU-006 | J25: Aplicado en borrador T1
A26: HU-006 | B26: V-01, V-08, V-11, V-13 | D26: Cumple | E26: Escenarios 3 a 6 se quedan: ciudad y ocupación siguen como reglas del paciente. | F26: Docente: c2 | G26: Juan Fernando | H26: 46315 | I26: HU-006 | J26: Aplicado en borrador T1
A27: HU-007 | B27: V-18 a V-28 | D27: Ajustar | E27: Reglas: listar los datos de la atención con su nombre y su numeral (16 a 23): prestador, fecha y hora de inicio, modalidad, grupo de servicios, entorno, vía de ingreso, causa, triage cuando corresponda, diagnóstico principal, enfermedad huérfana si la hay y tipo de diagnóstico. Cada dato se valida con el formato de su numeral. | F27: Docente: c2; anexo, numerales 16 a 23 | G27: Juan Fernando | H27: 46315 | I27: HU-007 | J27: Aplicado en borrador T2
A28: HU-007 | B28: V-18 a V-28 | D28: Ajustar | E28: Escenario nuevo: un dato que no cumple su numeral se rechaza y el sistema dice cuál es. Escenario nuevo: un valor que no está en su catálogo (modalidad, vía, causa, diagnóstico, enfermedad huérfana) se rechaza. | F28: Anexo, numerales 16 a 23 | G28: Juan Fernando | H28: 46315 | I28: HU-007 | J28: Aplicado en borrador T2
A29: HU-007 | B29: V-26 | C29: D | D29: Ajustar | E29: Escenario 11: cambiar “aplica el criterio que el equipo haya definido” por un resultado: un código de 3 caracteres se rechaza, porque el numeral 23 pide 4 (D-22). | F29: Docente: c1 y c2; anexo, numeral 23 | G29: Juan Fernando | H29: 46315 | I29: HU-007 | J29: Aplicado en borrador T2
A30: HU-007 | B30: Sin fila | D30: Ajustar | E30: Escenario 10: decir en qué estado queda la atención sin terminar y cómo se termina (D-08). | F30: Docente: c2 | G30: Juan Fernando | H30: 46315 | I30: HU-007 | J30: Aplicado en borrador T2
A31: HU-007 | B31: V-18 a V-28 | D31: Ajustar | E31: Decir cuáles datos de la atención son obligatorios (D-15) y cuándo se pide el triage (D-13). | F31: Docente: c1 y c2 | G31: Juan Fernando | H31: 46315 | I31: HU-007 | J31: Aplicado en borrador T2
A32: HU-007 | B32: V-26 | C32: D | D32: Ajustar | E32: Decir qué versión del CIE-10 se usa en las pruebas (D-09). | F32: Docente: c1 | G32: Juan Fernando | H32: 46315 | I32: HU-007 | J32: Aplicado en borrador T2
A33: HU-008 | B33: V-18 a V-28 | D33: Ajustar | E33: Escenario 1: entregar todos los datos de la atención (numerales 16 a 23), con el diagnóstico principal y su tipo, no solo fecha y diagnóstico. | F33: Docente: c2; anexo, numerales 16 a 23 | G33: Juan Fernando | H33: 46315 | I33: HU-008 | J33: Aplicado en borrador T2
A34: HU-008 | B34: Sin fila | D34: Ajustar | E34: Escenario 2: decir el orden. Propuesta: de la más reciente a la más antigua. | F34: Docente: c1 y c2 | G34: Juan Fernando | H34: 46315 | I34: HU-008 | J34: Aplicado en borrador T2
A35: HU-008 | B35: Sin fila | D35: Ajustar | E35: Precondición “al menos una atención”: quitarla, porque el escenario 3 es un paciente sin atenciones. | F35: Docente: c1 | G35: Juan Fernando | H35: 46315 | I35: HU-008 | J35: Aplicado en borrador T2
A36: HU-008 | B36: V-26 | C36: D | D36: Ajustar | E36: Escenario 5 (varios diagnósticos): cambiarlo. El numeral 23 pide un diagnóstico principal. | F36: Anexo, numeral 23 | G36: Juan Fernando | H36: 46315 | I36: HU-008 | J36: Aplicado en borrador T2
A37: HU-008 | B37: Sin fila | D37: Ajustar | E37: Escenario 6: el historial muestra el valor anterior y el vigente con fecha, hora, nombre e identificación de quien corrigió. El mockup muestra cómo se ve. | F37: Docente: c1 y c2 | G37: Juan Fernando | H37: 46315 | I37: HU-008 | J37: Aplicado en borrador T2
A38: HU-008 | B38: Sin fila | D38: Ajustar | E38: Decir quién puede consultar (D-04). | F38: Docente: c2 | G38: Juan Fernando | H38: 46315 | I38: HU-008 | J38: Aplicado en borrador T2
A39: HU-009 | B39: Sin fila | D39: Ajustar | E39: Escenarios 2 y 8: guardar el valor anterior y el nuevo, la fecha, la hora, el nombre y la identificación de quien corrige. Hoy el escenario 8 solo pide la identificación. | F39: Docente: c1 y c2; Res. 866, art. 10, parágrafo 2 | G39: Juan Fernando | H39: 46315 | I39: HU-009 | J39: Aplicado en borrador T2
A40: HU-009 | B40: V-18 a V-28 | D40: Ajustar | E40: Decir qué datos se pueden modificar: los de HU-007, con las reglas de su numeral, incluidos el diagnóstico principal y su tipo. | F40: Docente: c2; anexo, numerales 16 a 23 | G40: Juan Fernando | H40: 46315 | I40: HU-009 | J40: Aplicado en borrador T2
A41: HU-009 | B41: V-26 | C41: D | D41: Ajustar | E41: Escenario nuevo: cambiar el diagnóstico por un código de 3 caracteres se rechaza, igual que en HU-007 (D-22). Escenario 4: el código debe estar en la versión adoptada (D-09). | F41: Docente: c1; anexo, numeral 23 | G41: Juan Fernando | H41: 46315 | I41: HU-009 | J41: Aplicado en borrador T2
A42: HU-010 | B42: V-09 | C42: B | D42: Ajustar | E42: Valor de negocio: quitar “si no está registrada al momento en que se necesita, no existe”. Que no haya registro en el sistema no prueba que el paciente no se haya opuesto. | F42: Docente: c2 | G42: Juan Fernando | H42: 46315 | I42: HU-010 | J42: Aplicado en borrador T3
A43: HU-010 | B43: V-09 | C43: B | D43: Ajustar | E43: Datos: los dos del numeral 8: Sí o No, y la fecha en que se firmó el documento. Escenario 4: cambiar “la fecha en que se manifestó” por la fecha del documento. Escenario 9: la manifestación es obligatoria; la fecha, cuando es Sí. Con No no hay documento de oposición y la fecha no se pide (inferencia del equipo por la definición del numeral 8). | F43: Docente: c1 y c2; anexo, numeral 8 | G43: Juan Fernando | H43: 46315 | I43: HU-010 | J43: Aplicado en borrador T3
A44: HU-010 | B44: V-09 | C44: B | D44: Ajustar | E44: Distinguir tres casos: Sí, No y sin registro. Sin registro no es No; el escenario 3 ya lo dice y se queda. | F44: Docente: c1 | G44: Juan Fernando | H44: 46315 | I44: HU-010 | J44: Aplicado en borrador T3
A45: HU-010 | B45: V-09 | C45: B | D45: Ajustar | E45: Escenario 10: escribirlo como algo que se ve: la oposición se registra y se consulta aparte de los datos del paciente, sin cambiarlos. | F45: Docente: c2 | G45: Juan Fernando | H45: 46315 | I45: HU-010 | J45: Aplicado en borrador T3
A46: HU-011 | B46: V-09 | C46: B | D46: Ajustar | E46: Escenario 5: decir qué muestra el historial y cómo se ve cuál es la vigente, cuál la anterior y cuál la anulada. | F46: Docente: c1 | G46: Juan Fernando | H46: 46315 | I46: HU-011 | J46: Aplicado en borrador T3
A47: HU-011 | B47: V-09 | C47: B | D47: Ajustar | E47: La fecha que se muestra es la del documento (numeral 8). Escenario 2: cambiar “informa que no existe” por “informa que no hay registro”; no tener registro no quiere decir que el paciente no haya manifestado nada. | F47: Docente: c2; anexo, numeral 8 | G47: Juan Fernando | H47: 46315 | I47: HU-011 | J47: Aplicado en borrador T3
A48: HU-011 | B48: Sin fila | D48: Ajustar | E48: Decir quién puede consultar (D-04). | F48: Docente: c2 | G48: Juan Fernando | H48: 46315 | I48: HU-011 | J48: Aplicado en borrador T3
A49: HU-012 | B49: V-09 | C49: B | D49: Ajustar | E49: Escenario nuevo: cambio de No a Sí. Hoy solo está el de Sí a No. | F49: Docente: c1 | G49: Juan Fernando | H49: 46315 | I49: HU-012 | J49: Aplicado en borrador T3
A50: HU-012 | B50: V-09 | C50: B | D50: Ajustar | E50: Escenario 2: mostrar también quién registró la manifestación anterior. | F50: Docente: c1 | G50: Juan Fernando | H50: 46315 | I50: HU-012 | J50: Aplicado en borrador T3
A51: HU-012 | B51: V-09 | C51: B | D51: Ajustar | E51: Separar dos casos: el paciente cambió de voluntad (trae la fecha del documento nuevo, numeral 8) y alguien corrige un error (guarda fecha, hora, nombre e identificación de quien corrige). Los dos guardan versiones. | F51: Docente: c2; anexo, numeral 8 | G51: Juan Fernando | H51: 46315 | I51: HU-012 | J51: Aplicado en borrador T3
A52: HU-013 | B52: V-09 | C52: B | D52: Ajustar | E52: Descripción: esta historia es para anular un registro hecho por error. Cambiar la voluntad del paciente va por HU-012. Anular un registro no revoca la voluntad del paciente. | F52: Docente: c2 | G52: Juan Fernando | H52: 46315 | I52: HU-013 | J52: Aplicado en borrador T3
A53: HU-013 | B53: V-09 | C53: B | D53: Ajustar | E53: Al anular: pedir el motivo y guardar fecha, hora y quién anuló. El registro queda como anulado y se sigue viendo en el historial (D-20). Decir quién puede anular. | F53: Docente: c2; D-20 | G53: Juan Fernando | H53: 46315 | I53: HU-013 | J53: Aplicado en borrador T3
A54: HU-013 | B54: V-09 | C54: B | D54: Ajustar | E54: Mockup: el aviso de confirmación, los mensajes y cómo se ve el registro anulado en el historial. | F54: Docente: c1 | G54: Juan Fernando | H54: 46315 | I54: HU-013 | J54: Aplicado en borrador T3
A55: HU-014 | B55: V-10 | C55: B | D55: Ajustar | E55: Datos: los tres del numeral 9: si tiene documento (Sí o No), la fecha (de firma, cambio, reemplazo o revocación) y el código del prestador donde está, cada uno con el formato de su numeral. | F55: Docente: c1 y c2; anexo, numeral 9 | G55: Juan Fernando | H55: 46315 | I55: HU-014 | J55: Aplicado en borrador T3
A56: HU-014 | B56: V-10 | C56: B | D56: Ajustar | E56: Escenarios 2 y 9: si el paciente dice que no tiene documento, no se piden la fecha ni el prestador. | F56: Docente: c1 | G56: Juan Fernando | H56: 46315 | I56: HU-014 | J56: Aplicado en borrador T3
A57: HU-014 | B57: V-10 | C57: B | D57: Ajustar | E57: Distinguir tres casos: tiene documento, no tiene, y no se sabe (sin registro). | F57: Docente: c2 | G57: Juan Fernando | H57: 46315 | I57: HU-014 | J57: Aplicado en borrador T3
A58: HU-014 | B58: V-10, V-18 | D58: Ajustar | E58: Código del prestador: formato del numeral 9. Si sale de un catálogo lo decide D-05. | F58: Docente: c1 y c2; D-05 | G58: Juan Fernando | H58: 46315 | I58: HU-014 | J58: Aplicado en borrador T3
A59: HU-014 | B59: V-10 | C59: B | D59: Ajustar | E59: Escenario 10: escribirlo como algo que se ve, igual que en HU-010. | F59: Docente: c2 | G59: Juan Fernando | H59: 46315 | I59: HU-014 | J59: Aplicado en borrador T3
A60: HU-015 | B60: V-10 | C60: B | D60: Ajustar | E60: Escenario nuevo: consultar a un paciente que dijo que no tiene documento. Se ve distinto de “no se ha preguntado” y de “registro anulado”. | F60: Docente: c1 | G60: Juan Fernando | H60: 46315 | I60: HU-015 | J60: Aplicado en borrador T3
A61: HU-015 | B61: V-10 | C61: B | D61: Ajustar | E61: Mostrar el registro vigente y sus cambios (cambio, reemplazo, revocación) con fecha y prestador. Sin dato no quiere decir que el documento no exista. | F61: Docente: c2; anexo, numeral 9 | G61: Juan Fernando | H61: 46315 | I61: HU-015 | J61: Aplicado en borrador T3
A62: HU-015 | B62: Sin fila | D62: Ajustar | E62: Decir quién puede consultar (D-04). | F62: Docente: c2 | G62: Juan Fernando | H62: 46315 | I62: HU-015 | J62: Aplicado en borrador T3
A63: HU-016 | B63: V-10 | C63: B | D63: Ajustar | E63: Escenarios nuevos para cada evento del numeral 9: cambio, reemplazo y revocación, cada uno con su fecha. Revocar es una actualización: cierra el pendiente 2 de la tanda 3. | F63: Docente: c1 y c2; anexo, numeral 9 | G63: Juan Fernando | H63: 46315 | I63: HU-016 | J63: Aplicado en borrador T3
A64: HU-016 | B64: V-10 | C64: B | D64: Ajustar | E64: Escenario 2: mostrar también quién registró el anterior. Guardar fecha, hora, nombre e identificación de quien corrige. | F64: Docente: c1 y c2 | G64: Juan Fernando | H64: 46315 | I64: HU-016 | J64: Aplicado en borrador T3
A65: HU-016 | B65: V-10 | C65: B | D65: Ajustar | E65: Escenario 9: decir cuáles datos son obligatorios. | F65: Docente: c1 | G65: Juan Fernando | H65: 46315 | I65: HU-016 | J65: Aplicado en borrador T3
A66: HU-017 | B66: V-10 | C66: B | D66: Ajustar | E66: Descripción: esta historia es para anular un registro hecho por error. Revocar el documento va por HU-016. | F66: Docente: c2 | G66: Juan Fernando | H66: 46315 | I66: HU-017 | J66: Aplicado en borrador T3
A67: HU-017 | B67: V-10 | C67: B | D67: Ajustar | E67: Al anular: motivo, fecha, hora y quién. El registro queda anulado en el historial (D-20). Sin registro vigente no prueba que el documento no exista. | F67: Docente: c2; D-20 | G67: Juan Fernando | H67: 46315 | I67: HU-017 | J67: Aplicado en borrador T3
A68: HU-017 | B68: V-10 | C68: B | D68: Ajustar | E68: Mockup: el aviso de anulación, el estado sin registro vigente y cómo se consulta el historial. | F68: Docente: c1 | G68: Juan Fernando | H68: 46315 | I68: HU-017 | J68: Aplicado en borrador T3
A69: HU-018 | B69: V-01 | C69: A | D69: Ajustar | E69: La carga se queda y se precisa; el docente la da por funcional (“Carga de países funcional”) y pide definir el formato de importación: archivo oficial de la norma ISO 3166-1 con código y nombre, un país ya existe si tiene el mismo código, y el sistema informa los valores rechazados y por qué. Crear un país suelto queda como escenario aparte. | F69: Docente: c1 y c2 | G69: Juan Fernando | H69: 46315 | I69: HU-018 | J69: Aplicado en borrador T4
A70: HU-018 | B70: V-01 | C70: A | D70: Ajustar | E70: El código y el nombre se revisan contra la norma ISO 3166-1, no solo por longitud (D-03, D-21). Un país ya existe si tiene el mismo código. | F70: Docente: c1 y c2; anexo, numeral 1 | G70: Juan Fernando | H70: 46315 | I70: HU-018 | J70: Aplicado en borrador T4
A71: HU-018 | B71: V-01 | C71: A | D71: Ajustar | E71: Enlazar o copiar RC-1, RC-3 y RC-5. | F71: Docente: c1 | G71: Juan Fernando | H71: 46315 | I71: HU-018 | J71: Aplicado en borrador T4
A72: HU-019 | B72: V-01 | C72: A | D72: Ajustar | E72: Escenario 3: decir si la búsqueda por nombre es exacta o parcial y qué pasa si hay varios resultados (D-23). | F72: Docente: c1 | G72: Juan Fernando | H72: 46315 | I72: HU-018 | J72: Aplicado en borrador T4
A73: HU-019 | B73: V-01 | C73: A | D73: Ajustar | E73: Escenario 5: contar los valores no prueba que el catálogo esté completo. Decir la fuente y la versión (D-21). | F73: Docente: c2 | G73: Juan Fernando | H73: 46315 | I73: HU-018 | J73: Aplicado en borrador T4
A74: HU-019 | B74: V-01 | C74: A | D74: Ajustar | E74: Escenario 6: “quién cargó” pasa a “quién creó”. Escenario 10: “eliminados” pasa a “inactivos” (D-20). Enlazar o copiar RC-1 y RC-2. | F74: Docente: c1; D-20 | G74: Juan Fernando | H74: 46315 | I74: HU-018 | J74: Aplicado en borrador T4
... A105: HU-033 | B105: V-26 | C105: D | D105: Ajustar | E105: Eliminar pasa a inactivar (D-20): motivo, quién y cuándo; se puede reactivar. Escenario 2 como en HU-021. El escenario 3 se queda: no se inactiva un código padre con hijos activos. Escenario nuevo: un cargo con sesión y sin permiso no puede inactivar. | F105: Retro HU-033, no está en la exportación del 19 oct; D-20 | G105: Juan Fernando | H105: 46315 | I105: HU-030 | J105: Aplicado en borrador T5

Sheet Por redactar
A1: ID reservado | B1: Sale de la fila de validación | C1: Entidad | D1: Elemento del anexo | E1: Acción | F1: Título propuesto | G1: Responsable | H1: Estado | I1: ¿Se puede tomar? | J1: Alerta | K1: Fuente del análisis | L1: Detalle de la fuente | M1: Bloqueada por | N1: Revisor | O1: Fecha de inicio | P1: Fecha de cierre | Q1: ID en Trello
A2: HU-034 | H2: Libre | I2: =IF(OR(H2="",H2="Libre"),"Disponible",IF(H2="Bloqueado","Bloqueada: "&IF(M2="","falta motivo",M2),IF(OR(H2="Aprobado",H2="En Trello"),"Cerrada",IF(H2="En revisión","En revisión: "&IF(N2="","falta revisor",N2),IF(H2="Analizado","Lista para revisar: analizó "&IF(G2="","falta responsable",G2),IF(G2="","Falta responsable","Ocupada por "&G2)))))) -> Disponible | J2: =IF(AND(N2<>"",N2=G2),"El revisor no puede ser el responsable",IF(AND(OR(H2="Analizado",H2="En revisión",H2="Aprobado"),K2=""),"Falta la fuente del análisis",IF(AND(OR(H2="Aprobado",H2="En Trello"),N2=""),"Aprobado sin revisor","")))
A3: HU-035 | H3: Libre | I3: =IF(OR(H3="",H3="Libre"),"Disponible",IF(H3="Bloqueado","Bloqueada: "&IF(M3="","falta motivo",M3),IF(OR(H3="Aprobado",H3="En Trello"),"Cerrada",IF(H3="En revisión","En revisión: "&IF(N3="","falta revisor",N3),IF(H3="Analizado","Lista para revisar: analizó "&IF(G3="","falta responsable",G3),IF(G3="","Falta responsable","Ocupada por "&G3)))))) -> Disponible | J3: =IF(AND(N3<>"",N3=G3),"El revisor no puede ser el responsable",IF(AND(OR(H3="Analizado",H3="En revisión",H3="Aprobado"),K3=""),"Falta la fuente del análisis",IF(AND(OR(H3="Aprobado",H3="En Trello"),N3=""),"Aprobado sin revisor","")))
A4: HU-036 | H4: Libre | I4: =IF(OR(H4="",H4="Libre"),"Disponible",IF(H4="Bloqueado","Bloqueada: "&IF(M4="","falta motivo",M4),IF(OR(H4="Aprobado",H4="En Trello"),"Cerrada",IF(H4="En revisión","En revisión: "&IF(N4="","falta revisor",N4),IF(H4="Analizado","Lista para revisar: analizó "&IF(G4="","falta responsable",G4),IF(G4="","Falta responsable","Ocupada por "&G4)))))) -> Disponible | J4: =IF(AND(N4<>"",N4=G4),"El revisor no puede ser el responsable",IF(AND(OR(H4="Analizado",H4="En revisión",H4="Aprobado"),K4=""),"Falta la fuente del análisis",IF(AND(OR(H4="Aprobado",H4="En Trello"),N4=""),"Aprobado sin revisor","")))
A5: HU-037 | H5: Libre | I5: =IF(OR(H5="",H5="Libre"),"Disponible",IF(H5="Bloqueado","Bloqueada: "&IF(M5="","falta motivo",M5),IF(OR(H5="Aprobado",H5="En Trello"),"Cerrada",IF(H5="En revisión","En revisión: "&IF(N5="","falta revisor",N5),IF(H5="Analizado","Lista para revisar: analizó "&IF(G5="","falta responsable",G5),IF(G5="","Falta responsable","Ocupada por "&G5)))))) -> Disponible | J5: =IF(AND(N5<>"",N5=G5),"El revisor no puede ser el responsable",IF(AND(OR(H5="Analizado",H5="En revisión",H5="Aprobado"),K5=""),"Falta la fuente del análisis",IF(AND(OR(H5="Aprobado",H5="En Trello"),N5=""),"Aprobado sin revisor","")))
A6: HU-038 | H6: Libre | I6: =IF(OR(H6="",H6="Libre"),"Disponible",IF(H6="Bloqueado","Bloqueada: "&IF(M6="","falta motivo",M6),IF(OR(H6="Aprobado",H6="En Trello"),"Cerrada",IF(H6="En revisión","En revisión: "&IF(N6="","falta revisor",N6),IF(H6="Analizado","Lista para revisar: analizó "&IF(G6="","falta responsable",G6),IF(G6="","Falta responsable","Ocupada por "&G6)))))) -> Disponible | J6: =IF(AND(N6<>"",N6=G6),"El revisor no puede ser el responsable",IF(AND(OR(H6="Analizado",H6="En revisión",H6="Aprobado"),K6=""),"Falta la fuente del análisis",IF(AND(OR(H6="Aprobado",H6="En Trello"),N6=""),"Aprobado sin revisor","")))
A7: HU-039 | H7: Libre | I7: =IF(OR(H7="",H7="Libre"),"Disponible",IF(H7="Bloqueado","Bloqueada: "&IF(M7="","falta motivo",M7),IF(OR(H7="Aprobado",H7="En Trello"),"Cerrada",IF(H7="En revisión","En revisión: "&IF(N7="","falta revisor",N7),IF(H7="Analizado","Lista para revisar: analizó "&IF(G7="","falta responsable",G7),IF(G7="","Falta responsable","Ocupada por "&G7)))))) -> Disponible | J7: =IF(AND(N7<>"",N7=G7),"El revisor no puede ser el responsable",IF(AND(OR(H7="Analizado",H7="En revisión",H7="Aprobado"),K7=""),"Falta la fuente del análisis",IF(AND(OR(H7="Aprobado",H7="En Trello"),N7=""),"Aprobado sin revisor","")))
A8: HU-040 | H8: Libre | I8: =IF(OR(H8="",H8="Libre"),"Disponible",IF(H8="Bloqueado","Bloqueada: "&IF(M8="","falta motivo",M8),IF(OR(H8="Aprobado",H8="En Trello"),"Cerrada",IF(H8="En revisión","En revisión: "&IF(N8="","falta revisor",N8),IF(H8="Analizado","Lista para revisar: analizó "&IF(G8="","falta responsable",G8),IF(G8="","Falta responsable","Ocupada por "&G8)))))) -> Disponible | J8: =IF(AND(N8<>"",N8=G8),"El revisor no puede ser el responsable",IF(AND(OR(H8="Analizado",H8="En revisión",H8="Aprobado"),K8=""),"Falta la fuente del análisis",IF(AND(OR(H8="Aprobado",H8="En Trello"),N8=""),"Aprobado sin revisor","")))
A9: HU-041 | H9: Libre | I9: =IF(OR(H9="",H9="Libre"),"Disponible",IF(H9="Bloqueado","Bloqueada: "&IF(M9="","falta motivo",M9),IF(OR(H9="Aprobado",H9="En Trello"),"Cerrada",IF(H9="En revisión","En revisión: "&IF(N9="","falta revisor",N9),IF(H9="Analizado","Lista para revisar: analizó "&IF(G9="","falta responsable",G9),IF(G9="","Falta responsable","Ocupada por "&G9)))))) -> Disponible | J9: =IF(AND(N9<>"",N9=G9),"El revisor no puede ser el responsable",IF(AND(OR(H9="Analizado",H9="En revisión",H9="Aprobado"),K9=""),"Falta la fuente del análisis",IF(AND(OR(H9="Aprobado",H9="En Trello"),N9=""),"Aprobado sin revisor","")))
A10: HU-042 | H10: Libre | I10: =IF(OR(H10="",H10="Libre"),"Disponible",IF(H10="Bloqueado","Bloqueada: "&IF(M10="","falta motivo",M10),IF(OR(H10="Aprobado",H10="En Trello"),"Cerrada",IF(H10="En revisión","En revisión: "&IF(N10="","falta revisor",N10),IF(H10="Analizado","Lista para revisar: analizó "&IF(G10="","falta responsable",G10),IF(G10="","Falta responsable","Ocupada por "&G10)))))) -> Disponible | J10: =IF(AND(N10<>"",N10=G10),"El revisor no puede ser el responsable",IF(AND(OR(H10="Analizado",H10="En revisión",H10="Aprobado"),K10=""),"Falta la fuente del análisis",IF(AND(OR(H10="Aprobado",H10="En Trello"),N10=""),"Aprobado sin revisor","")))
A11: HU-043 | H11: Libre | I11: =IF(OR(H11="",H11="Libre"),"Disponible",IF(H11="Bloqueado","Bloqueada: "&IF(M11="","falta motivo",M11),IF(OR(H11="Aprobado",H11="En Trello"),"Cerrada",IF(H11="En revisión","En revisión: "&IF(N11="","falta revisor",N11),IF(H11="Analizado","Lista para revisar: analizó "&IF(G11="","falta responsable",G11),IF(G11="","Falta responsable","Ocupada por "&G11)))))) -> Disponible | J11: =IF(AND(N11<>"",N11=G11),"El revisor no puede ser el responsable",IF(AND(OR(H11="Analizado",H11="En revisión",H11="Aprobado"),K11=""),"Falta la fuente del análisis",IF(AND(OR(H11="Aprobado",H11="En Trello"),N11=""),"Aprobado sin revisor","")))
A12: HU-044 | H12: Libre | I12: =IF(OR(H12="",H12="Libre"),"Disponible",IF(H12="Bloqueado","Bloqueada: "&IF(M12="","falta motivo",M12),IF(OR(H12="Aprobado",H12="En Trello"),"Cerrada",IF(H12="En revisión","En revisión: "&IF(N12="","falta revisor",N12),IF(H12="Analizado","Lista para revisar: analizó "&IF(G12="","falta responsable",G12),IF(G12="","Falta responsable","Ocupada por "&G12)))))) -> Disponible | J12: =IF(AND(N12<>"",N12=G12),"El revisor no puede ser el responsable",IF(AND(OR(H12="Analizado",H12="En revisión",H12="Aprobado"),K12=""),"Falta la fuente del análisis",IF(AND(OR(H12="Aprobado",H12="En Trello"),N12=""),"Aprobado sin revisor","")))
A13: HU-045 | H13: Libre | I13: =IF(OR(H13="",H13="Libre"),"Disponible",IF(H13="Bloqueado","Bloqueada: "&IF(M13="","falta motivo",M13),IF(OR(H13="Aprobado",H13="En Trello"),"Cerrada",IF(H13="En revisión","En revisión: "&IF(N13="","falta revisor",N13),IF(H13="Analizado","Lista para revisar: analizó "&IF(G13="","falta responsable",G13),IF(G13="","Falta responsable","Ocupada por "&G13)))))) -> Disponible | J13: =IF(AND(N13<>"",N13=G13),"El revisor no puede ser el responsable",IF(AND(OR(H13="Analizado",H13="En revisión",H13="Aprobado"),K13=""),"Falta la fuente del análisis",IF(AND(OR(H13="Aprobado",H13="En Trello"),N13=""),"Aprobado sin revisor","")))
... A41: HU-073 | H41: Libre | I41: =IF(OR(H41="",H41="Libre"),"Disponible",IF(H41="Bloqueado","Bloqueada: "&IF(M41="","falta motivo",M41),IF(OR(H41="Aprobado",H41="En Trello"),"Cerrada",IF(H41="En revisión","En revisión: "&IF(N41="","falta revisor",N41),IF(H41="Analizado","Lista para revisar: analizó "&IF(G41="","falta responsable",G41),IF(G41="","Falta responsable","Ocupada por "&G41)))))) -> Disponible | J41: =IF(AND(N41<>"",N41=G41),"El revisor no puede ser el responsable",IF(AND(OR(H41="Analizado",H41="En revisión",H41="Aprobado"),K41=""),"Falta la fuente del análisis",IF(AND(OR(H41="Aprobado",H41="En Trello"),N41=""),"Aprobado sin revisor","")))

Sheet Decisiones
A1: N.º | B1: Decisión | C1: Afecta a | D1: Valor acordado | E1: Estado de la decisión | F1: Propuesta por | G1: Fecha | H1: Fuente | I1: Observaciones
A2: D-01 | B2: Umbral del numeral 2.3: cuántas opciones hacen falta para que un campo sea entidad | C2: Toda la hoja Validación | D2: Más de 5, según el texto del numeral 2.3 | E2: Pendiente | H2: Documento del docente | I2: La revisión General ampliada del docente (2026-10-13, hoja Retroalimentación, fila 3) repite "campos con más de cinco opciones". El estado en E2 lo cambia el equipo. Lo que propongo es “Confirmada por el docente”.
A3: D-02 | B3: Cargo que mantiene los catálogos, con su función y sus permisos | C3: HU-003 y todas las de catálogo | D3: Profesional de estadística de la IPS. Carga los catálogos desde el archivo oficial; crea y cambia valores solo por cambio oficial; inactiva y reactiva; no ve datos de pacientes ni de atenciones, solo cuántos registros usan un valor. Se supone que el área de estadística es la que reporta los datos de la IPS con las tablas oficiales; no hay fuente. El docente pidió un cargo real, no un nombre (HU-022 c2). Pregunta al docente. (Propuesta, 2026-10-20) | E3: Pendiente | I3: Docente, HU-022 c2: “Esto “responsable de catálogos” no es un rol? quien es responsable de catalogos? yo en la IPS no tengo ningun responsable en mi organización”. El cargo tiene que existir en la IPS. En otras tarjetas sugiere “administrador de catálogos o gestor de datos maestros, validado con el dominio”. Hipótesis del modelo, sin fuente: un cargo que ya maneje los datos que la IPS reporta, como el profesional de estadística o el líder de sistemas de información; confirmar con el docente.
A4: D-03 | B4: Código ISO 3166-1 de país: alfabético (COL) o numérico (170) | C4: Países, elementos 1 y 11 | D4: El numérico de 3 dígitos de la ISO 3166-1 (Colombia es 170); una fila con letras en el código se rechaza. El numeral 1 tiene formato 999 y el anexo de la Resolución 1888 de 2025 remite a la tabla Pais de SISPRO; que esa tabla use el numérico se confirma al descargarla. (Propuesta, 2026-10-20) | E4: Pendiente
A5: D-04 | B5: Inicio de sesión: una historia o una por cargo | C5: HU-001 a HU-003 | D5: Una sola historia (HU-001) con permisos por cargo en los escenarios. (Propuesta, 2026-10-20) | E5: Pendiente | I5: El docente pide justificar la separación de los accesos por resultados distintos de negocio (HU-001 c2, HU-002 c2, HU-003 c2).
A6: D-05 | B6: Prestador como catálogo propio | C6: Elementos 9 y 16 | D6: La IPS se trata como un solo prestador con una sede, porque la guía no menciona sedes. El equipo técnico deja su código de 12 caracteres configurado al instalar y el sistema lo pone en cada atención. No hay catálogo de prestadores. El prestador donde está la voluntad anticipada (numeral 9) se escribe y se valida por formato. (Propuesta, 2026-10-20) | E6: Pendiente | I6: Hoja 16: código del REPS publicado en SISPRO (12 caracteres); hoja 14: código del prestador donde reposa la voluntad anticipada, mismo formato. Para una sola IPS, el prestador que realiza la atención puede ser fijo (sus sedes); el del elemento 9 puede ser cualquier prestador del país. V-18 queda bloqueada hasta esta decisión.
A7: D-06 | B7: Tiempo de inactividad que cierra la sesión | C7: HU-001, escenario 12 (en el backlog anterior, HU-001 a HU-003, escenario 10) | D7: 15 minutos sin actividad. (Propuesta, 2026-10-20) | E7: Pendiente
A8: D-07 | B8: Clave que identifica a un paciente duplicado | C8: HU-004, escenario 12 (en el backlog anterior, escenario 11) | D8: Tipo y número de documento, como sugiere el docente en HU-004. (Propuesta, 2026-10-20) | E8: Pendiente | I8: La retroalimentación de HU-004 sugiere tipo y número de documento. Sirve también para responder por qué dato se busca a un paciente (HU-005).
A9: D-08 | B9: Estado de una atención que no se terminó de registrar | C9: HU-007, escenarios 11 a 13 (en el backlog anterior, escenario 10) | D9: Dos estados: Borrador (le falta algo) y Registrada (completa). El borrador se completa en HU-007; la atención registrada se corrige en HU-009. (Propuesta, 2026-10-20) | E9: Pendiente | I9: Docente, HU-007 c2: “definir estado y finalización del borrador del escenario 10”.
A10: D-09 | B10: Versión del CIE-10 que se usa en las pruebas | C10: HU-007 y catálogo de diagnósticos | D10: La tabla CIE10 de SISPRO, en la versión vigente el día de la carga (HU-030). La carga guarda la dirección y la fecha de descarga (RC-8). El anexo de la Resolución 1888 de 2025 remite a esa tabla y dice que la transición al CIE-11 se amplió; la Resolución 2625 de 2025 cita la 1895 de 2001 como la que adoptó la CIE-10 (por confirmar). (Propuesta, 2026-10-20) | E10: Pendiente
A11: D-10 | B11: Incremento del sprint 1 en consola o en web, confirmado por el docente | C11: Sprint 1 | D11: Aplicación web: la guía dice “desarrollar una aplicación web” (sección 2). Confirmar con el docente qué debe mostrar el incremento del sprint 1. (Propuesta, 2026-10-20) | E11: Pendiente
A12: D-11 | B12: Qué acepta el docente como mockup | C12: Todas las historias | D12: Una imagen PNG por historia, pegada en la tarjeta, con la pantalla y sus estados principales, ligada a los escenarios. Se dibujan como maquetas HTML y se exportan a imagen (fase 3). Si el docente pide otra herramienta, se rehacen. (Propuesta, 2026-10-20) | E12: Pendiente
A13: D-12 | B13: Escala de estimación | C13: Todas las historias | D13: Puntos de historia con la serie 1, 2, 3, 5, 8, 13, estimados en clase con planning poker; si no se hace en clase, con video de todo el equipo (guía 2.5). La estimación no la hace el modelo. (Propuesta, 2026-10-20) | E13: Pendiente
A14: D-13 | B14: Cuándo se exige el triage en una atención | C14: V-25, HU-007 a HU-009 | D14: Se pide cuando el grupo de servicios es 05 Atención inmediata: el anexo define el triage para un servicio de urgencias (hojas 17 y 18). Salvedad: ese grupo también incluye servicios que no son de urgencias, como la atención del parto, según el manual de habilitación del Ministerio (por confirmar). Pregunta al docente. (Propuesta, 2026-10-20) | E14: Pendiente | F14: Juan Fernando | G14: 46313 | H14: Hoja del PDF del anexo | I14: Las hojas 17 y 18 lo definen para un servicio de urgencias; la revisión ampliada de HU-007 dice “triage cuando corresponda”. Ningún elemento del 16 al 23 dice por sí solo que una atención es de urgencias.
A15: D-14 | B15: Catálogo de enfermedades huérfanas: fuente y versión | C15: V-27 | D15: El listado de enfermedades huérfanas de la Resolución 2625 de 2025 del Ministerio de Salud, versión 5.0, que derogó la 023 de 2023. El código es el número que el listado da a cada enfermedad, que no se reasigna (artículo 3); que ese número sea el código de 1 a 4 caracteres del numeral 23 es inferencia del equipo. (Propuesta, 2026-10-20) | E15: Pendiente | F15: Juan Fernando | G15: 46313 | H15: Hoja del PDF del anexo | I15: La hoja 18 dice “catálogo de enfermedades huérfanas vigente” sin nombrar cuál.
A16: D-15 | B16: Datos obligatorios de la atención | C16: V-18 a V-28, HU-007 y HU-009 | D16: Columna “¿Obligatorio?” de la lista de datos de HU-007 (tanda 2 del backlog v3). (Propuesta, 2026-10-20) | E16: Pendiente | F16: Juan Fernando | G16: 46313 | H16: Retroalimentación del docente | I16: Las hojas 13 a 18 no tienen columna de obligatoriedad. La revisión de HU-007 pide “detallar los campos obligatorios de la atención”. HU-004 tiene el mismo vacío para el paciente.
A17: D-16 | B17: Alcance de la primera fase: elementos 1 a 23 (grupos 1 y 2 del anexo) o 1 a 49 | C17: Todo el tablero y la hoja Por redactar | D17: Se asume 1 a 23 (grupos 1 y 2 del anexo) mientras el docente no diga otra cosa; el plan B, para 1 a 49, está listo. Pregunta al docente. (Propuesta, 2026-10-20) | E17: Pendiente | F17: Juan Fernando | G17: 46313 | H17: Documento del docente | I17: La guía no dice 23. A favor: “en una primera fase” y los dos módulos (página 1); el título del grupo de la hoja 16 es el nombre del segundo módulo; la revisión ampliada de HU-007 enumera los datos del 16 al 23. En contra: la revisión General pide “cobertura de todos los catálogos para campos con más de cinco opciones” sin límite; el artículo 13.2 de la Resolución 866 asocia el contacto con tecnologías en salud. Preguntar al docente por Teams. Del 24 al 49 salen 6 listas de más de 5 valores y entre 9 y 17 catálogos externos (hoja Anexo 1 a 49): entre 60 y 92 historias más con una por operación.
A18: D-17 | B18: Historias por entidad de catálogo: una por operación del CRUD (4) o una por entidad | C18: Hoja Por redactar; HU-010 a HU-033 | D18: Una historia por catálogo, también en el CIE-10 (HU-030); la búsqueda del médico va aparte por actor (HU-031). Operaciones separadas solo en oposición y voluntad anticipada (2.1) y en la atención (registrar, consultar, corregir, anular). Backlog v3: 30 historias. (Propuesta, 2026-10-20) | E18: Pendiente | F18: Juan Fernando | G18: 46313 | H18: Documento del docente | I18: El numeral 2.3 escribe “Create, Read, Update, Delete”. El Prompt 2 del docente dice “No dividas historias únicamente por: [...] Operaciones de base de datos”. Testimonio del profesor, sin texto escrito: cada parte del CRUD puede ser una historia. Con todo el CRUD comprimido el backlog queda por debajo de 30 (numeral 2.5). Mientras esté pendiente, no se reservan IDs en Por redactar.
A19: D-18 | B19: Cómo se guardan los componentes del anexo | C19: Todas las filas de Validación y sus escenarios | D19: Cada componente con el tipo de la columna Tipo de la hoja: Alfanumérico como texto de la longitud indicada, Numérico como entero, Fecha como fecha y hora. | E19: Pendiente | F19: Juan Fernando | G19: 46313 | H19: Hoja del PDF del anexo | I19: Ejemplos: elemento 12, Medellín 05001, como entero pierde el 0 y queda debajo de la longitud 5; elemento 2, códigos con letras (CC, TI); elemento 46, Numérico “Entre 1 y 999”. Los nombres de las opciones se guardan en la tabla del catálogo; la atención guarda solo el código.
A20: D-19 | B20: Datos obligatorios del paciente | C20: V-01 a V-17; HU-004 y HU-006 | D20: Tabla de HU-004 en la tanda 1 del backlog v3: obligatorios los datos que siempre tienen respuesta en su lista (incluidos los valores de no declara, sin discapacidad y ninguna); opcionales el segundo nombre, el segundo apellido y la hora de nacimiento; condicionados la ocupación, el municipio y la comunidad étnica, que se pide solo si el catálogo de HU-037 tiene valores (mientras no lo tenga, el paciente se registra sin ese dato). La identidad de género queda obligatoria porque su lista tiene “No lo declara”; el anexo de la Resolución 1888 de 2025 dice que “es un dato opcional que será diligenciado a criterio del profesional de la salud de acuerdo con el escenario de atención” (pregunta 14 al docente). (Propuesta, 2026-10-20) | E20: Pendiente | F20: Juan Fernando | G20: 46315 | H20: Retroalimentación del docente | I20: Las hojas 13 a 15 no tienen columna de obligatoriedad. La revisión ampliada de HU-004 pide “Enumerar todos los datos del grupo paciente del anexo, formatos y obligatoriedad”. Caso visible: el segundo nombre y el segundo apellido pueden no existir.
A21: D-20 | B21: “Eliminar” no borra: en los catálogos se inactiva y en las estructuras separadas se anula | C21: HU-013, HU-017, HU-021, HU-025, HU-029, HU-033 y las historias nuevas de eliminación | D21: Nada se borra. Un valor de catálogo se inactiva: deja de ofrecerse para registros nuevos y los registros que ya lo usan lo conservan; una versión nueva de un catálogo oficial inactiva los valores que retira. En la oposición y la voluntad anticipada, un registro hecho por error se anula con motivo y queda en el historial; el docente da por funcional anular (HU-013 c2, HU-017 c2). | E21: Pendiente | F21: Juan Fernando | G21: 46315 | H21: Retroalimentación del docente | I21: Propuesta del autor (2026-10-20). Apoyo: artículo 7 de la Resolución 866 (los catálogos “no podrán ser modificados, reducidos o adicionados”) y artículo 10 (los datos de las atenciones quedan disponibles de forma permanente). Resuelve lo que RC-4 deja abierto: los registros que usan el valor lo conservan. La revisión ampliada de HU-033 pide “Precisar inactivación/recarga, motivo/autor” (sin verificar en Trello). En contra: el numeral 2.3 escribe “Delete”; confirmar con el docente que la inactivación cuenta como la D del CRUD. Exportación de Trello del 19 oct 2026: HU-021 c2, “precisar inactivación/recarga, motivo y autor, sin retirar valores oficiales arbitrariamente”; HU-029 c2, “precisar inactivación/recarga, motivo/autor y preservar valores oficiales”; HU-025 c2, “precisar vigencia, recarga, motivo/autor e historial”; HU-013 c2, “estado anulado”. El docente también valora el bloqueo de valores en uso (HU-021 c2): con la inactivación, el valor en uso no se borra y sus registros lo conservan.
A22: D-21 | B22: Fuente y versión de los catálogos externos | C22: V-01, V-08, V-12, V-13, V-15, V-17, V-18 | D22: Fuentes: la tabla Pais de SISPRO (ISO 3166-1); la CIUO-88 A.C. y la DIVIPOLA del DANE; el catálogo de referencia de comunidades étnicas y el de entidades del Ministerio; las listas del anexo, en su hoja: si el archivo no coincide con la hoja, manda la hoja y se guardan sus códigos y nombres. Formato de carga: CSV UTF-8 separado por punto y coma, con la fuente, la dirección y la fecha de descarga y la fecha de publicación (RC-8). Versión nueva y recarga: RC-9 (el código de una fila rechazada conserva su nombre y su estado). Apoyo: artículo 8 de la Resolución 866, que pone los catálogos a cargo del Ministerio, que definirá el procedimiento para individualizarlos en SISPRO. (Propuesta, 2026-10-20) | E22: Pendiente | F22: Juan Fernando | G22: 46315 | H22: Hoja del PDF del anexo | I22: ISO 3166-1, CIUO-88 A.C., DIVIPOLA, comunidades étnicas, entidades del plan de beneficios y REPS. El CIE-10 va en D-09 y las enfermedades huérfanas en D-14. La carga desde el archivo oficial es funcionalidad: el docente la da por funcional (HU-018 c2, HU-022 c4) y pide precisar el formato de importación. Docente: HU-018 c2, “Validar código/nombre contra ISO 3166-1, no solo longitud”; HU-019 c2, “Definir fuente/versión”; HU-022 c3, “Precisar cómo se cargan los valores: formato de archivo o formulario, campos código/nombre/padre, clave de duplicidad y tratamiento de padre e hija en el mismo lote.”
A23: D-22 | B23: ¿Un código padre del CIE-10 se puede asociar a una atención? | C23: V-26; HU-007 escenario 9, HU-009, HU-030, HU-031 escenario 4 | D23: No. El numeral 23 fija para el código CIE-10 longitud 4 y 4, así que un código de 3 caracteres se rechaza. El código de enfermedad huérfana, del mismo numeral, va de 1 a 4. | E23: Pendiente | F23: Juan Fernando | G23: 46315 | H23: Hoja del PDF del anexo | I23: El docente pide resultado concreto (HU-007 c1 y c2, HU-009 c1). Una categoría de 3 caracteres sin subdivisiones se escribe con X al final (por ejemplo I10X), de modo que todo diagnóstico asociable tiene 4: así aparecen en el listado de la Resolución 2625 de 2025 (D71X, D67X; revisión de la tanda 5). Se confirma con la tabla CIE10 de SISPRO (D-09).
A24: D-23 | B24: Búsqueda en los catálogos: exacta o parcial | C24: HU-019, HU-023, HU-027, HU-031 | D24: Por código, exacta. Por nombre, parcial, sin distinguir mayúsculas ni tildes, y muestra todas las coincidencias. | E24: Pendiente | F24: Juan Fernando | G24: 46315 | H24: Retroalimentación del docente | I24: El docente lo pide en HU-019 c1, HU-023 c1 y HU-027 c1. Valor propuesto por el modelo.
A25: D-24 | B25: Ocupación que guarda la atención | C25: HU-007 a HU-009; numeral 7 | D25: Al crear la atención, el sistema guarda la ocupación que el paciente tiene en ese momento. Si después cambia la del paciente, la atención conserva la suya; si quedó mal, se corrige en HU-009. (Propuesta, 2026-10-20) | E25: Pendiente | F25: Juan Fernando | G25: 46315 | H25: Hoja del PDF del anexo | I25: El numeral 7 se llama “Ocupación al momento de la atención” (hoja 14). Inferencia del equipo; la pidió marcar como propuesta la revisión independiente de la tanda 2.
... A28: D-27 | B28: Anulación de una atención registrada por error | C28: HU-043; HU-007 a HU-009 | D28: Una atención registrada por error, o un borrador que no debía existir (a nombre del paciente equivocado, repetida o que no ocurrió), se anula con un motivo que es una inconsistencia: queda en estado “Anulada”, no se borra, no se corrige y no se pasa a otro paciente. Las anuladas siguen contando como registros que usan un valor de catálogo. Historia nueva HU-043. (Propuesta, 2026-10-20) | E28: Pendiente | F28: Juan Fernando | G28: 46315 | H28: Análisis propio | I28: La guía y el docente no lo mencionan. La versión 2 de la tanda 2 lo dejó pendiente en HU-009; la oposición y la voluntad anticipada tienen su anulación (HU-013, HU-017). Con HU-032 y HU-033 fundidas en HU-030 (revisión de la tanda 5, hallazgo 3), el backlog queda en 30 historias. Pregunta al docente.

Sheet Retroalimentación
A1: Alcance | B1: Tipo de revisión | C1: Texto del docente, como llegó | D1: Compartida en el chat | E1: Nota | F1: Historia destino (v3)
A2: General | B2: Primera revisión | C2: * Lo bueno: todas tienen estructura «Como / Quiero / Para» y criterios BDD. Cubren casos exitosos, errores, permisos y trazabilidad. * Lo malo: ninguna tiene mockup; 17 usan «responsable de catálogos», que requiere un cargo funcional real. Hay criterios ambiguos o pendientes y todas tienen estimación en 0. | D2: 2026-10-13 | E2: Verificado contra captura de Trello: descripción de la tarjeta “NOTA REVISIÓN HU 3,0 / 5.”. | F2: Todas (tanda 0)
A3: General | B3: Revisión ampliada | C3: Lo bueno: estructura Como/Quiero/Para y CA BDD presentes; operaciones funcionales de pacientes, contacto clínico y catálogos, roles auxiliar de admisión y médico tratante, reglas de integridad e historial. Lo malo: faltan mockups en las 33 HU; 17 usan responsable de catálogos sin cargo funcional real; estimaciones en 0 sin sustento; campos del anexo y varios resultados BDD por precisar. Falta demostrar cobertura de todos los catálogos para campos con más de cinco opciones. Ciudad/código DANE deben quedar como CA de registro/actualización del paciente; gestionar catálogo de municipios sí es funcionalidad. Se mantiene la revisión de estructura y BDD, los CA originales y comentarios previos. Proyecto de Clase y Resolución 866 de 2021 son las referencias de esta ampliación. | D3: 2026-10-13 | E3: Verificado contra captura de Trello: comentario del 2026-10-11, tarjeta “NOTA REVISIÓN HU 3,0 / 5.”. La nota de la tarjeta es 3,0 sobre 5. | F3: Todas (tanda 0)
A4: HU-001 | B4: Revisión | C4: Revisión HU-001: cumple la estructura Como/Quiero/Para, tiene un rol funcional válido (auxiliar de admisión) y 10 escenarios BDD Dado/Cuando/Entonces. Falta adjuntar o enlazar una imagen de mockup de la pantalla de acceso y sus estados de error. En el escenario 10 falta definir el tiempo de inactividad que termina la sesión para que el criterio sea comprobable. La estimación relativa figura en 0: completar o indicar que está pendiente de estimación. | D4: 2026-10-20 | E4: Trello, comentario 1: 10 oct 2026, 20:54 hora de Colombia (11 oct 2026, 01:54 UTC). Exportación HTML del 19 oct 2026, entregada por el autor. | F4: HU-001
A5: HU-001 | B5: Revisión ampliada | C5: Revisión ampliada HU-001 — Proyecto de Clase y Resolución 866 de 2021. Estructura de la HU: Como/Quiero/Para, valor, prioridad, estimación, relaciones, reglas, precondiciones y dependencias presentes. Estimación en 0: falta evidencia de estimación o declaración de pendiente. CA en BDD: 10 escenarios Dado/Cuando/Entonces. El formato está presente; precisar los resultados pendientes o genéricos según lo indicado abajo, conservando los CA. Rol, funcionalidad y alcance: Rol auxiliar de admisión válido; login funcional. Precisar permisos y tiempo de inactividad del escenario 10. La recuperación de credenciales del escenario 9 amplía el login básico y requiere justificar alcance. Justificar diferencias funcionales frente a HU-002/HU-003. Mockup: no se observa imagen adjunta, pegada ni URL de imagen de la interfaz. Adjuntar mockup de la operación y estados principales, vinculado a los CA. Complementa la revisión anterior; conserva la evaluación de estructura y BDD. | D5: 2026-10-20 | E5: Trello, comentario 2: 10 oct 2026, 21:52 hora de Colombia (11 oct 2026, 02:52 UTC). Exportación HTML del 19 oct 2026, entregada por el autor. | F5: HU-001
A6: HU-001 | B6: Aclaración | C6: Aclaración de la revisión ampliada HU-001: el escenario 9 dice expresamente que el sistema NO ofrece recuperación de clave. Por tanto, sí respeta el alcance del login básico; retiro esa observación de ampliación de alcance. Se mantienen las demás observaciones sobre permisos, duración de sesión, estimación y mockup. La estructura y los CA BDD originales se conservan. | D6: 2026-10-20 | E6: Trello, comentario 3: 10 oct 2026, 21:58 hora de Colombia (11 oct 2026, 02:58 UTC). Exportación HTML del 19 oct 2026, entregada por el autor. | F6: HU-001
A7: HU-002 | B7: Revisión | C7: Revisión HU-002: cumple Como/Quiero/Para, rol funcional médico tratante y escenarios BDD. Falta imagen de mockup o URL de la pantalla de acceso y sus estados. En el escenario 10 definir el tiempo de inactividad para comprobar la expiración de sesión. En el escenario 5 precisar qué datos puede consultar el médico. Completar la estimación relativa (actualmente 0) o marcarla pendiente. | D7: 2026-10-20 | E7: Trello, comentario 1: 10 oct 2026, 20:54 hora de Colombia (11 oct 2026, 01:54 UTC). Exportación HTML del 19 oct 2026, entregada por el autor. | F7: HU-001
A8: HU-002 | B8: Revisión ampliada | C8: Revisión ampliada HU-002 — Proyecto de Clase y Resolución 866 de 2021. Estructura de la HU: Como/Quiero/Para, valor, prioridad, estimación, relaciones, reglas, precondiciones y dependencias presentes. Estimación en 0: falta evidencia de estimación o declaración de pendiente. CA en BDD: 10 escenarios Dado/Cuando/Entonces. El formato está presente; precisar los resultados pendientes o genéricos según lo indicado abajo, conservando los CA. Rol, funcionalidad y alcance: Médico tratante válido; login funcional. Definir permisos y duración de sesión, y justificar separación de los otros accesos por resultados distintos de negocio. Mockup: no se observa imagen adjunta, pegada ni URL de imagen de la interfaz. Adjuntar mockup de la operación y estados principales, vinculado a los CA. Complementa la revisión anterior; conserva la evaluación de estructura y BDD. | D8: 2026-10-20 | E8: Trello, comentario 2: 10 oct 2026, 21:52 hora de Colombia (11 oct 2026, 02:52 UTC). Exportación HTML del 19 oct 2026, entregada por el autor. | F8: HU-001
A9: HU-003 | B9: Revisión | C9: Revisión HU-003: cumple estructura Como/Quiero/Para y criterios Dado/Cuando/Entonces. Falta mockup como imagen adjunta, pegada o URL. El rol «responsable de catálogos» no cumple el criterio solicitado: sustituirlo por un cargo funcional real, por ejemplo administrador de catálogos o gestor de datos maestros, validado con el dominio, y ajustar título, precondiciones y escenarios. Precisar tiempo de inactividad del escenario 10 y operaciones permitidas del escenario 1. Completar estimación relativa (0) o marcar pendiente. | D9: 2026-10-20 | E9: Trello, comentario 1: 10 oct 2026, 20:54 hora de Colombia (11 oct 2026, 01:54 UTC). Exportación HTML del 19 oct 2026, entregada por el autor. | F9: HU-001
A10: HU-003 | B10: Revisión ampliada | C10: Revisión ampliada HU-003 — Proyecto de Clase y Resolución 866 de 2021. Estructura de la HU: Como/Quiero/Para, valor, prioridad, estimación, relaciones, reglas, precondiciones y dependencias presentes. Estimación en 0: falta evidencia de estimación o declaración de pendiente. CA en BDD: 10 escenarios Dado/Cuando/Entonces. El formato está presente; precisar los resultados pendientes o genéricos según lo indicado abajo, conservando los CA. Rol, funcionalidad y alcance: Login funcional, pero responsable de catálogos es genérico: indicar cargo funcional real, función y permisos. Definir duración de sesión y justificar separación de los otros accesos. Mockup: no se observa imagen adjunta, pegada ni URL de imagen de la interfaz. Adjuntar mockup de la operación y estados principales, vinculado a los CA. Complementa la revisión anterior; conserva la evaluación de estructura y BDD. | D10: 2026-10-20 | E10: Trello, comentario 2: 10 oct 2026, 21:52 hora de Colombia (11 oct 2026, 02:52 UTC). Exportación HTML del 19 oct 2026, entregada por el autor. | F10: HU-001
A11: HU-004 | B11: Revisión | C11: Revisión HU-004: cumple estructura Como/Quiero/Para, rol funcional auxiliar de admisión y 12 escenarios BDD. Falta mockup en imagen o URL del formulario de registro, sus campos y mensajes de validación. Precisar los campos obligatorios del escenario 9 y la clave que identifica duplicados en el escenario 11 (por ejemplo tipo y número de documento, según la regla del dominio). Completar la estimación relativa (0) o marcar pendiente. | D11: 2026-10-20 | E11: Trello, comentario 1: 10 oct 2026, 20:54 hora de Colombia (11 oct 2026, 01:54 UTC). Exportación HTML del 19 oct 2026, entregada por el autor. | F11: HU-004
A12: HU-004 | B12: Revisión ampliada | C12: Revisión ampliada HU-004 — Proyecto de Clase y Resolución 866 de 2021. Estructura de la HU: Como/Quiero/Para, valor, prioridad, estimación, relaciones, reglas, precondiciones y dependencias presentes. Estimación en 0: falta evidencia de estimación o declaración de pendiente. CA en BDD: 12 escenarios Dado/Cuando/Entonces. El formato está presente; precisar los resultados pendientes o genéricos según lo indicado abajo, conservando los CA. Rol, funcionalidad y alcance: Registro de paciente funcional y auxiliar de admisión válido. Ciudad/código DANE, nacionalidades y discapacidades son criterios de esta operación. Enumerar todos los datos del grupo paciente del anexo, formatos y obligatoriedad; definir clave del duplicado del escenario 11. Fecha sin hora es compatible con la longitud mínima 10 del anexo. Mockup: no se observa imagen adjunta, pegada ni URL de imagen de la interfaz. Adjuntar mockup de la operación y estados principales, vinculado a los CA. Complementa la revisión anterior; conserva la evaluación de estructura y BDD. | D12: 2026-10-20 | E12: Trello, comentario 2: 10 oct 2026, 21:53 hora de Colombia (11 oct 2026, 02:53 UTC). Exportación HTML del 19 oct 2026, entregada por el autor. | F12: HU-004
... A70: HU-033 | B70: Revisión ampliada (sin encabezado) | C70: Estructura de HU: Como/Quiero/Para, valor, prioridad, estimación, relaciones, reglas, precondiciones y dependencias presentes. Estimación 0: falta sustento o estado pendiente. CA en BDD: 10 escenarios Dado/Cuando/Entonces presentes. Conservar los CA y precisar resultados según esta observación. Rol: responsable de catálogos es genérico. Definir un cargo funcional real de la IPS, su función y permisos; no basta cambiar el nombre. Funcionalidad y alcance: Retiro de código erróneo funcional. Bien bloqueo de uso y padres con hijos, e historial. Precisar inactivación/recarga, motivo/autor y preservación de valores oficiales. Mockup: falta imagen adjunta, pegada o URL de imagen de esta operación y sus estados, relacionada con los CA. Complementa la revisión anterior, conservando la evaluación de estructura y BDD. | D70: 2026-10-13 | E70: El texto llegó sin encabezado. Se asigna a HU-033 por su contenido: retiro de código, padres con hijos. Sin verificar en Trello. No está en la exportación de Trello del 19 oct 2026, que trae HU-001 a HU-030. | F70: HU-030

Sheet Reglas comunes
A1: Regla | B1: Texto | C1: Historias del backlog anterior que la citan (las del v3 están en las tandas)
A2: RC-1 | B2: Todo dato con más de 5 opciones tiene su propio catálogo con su CRUD [2.3]. Propuestas del equipo: una historia por catálogo (D-17) y eliminar es inactivar (D-20). El CIE-10 tiene además la historia del médico que busca y elige un diagnóstico (HU-031). (Backlog v3, 2026-10-20) | C2: =COUNTIF(Historias!K:K,"*"&A2&"*") -> 16
A3: RC-2 | B3: Un dato que sale de un catálogo solo acepta valores activos de ese catálogo. (Backlog v3, 2026-10-20) | C3: =COUNTIF(Historias!K:K,"*"&A3&"*") -> 4
A4: RC-3 | B4: Los catálogos son los del anexo y los administra el Ministerio de Salud (artículos 6 y 8 de la Resolución 866); los prestadores no los pueden modificar, reducir ni adicionar (artículo 7). La IPS carga cada catálogo desde su archivo oficial, con su versión, y crea o actualiza un valor solo cuando cambia la fuente oficial (artículo 12). (Backlog v3, 2026-10-20) | C4: =COUNTIF(Historias!K:K,"*"&A4&"*") -> 8
A5: RC-4 | B5: Nada se borra. Un valor de catálogo se inactiva con su motivo (RC-10), la fecha, la hora y quién lo hizo; deja de ofrecerse para registros nuevos y los registros que ya lo usan lo conservan (D-20). (Backlog v3, 2026-10-20) | C5: =COUNTIF(Historias!K:K,"*"&A5&"*") -> 4
A6: RC-5 | B6: Toda acción queda atribuida a quien la hizo, con fecha y hora. La fecha y la hora las guarda cada historia; quién lo hizo lo agrega el inicio de sesión (HU-001, escenario 9). Lo que se registre antes de tenerlo queda sin autor. (Backlog v3, 2026-10-20) | C6: =COUNTIF(Historias!K:K,"*"&A6&"*") -> 12
A7: RC-6 | B7: Al corregir un dato mal registrado “se agregará el nuevo dato con la fecha, hora, nombre e identificación de quien hizo la corrección” (artículo 10, parágrafo 2). El dato anterior no se borra. (Backlog v3, 2026-10-20) | C7: =COUNTIF(Historias!K:K,"*"&A7&"*") -> 0
A8: RC-7 | B8: Cada dato se valida con los valores permitidos, el formato y la longitud de su numeral en el anexo. La tarjeta nombra el numeral y la hoja; no copia el formato. (Backlog v3, 2026-10-20) | C8: =COUNTIF(Historias!K:K,"*"&A8&"*") -> 0
A9: RC-8 | B9: Carga desde el archivo oficial: CSV en UTF-8 separado por punto y coma, con la fuente, la dirección y la fecha de descarga, y la versión y la fecha de publicación. El sistema busca por nombre las columnas que lista cada historia e ignora las demás; si el archivo viene en Excel, se guarda como CSV UTF-8 con los códigos como texto y, si las columnas tienen otros nombres, se cambia solo el encabezado (supuesto). El código es la clave y conserva sus ceros iniciales (D-18). Se rechaza el archivo si le falta una columna, y cada fila que no cumple su numeral o repite un código; un código de solo dígitos más corto que su numeral sale con el aviso de ceros perdidos. En ocupaciones y CIE-10, los niveles de arriba se validan con la regla de su historia. El sistema muestra filas leídas, aceptadas y rechazadas con su motivo; en la primera carga se guardan las aceptadas o se cancela todo, salvo en las listas del anexo (la hoja completa) y en las ocupaciones (cantidades por nivel). (Backlog v3, 2026-10-20) | C9: =COUNTIF(Historias!K:K,"*"&A9&"*") -> 0
A10: RC-9 | B10: Versión nueva, si la fecha de publicación es posterior a la vigente: el sistema muestra nuevos, cambios de nombre, inactivos que vuelven y retirados, avisa si deshace un cambio oficial posterior, deja anotar reemplazos y pide confirmar aparte las inactivaciones. Recarga, si la fecha es la misma: solo crea los códigos que faltan, sin inactivar nada. Rechazo, si es anterior o futura. El código de una fila rechazada conserva su nombre y su estado, y queda en la versión porque vino en su archivo (D-21). (Backlog v3, 2026-10-20) | C10: =COUNTIF(Historias!K:K,"*"&A10&"*") -> 0
A11: RC-10 | B11: Motivos de inactivación: Retirado por la fuente oficial, con referencia; Reemplazado por, con el código nuevo y la referencia; No está en la versión, que pone el sistema; Creado por error, solo para un código que no está en la versión vigente. Un código está en la versión vigente si vino en su archivo, aunque su fila se rechazara. Reactivar pide motivo; se reactiva lo que está en la versión vigente o lo que creó un cambio oficial posterior a ella; lo inactivado con referencia oficial se reactiva solo con otra referencia o diciendo por qué no lo retiraba. El conteo de uso incluye borradores y anuladas. (Backlog v3, 2026-10-20) | C11: =COUNTIF(Historias!K:K,"*"&A11&"*") -> 0
A12: RC-11 | B12: Un registro conserva el código y el nombre que tenía el valor el día en que se registró; si la fuente cambia el nombre después, su consulta muestra también el vigente (D-25). (Backlog v3, 2026-10-20) | C12: =COUNTIF(Historias!K:K,"*"&A12&"*") -> 0

Sheet Escenarios
A1: ID | B1: N.º | C1: Escenario | D1: Dado | E1: Y (contexto) | F1: Cuando | G1: Entonces | H1: Y (resultado) | I1: Nota
A2: HU-001 | B2: 1 | C2: Acceso con credenciales válidas | D2: que el auxiliar de admisión tiene credenciales asignadas | F2: se identifica con ellas | G2: el sistema le permite trabajar sobre la información de pacientes
